Workbook
Name Metas_DB: #REF!
Name Metas_Distribuidor: #REF!
Name Metas_GD: #REF!
Name Metas_Geral: #REF!
Name Metas_Hemocentro: #REF!
Name Metas_Indústria: #REF!
Name Metas_Inst: #REF!
Name Metas_Interno: #REF!
Name Metas_LabCorp: #REF!
Name Metas_LPC: #REF!

Sheet FatoOrçamento
A1: Ano | B1: Mês | C1: Tipo_de_despesa | D1: Vl_Planejado | E1: Centro de Custo
A2: 2025 | B2: 1 | C2: ALIMENTAÇÃO | D2: 8000 | E2: COMERCIAL
A3: 2025 | B3: 2 | C3: ALIMENTAÇÃO | D3: 8000 | E3: COMERCIAL
A4: 2025 | B4: 3 | C4: ALIMENTAÇÃO | D4: 8000 | E4: COMERCIAL
A5: 2025 | B5: 4 | C5: ALIMENTAÇÃO | D5: 8000 | E5: COMERCIAL
A6: 2025 | B6: 5 | C6: ALIMENTAÇÃO | D6: 8000 | E6: COMERCIAL
A7: 2025 | B7: 6 | C7: ALIMENTAÇÃO | D7: 8000 | E7: COMERCIAL
A8: 2025 | B8: 7 | C8: ALIMENTAÇÃO | D8: 8000 | E8: COMERCIAL
A9: 2025 | B9: 8 | C9: ALIMENTAÇÃO | D9: 8000 | E9: COMERCIAL
A10: 2025 | B10: 9 | C10: ALIMENTAÇÃO | D10: 8000 | E10: COMERCIAL
A11: 2025 | B11: 10 | C11: ALIMENTAÇÃO | D11: 8000 | E11: COMERCIAL
A12: 2025 | B12: 11 | C12: ALIMENTAÇÃO | D12: 8000 | E12: COMERCIAL
A13: 2025 | B13: 12 | C13: ALIMENTAÇÃO | D13: 8000 | E13: COMERCIAL
... A769: 2026 | B769: 12 | C769: PEDÁGIO | D769: 0 | E769: SUPRIMENTOS

Sheet dimTipoDespesa
A1: DS_TIPO_DESP_VIAGEM | B1: Ajustada
A2: AG1 HOSPEDAGEM | B2: HOSPEDAGEM
A3: AG1 LOCAÇÃO | B3: LOCAÇÃO
A4: AG1 PASSAGEM | B4: PASSAGEM
A5: ALIMENTAÇÃO - DNH | B5: ALIMENTAÇÃO
A6: ALIMENTAÇÃO - VISA/MASTERCARD | B6: ALIMENTAÇÃO
A7: ALIMENTAÇÃO CLIENTE - DNH | B7: ALIMENTAÇÃO
A8: ALIMENTAÇÃO CLIENTE - VISA/MASTERCARD | B8: ALIMENTAÇÃO
A9: ALIMENTAÇÃO FORNECEDOR - VISA/MASTERCARD | B9: ALIMENTAÇÃO
A10: COMBUSTÍVEL - DNH | B10: COMBUSTÍVEL
A11: COMBUSTÍVEL - VISA/MASTERCARD | B11: COMBUSTÍVEL
A12: CONDUÇÃO - DNH | B12: CONDUÇÃO
... A106: COMBUSTÍVEL - DNH | B106: COMBUSTÍVEL

Sheet dimColaborador
A1: COLABORADOR | B1: Cód. Colaborador | C1: SUB-REGIÃO | D1: CANAL | E1: Coluna1
A2: ALLYNE DE OLIVEIRA DYBAS DIAS | B2: 24246 | C2: CONSULTOR DESLIGADO | D2: CONSULTOR DESLIGADO
A3: AMANDA BRANCHER SCALON | B3: 8254 | C3: SUPERVISORA EXTERNA FIRSTLAB | D3: SUPERVISORA EXTERNA FIRSTLAB
A4: AMANDA CAROLINE PORRUA | B4: 25120 | C4: CONSULTOR DESLIGADO | D4: CONSULTOR DESLIGADO
A5: AMANDA FERREIRA MACHADO | B5: 25575 | C5: CONSULTOR DESLIGADO | D5: CONSULTOR DESLIGADO
A6: ANDERSON JUNIOR STOBBE | B6: 999999991 | C6: CONSULTOR DESLIGADO | D6: CONSULTOR DESLIGADO
A7: ANDREIA ANTONIA MACHADO HERNANI FERREIRA | B7: 24052 | C7: CONSULTOR DESLIGADO | D7: CONSULTOR DESLIGADO
A8: ARON DA ROSA FREITAS DE BORBA | B8: 999999992 | C8: CONSULTOR DESLIGADO | D8: CONSULTOR DESLIGADO
A9: ATHAYANE DA CUNHA CARNEIRO | B9: 24057 | C9: CONSULTOR DESLIGADO | D9: CONSULTOR DESLIGADO
A10: BEATRIZ FRANCIELE FERREIRA DOS SANTOS | B10: 23633 | C10: CONSULTOR DESLIGADO | D10: CONSULTOR DESLIGADO
A11: BRUNO MICKAEL BOHR DE OLIVEIRA | B11: 999999993 | C11: TÉCNICO E MANUTENÇÃO | D11: TÉCNICO E MANUTENÇÃO
A12: CAMILA MANFRINATTO | B12: 999999994 | C12: APOIO ADM | D12: APOIO ADM
A13: CAROLINE BRETAS GONCALVES DIAS | B13: 999999995 | C13: QUALIDADE | D13: QUALIDADE
... A38: ALLYNE DIAS | B38: 9999999918 | C38: DR - PRIME - SP | D38: DISTRIBUIDOR
A39: PABLO RODRIGUES DE SOUZA | B39: 9999999919
A40: ALISSON SAMPAIO DE LIMA | B40: 9999999921
A41: VITOR HUGO DE PAIVA SANTOS | B41: 9999999922
A42: PABLO RODRIGUES DE SOUZA | B42: 9999999923
A43: JULIANA FARIA GASPARIN | B43: 9999999924 | E43: Consultora
A44: LUCIANO DA SILVA LOPES | B44: 9999999925
A45: KATIA APARECIDA MARINHO NASCIMENTO | B45: 9999999926
A46: JULIANA FARIA GASPARIN | B46: 9999999927

Sheet dimCentroCusto
A1: Codigo_CentroCusto | B1: Centro_Custo
A2: 014 | B2: INATIVO
A3: 024 | B3: REGIÃO 2
A4: 025 | B4: REGIÃO 3
A5: 026 | B5: REGIÃO 4
A6: 027 | B6: REGIÃO 5
A7: 028 | B7: REGIÃO 6
A8: 029 | B8: COMPRAS
A9: 030 | B9: COMPRAS NACIONAIS
A10: 031 | B10: IMPORTAÇÃO
A11: 032 | B11: SUPRIMENTOS
A12: 033 | B12: MANUTENÇÃO
... A103: -1 | B103: NÃO PREENCHIDO

Sheet dimRepresentantesVendedores
A1: Código | B1: Número CNPJ/CPF | C1: Tipo Pessoa | D1: Nome | E1: Endereço | F1: Bairro | G1: Cidade | H1: Estado | I1: País | J1: Região | K1: Status | L1: Sub-Grupo | M1: Grupo | N1: Tipo | O1: EMAIL | P1: Código Supervisor | Q1: Nome Supervisor
A2: 1460 | B2: 008.331.301-02 | C2: FÍSICO | D2: 1460-RAPHAEL LEME CARNEIRO CESPEDES | E2: RUA ABRÃO CALIXTO | F2: ATUBA | G2: CURITIBA | H2: PR | J2: REGIÃO 01 | K2: ENCERRADO | L2: REGIÃO 01 | M2: CONSULTORES | N2: VENDEDOR
A3: 2230 | B3: 633.712.787-00 | C3: FÍSICO | D3: 2230-EDUARDO EUGÊNIO DE SOUZA MOURA | E3: PRAIA DE BOTAFOGO | F3: BOTAFOGO | G3: RIO DE JANEIRO | H3: RJ | J3: REGIÃO 01 | K3: ENCERRADO | L3: REGIÃO 03 | M3: CONSULTORES | N3: VENDEDOR
A4: 2680 | B4: 055.082.204-61 | C4: FÍSICO | D4: 2680-RODRIGO SANTANA MARTINS DA SILVA | E4: RUA MAITRE CATOLÉ | F4: VÁRZEA | G4: RECIFE | H4: PE | J4: REGIÃO 06 | K4: ENCERRADO | L4: REGIÃO 06 | M4: ASSESSORES | N4: VENDEDOR
A5: 2719 | B5: 006.556.729-31 | C5: FÍSICO | D5: 2719-DANIEL BELIN CAMARGO | E5: RUA MARIA VERÔNICA STROPARO | F5: SÃO BRAZ | G5: CURITIBA | H5: PR | J5: REGIÃO 01 | K5: ENCERRADO | L5: REGIÃO 01 | M5: ASSESSORES | N5: VENDEDOR
A6: 2856 | B6: 082.683.724-78 | C6: FÍSICO | D6: 2856-LAURA BENTO DOS SANTOS | E6: RUA PEDRO CONSTANTINO DA ROCHA | F6: AFONSO PENA | G6: SÃO JOSÉ DOS PINHAIS | H6: PR | J6: REGIÃO 06 | K6: ATIVO | L6: REGIÃO 06 | M6: ASSESSORES | N6: REPRESENTANTE | O6: laura.santos@firstlab.ind.br
A7: 3114 | B7: 080.112.336-45 | C7: FÍSICO | D7: 3114-ALESSANDRA DE CAMPOS MARTINS FONTES | E7: RUA SÍLVIO ANDRADE | F7: SERRANO | G7: BELO HORIZONTE | H7: MG | J7: REGIÃO 01 | K7: ENCERRADO | L7: REGIÃO 05 | M7: CONSULTORES | N7: VENDEDOR
A8: 3285 | B8: 034.884.179-56 | C8: FÍSICO | D8: 3285-ALEXANDRE JACOBUS LOPES | E8: RUA EMILE ZOLA | F8: LINDÓIA | G8: CURITIBA | H8: PR | J8: REGIÃO 01 | K8: ATIVO | L8: REGIÃO 01 | M8: CONSULTORES | N8: VENDEDOR
A9: 3950 | B9: 136.391.978-44 | C9: FÍSICO | D9: 3950-MARCIO UETA | E9: RUA ENGENHEIRO GUILHERME CRISTIANO FRENDER | F9: VILA ANTONIETA | G9: SÃO PAULO | H9: SP | J9: REGIÃO 01 | K9: ENCERRADO | L9: REGIÃO 06 | M9: ASSESSORES | N9: VENDEDOR
A10: 3954 | B10: 016.060.929-10 | C10: FÍSICO | D10: 3954-JACSON DE ALMEIDA POLICANTE | E10: RUA TAMBOARA | F10: CAPÃO DA IMBUIA | G10: CURITIBA | H10: PR | J10: REGIÃO 01 | K10: ENCERRADO | L10: GERAL | M10: CONSULTORES | N10: VENDEDOR
A11: 4268 | B11: 064.409.979-80 | C11: FÍSICO | D11: 4268-GUSTAVO MORETTO BARROS | E11: RUA MARECHAL OTÁVIO SALDANHA MAZZA | F11: CAPÃO RASO | G11: CURITIBA | H11: PR | J11: REGIÃO 01 | K11: ATIVO | L11: REGIÃO 01 | M11: CONSULTORES | N11: VENDEDOR
A12: 4566 | B12: 356.318.788-60 | C12: FÍSICO | D12: 4566-LETICIA DESAN DE GOES | E12: RUA JOSÉ FERREIRA KEFFER | F12: VILA PACÍFICO | G12: BAURU | H12: SP | J12: REGIÃO 01 | K12: ENCERRADO | L12: REGIÃO 02 | M12: CONSULTORES | N12: VENDEDOR
A13: 4567 | B13: 326.022.088-76 | C13: FÍSICO | D13: 4567-RENATA LENITA DA SILVA | E13: AVENIDA VITÓRIO BRIZANTE | F13: JARDIM ZAIRA | G13: MAUÁ | H13: SP | I13: BRASIL | J13: REGIÃO 03 | K13: ATIVO | L13: REGIÃO 03 | M13: CONSULTORES | N13: VENDEDOR
A14: 4608 | B14: 328.562.198-29 | C14: FÍSICO | D14: 4608-JULIANA OLIVI MALTA | E14: AVENIDA PROFESSOR JORGE CORRÊA | F14: CENTRO | G14: ARARAQUARA | H14: SP | J14: REGIÃO 01 | K14: ENCERRADO | L14: REGIÃO 02 | M14: CONSULTORES | N14: VENDEDOR
A15: 5310 | B15: 338.260.768-93 | C15: FÍSICO | D15: 5310-ARISLAINE GOMIERO NOGUEIRA | E15: RUA ANTENOR BORBA | F15: PARQUE LARANJEIRAS | G15: ARARAQUARA | H15: SP | J15: REGIÃO 01 | K15: ENCERRADO | L15: REGIÃO 02 | M15: CONSULTORES | N15: VENDEDOR
A16: 5311 | B16: 016.685.256-23 | C16: FÍSICO | D16: 5311-LEONARDO DE ASSIS ROSA | E16: RUA DEOLINDA CÂNDIDA | F16: BOA VISTA | G16: BELO HORIZONTE | H16: MG | J16: REGIÃO 01 | K16: ENCERRADO | L16: REGIÃO 05 | M16: CONSULTORES | N16: VENDEDOR
A17: 5312 | B17: 032.874.856-01 | C17: FÍSICO | D17: 5312-LUCIANA NOGUEIRA DUARTE | E17: RUA MANILA | F17: ESTRELA DALVA | G17: BELO HORIZONTE | H17: MG | J17: REGIÃO 01 | K17: ENCERRADO | L17: REGIÃO 05 | M17: CONSULTORES | N17: VENDEDOR
A18: 5507 | B18: 089.155.217-06 | C18: FÍSICO | D18: 5507-CHRISTIAN DOS SANTOS CHAGAS | E18: PRAÇA MARTINS LEÃO | F18: ALTO DA BOA VISTA | G18: RIO DE JANEIRO | H18: RJ | J18: REGIÃO 04 | K18: ENCERRADO | L18: REGIÃO 04 | M18: CONSULTORES | N18: VENDEDOR
A19: 5508 | B19: 105.253.097-48 | C19: FÍSICO | D19: 5508-DANIEL ALVES DA CUNHA | E19: AVENIDA SALVADOR ALLENDE | F19: RECREIO DOS BANDEIRANTES | G19: RIO DE JANEIRO | H19: RJ | J19: REGIÃO 04 | K19: ATIVO | L19: REGIÃO 04 | M19: CONSULTORES | N19: VENDEDOR
A20: 7463 | B20: 111.111.111-11 | C20: FÍSICO | D20: 7463-GERAL | G20: CURITIBA | H20: PR | K20: ATIVO | L20: TRIANGULO MINEIRO | M20: CONSULTORES | N20: VENDEDOR | P20: 26101 | Q20: SOEMIA DA SILVA ASSUNCAO
A21: 6789 | B21: 029.999.879-78 | C21: FÍSICO | D21: 6789-RICARDO CAUCA MARZCZAOKOSKI | E21: RUA BERNARDO BUBNIAK | F21: ATUBA | G21: CURITIBA | H21: PR | J21: REGIÃO 01 | K21: INATIVO | L21: REGIÃO 01 | M21: CONSULTORES | N21: VENDEDOR
A22: 6009 | B22: 175.472.548-10 | C22: FÍSICO | D22: 6009-FABIANA MATIOLI | E22: RUA MARACAJÚ | F22: VILA MONTE ALEGRE | G22: RIBEIRÃO PRETO | H22: SP | J22: REGIÃO 02 | K22: ENCERRADO | L22: REGIÃO 02 | M22: CONSULTORES | N22: VENDEDOR
A23: 1061 | B23: 013.374.288-17 | C23: FÍSICO | D23: 1061-ANDRE PAULO ZAJAC | E23: Rua DOUTOR ANTÔNIO MACEDO LIMA | F23: VILA LÚCIA | G23: SÃO PAULO | H23: SP | J23: REGIÃO 03 | K23: ENCERRADO | L23: REGIÃO 03 | M23: CONSULTORES | N23: VENDEDOR
A24: 5771 | B24: 060.036.656-10 | C24: FÍSICO | D24: 5771-LUCIANA CARDOSO DE ANDRADE | E24: RUA DONA CHIQUITA DE CASTRO | F24: BRAÚNAS | G24: BELO HORIZONTE | H24: MG | J24: REGIÃO 05 | K24: ENCERRADO | L24: REGIÃO 05 | M24: CONSULTORES | N24: VENDEDOR
A25: 8074 | B25: 036.339.709-40 | C25: FÍSICO | D25: 8074-ESLEI DE SOUZA XAVIER | E25: RUA CORONEL JOSÉ LEAL FONTOURA | F25: XAXIM | G25: CURITIBA | H25: PR | K25: INATIVO | L25: REGIÃO 01 | M25: CONSULTORES | N25: VENDEDOR
A26: 8148 | B26: 085.722.519-79 | C26: FÍSICO | D26: 8148-CASSIA GABRIELI LOURENÇO | E26: RUA LILIAN VIANA DE ARAÚJO | F26: CIDADE JARDIM | G26: SÃO JOSÉ DOS PINHAIS | H26: PR | J26: REGIÃO 04 | K26: INATIVO | L26: REGIÃO 03 | M26: CONSULTORES | N26: VENDEDOR | O26: cassia.lourenco@firstlab.ind.br | P26: 26101 | Q26: SOEMIA DA SILVA ASSUNCAO
A27: 8218 | B27: 055.928.624-40 | C27: FÍSICO | D27: 8218-LUDHIMILLA GOMES LINS DE LIMA | E27: AVENIDA PINHEIROS | F27: IMBIRIBEIRA | G27: RECIFE | H27: PE | K27: INATIVO | L27: REGIÃO 06 | M27: ASSESSORES | N27: REPRESENTANTE | O27: ludhimilla.lima@firstlab.ind.br
A28: 8254 | B28: 103.939.409-42 | C28: FÍSICO | D28: 8254-AMANDA BRANCHER SCALON | E28: RUA ROSA SAHAGOFF | F28: UBERABA | G28: CURITIBA | H28: PR | J28: REGIÃO 01 | K28: ATIVO | L28: REGIÃO 02 | M28: CONSULTORES | N28: REPRESENTANTE | O28: amanda.scalon@firstlab.ind.br
A29: 8260 | B29: 066.162.129-47 | C29: FÍSICO | D29: 8260-GABRIELLI SCHAFAUSER | E29: RUA OTÁVIO CLAUDINO DE CAMARGO | F29: CRUZEIRO | G29: SÃO JOSÉ DOS PINHAIS | H29: PR | J29: SEM VINCULO C/ REGIÕES | K29: ATIVO | L29: GERAL | M29: CONSULTORES | N29: VENDEDOR | O29: gabrielli.schafauser@firstlab.ind.br | P29: 26101 | Q29: SOEMIA DA SILVA ASSUNCAO
A30: 6242 | B30: 043.070.634-06 | C30: FÍSICO | D30: 6242-GILCLEYA FELIX DE ASSIS | E30: RUA DOUTOR ORLANDO CABRAL | F30: CENTRO | G30: JABOATÃO DOS GUARARAPES | H30: PE | J30: REGIÃO 06 | K30: ENCERRADO | L30: REGIÃO 06 | M30: ASSESSORES | N30: VENDEDOR
A31: 8494 | B31: 660.708.306-44 | C31: FÍSICO | D31: 8494-CHRISTIANO RIZZI TYMBURIBA | E31: RUA DÁLIA - BAIRRO SANTO ANDRE | F31: PEDRO II | G31: BELO HORIZONTE | H31: MG | J31: REGIÃO 05 | K31: INATIVO | L31: REGIÃO 05 | M31: CONSULTORES | N31: VENDEDOR | P31: 151 | Q31: GERAL
A32: 8495 | B32: 044.598.257-83 | C32: FÍSICO | D32: 8495-DANIEL GONÇALVES DE FREITAS | E32: RUA AMOROSO LIMA | F32: CIDADE NOVA | G32: RIO DE JANEIRO | H32: RJ | J32: REGIÃO 04 | K32: INATIVO | L32: REGIÃO 04 | M32: CONSULTORES | N32: VENDEDOR
A33: 8545 | B33: 041.492.339-18 | C33: FÍSICO | D33: 8545-GEOVANA BROTTO RAMOS | E33: RUA PADRE MANUEL DA NÓBREGA | F33: FANNY | G33: CURITIBA | H33: PR | I33: BRASIL | K33: INATIVO | L33: REGIÃO 01 | M33: CONSULTORES | N33: VENDEDOR | P33: 151 | Q33: GERAL
A34: 8571 | B34: 115.870.847-59 | C34: FÍSICO | D34: 8571-TATIANA DI BLASI | E34: RUA DA REPÚBLICA | F34: QUINTINO BOCAIÚVA | G34: RIO DE JANEIRO | H34: RJ | J34: REGIÃO 04 | K34: ENCERRADO | L34: REGIÃO 04 | M34: CONSULTORES | N34: VENDEDOR | O34: tatiana.blasi@kasvi.com.br | P34: 151 | Q34: GERAL
A35: 8572 | B35: 274.267.168-48 | C35: FÍSICO | D35: 8572-BIANCA BRAGATO | E35: RUA ANDRÉA DEL SARTO | F35: TREMEMBÉ | G35: SÃO PAULO | H35: SP | J35: REGIÃO 03 | K35: ENCERRADO | L35: REGIÃO 03 | M35: CONSULTORES | N35: VENDEDOR
A36: 8573 | B36: 039.568.536-28 | C36: FÍSICO | D36: 8573-THIAGO PEREIRA PIRES | E36: RUA JOSE BRAZ DA COSTA VIDAL | F36: CENTRO | G36: VIÇOSA | H36: MG | J36: REGIÃO 05 | K36: ENCERRADO | L36: REGIÃO 05 | M36: CONSULTORES | N36: REPRESENTANTE
A37: 6016 | B37: 319.550.688-28 | C37: FÍSICO | D37: 6016-ANDERSON ANTONIO VILELA SILVEIRA | E37: RUA MARECHAL FLORIANO PEIXOTO | F37: CENTRO | G37: PIRANGI | H37: SP | J37: REGIÃO 02 | K37: INATIVO | L37: REGIÃO 02 | M37: CONSULTORES | N37: VENDEDOR
A38: 8756 | B38: 298.515.208-96 | C38: FÍSICO | D38: 8756-ALESSANDRA FRANCO NEOPICHANOW | E38: RUA CAETANÓPOLIS | F38: JAGUARÉ | G38: SÃO PAULO | H38: SP | K38: ENCERRADO | L38: REGIÃO 02 | M38: CONSULTORES | N38: VENDEDOR | O38: alessandra.franco@firstlab.com.br
A39: 5556 | B39: 064.265.296-13 | C39: FÍSICO | D39: 5556-VITOR ALVES VIGGIANO | E39: RUA DOUTOR JARBAS VIDAL GOMES | F39: CIDADE NOVA | G39: BELO HORIZONTE | H39: MG | J39: REGIÃO 05 | K39: ENCERRADO | L39: REGIÃO 05 | M39: CONSULTORES | N39: VENDEDOR
A40: 8830 | B40: 072.885.546-19 | C40: FÍSICO | D40: 8830-DANIEL FELLIPE FILGUEIRAS ARAUJO | E40: MARTINIANO DE CARVALHO | F40: BELA VISTA | G40: SÃO PAULO | H40: SP | J40: REGIÃO 03 | K40: ENCERRADO | L40: REGIÃO 03 | M40: CONSULTORES | N40: VENDEDOR | O40: daniel.araujo@kasvi.com.br
A41: 8831 | B41: 384.724.388-80 | C41: FÍSICO | D41: 8831-PRISCILA DONATO PACCI | E41: RUA THOMAS NILSEN JÚNIOR | F41: PARQUE IMPERADOR | G41: CAMPINAS | H41: SP | J41: REGIÃO 03 | K41: INATIVO | L41: REGIÃO 02 | M41: CONSULTORES | N41: REPRESENTANTE | O41: priscila.pacci@firstlab.ind.br
A42: 8933 | B42: 096.780.056-03 | C42: FÍSICO | D42: 8933-ISADORA VALADAO DOMINGUES | E42: RUA PROFESSOR BENEDITO FONSECA | F42: FERNÃO DIAS | G42: BELO HORIZONTE | H42: MG | J42: REGIÃO 05 | K42: ENCERRADO | L42: REGIÃO 05 | M42: CONSULTORES | N42: VENDEDOR | O42: ivaladao@hotmail.com
A43: 8934 | B43: 178.548.458-32 | C43: FÍSICO | D43: 8934-FABIANA LUCENA DE LIMA | E43: AVENIDA MANOEL RIBAS | F43: MERCÊS | G43: CURITIBA | H43: PR | K43: ENCERRADO | L43: GERAL | M43: CONSULTORES | N43: VENDEDOR | O43: fabiana.lima@kasvi.com.br
A44: 9157 | B44: 093.311.089-82 | C44: FÍSICO | D44: 9157-YOHANA DOS SANTOS | E44: AVENIDA RUI BARBOSA | F44: BONECA DO IGUAÇU | G44: SÃO JOSÉ DOS PINHAIS | H44: PR | K44: INATIVO | L44: GERAL | M44: CONSULTORES | N44: REPRESENTANTE | O44: yohana.santos@kasvi.com.br
A45: 9176 | B45: 987.159.648-09 | C45: FÍSICO | D45: 9176-CHRISTIAN SCHWARZ | E45: RUA MARIA JABOATÃO | G45: RECIFE | H45: PE | K45: INATIVO | L45: GERAL | M45: CONSULTORES | N45: GERENTE | O45: christian.schwarz@dbdiagnosticos.com.br
A46: 9177 | B46: 873.916.831-08 | C46: FÍSICO | D46: 9177-BRUNO DIAS | E46: RUA DOUTOR FELIPE UEBE | F46: PARQUE CALIFÓRNIA | G46: CAMPOS DOS GOYTACAZES | H46: RJ | K46: ENCERRADO | L46: GERAL | M46: CONSULTORES | N46: SUPERVISOR
A47: 9178 | B47: 074.802.264-38 | C47: FÍSICO | D47: 9178-GUSTAVO MORAES | E47: RUA MANOEL DOS SANTOS CORRÊA | F47: PITANGUEIRAS | G47: LAURO DE FREITAS | H47: BA | K47: INATIVO | L47: GERAL | M47: CONSULTORES | N47: SUPERVISOR
A48: 9179 | B48: 711.923.364-53 | C48: FÍSICO | D48: 9179-ANTONINO MELO | E48: AV. AVENIDA SUL GOV. CID SAMPAIO | F48: IMBIRIBEIRA | G48: RECIFE | H48: PE | K48: ENCERRADO | L48: GERAL | M48: CONSULTORES | N48: SUPERVISOR
A49: 9180 | B49: 412.731.116-99 | C49: FÍSICO | D49: 9180-STEPHENSON VERAS | E49: AV. AVENIDA SUL GOV. CID SAMPAIO | F49: IMBIRIBEIRA | G49: RECIFE | H49: PE | K49: ENCERRADO | L49: GERAL | M49: CONSULTORES | N49: SUPERVISOR
A50: 9181 | B50: 318.185.194-96 | C50: FÍSICO | D50: 9181-CARINE DA SILVA FREITAS | E50: RUA MARIA JABOATÃO | G50: RECIFE | H50: PE | K50: ENCERRADO | L50: GERAL | M50: CONSULTORES | N50: SUPERVISOR
A51: 9182 | B51: 831.145.231-88 | C51: FÍSICO | D51: 9182-JANETE NÉVIA DE GODOY | E51: RUA MARIA JABOATÃO | G51: RECIFE | H51: PE | K51: INATIVO | L51: GERAL | M51: CONSULTORES | N51: GERENTE | O51: janete.godoy@dbdiagnosticos.com.br
A52: 9183 | B52: 185.864.732-00 | C52: FÍSICO | D52: 9183-VALDI E. MELO JUNIOR | E52: RUA MARIA JABOATÃO | G52: RECIFE | H52: PE | K52: INATIVO | L52: GERAL | M52: CONSULTORES | N52: GERENTE | O52: valdi.melo@dbdiagnosticos.com.br
A53: 9184 | B53: 584.354.382-01 | C53: FÍSICO | D53: 9184-JULIO MARCOS DE ALMEIDA CRUZ | E53: RUA MARIA JABOATÃO | F53: VÁRZEA | G53: RECIFE | H53: PE | K53: INATIVO | L53: GERAL | M53: CONSULTORES | N53: SUPERVISOR | O53: juliomarcos.cruz@dbdiagnosticos.com.br
A54: 9185 | B54: 543.651.985-72 | C54: FÍSICO | D54: 9185-CARLOS HENRIQUE | E54: RUA MARIA JABOATÃO | F54: VÁRZEA | G54: RECIFE | H54: PE | K54: ENCERRADO | L54: GERAL | M54: CONSULTORES | N54: REPRESENTANTE | P54: 9176 | Q54: CHRISTIAN SCHWARZ
A55: 9186 | B55: 663.566.082-85 | C55: FÍSICO | D55: 9186-FABIO DILLMANN | E55: RUA MARIA JABOATÃO | G55: RECIFE | H55: PE | K55: ATIVO | L55: GERAL | M55: CONSULTORES | N55: REPRESENTANTE | P55: 9176 | Q55: CHRISTIAN SCHWARZ
A56: 9187 | B56: 574.278.665-41 | C56: FÍSICO | D56: 9187-JARI GUILHERME | E56: RUA MARIA JABOATÃO | G56: RECIFE | H56: PE | K56: ENCERRADO | L56: GERAL | M56: CONSULTORES | N56: REPRESENTANTE | P56: 9176 | Q56: CHRISTIAN SCHWARZ
A57: 9188 | B57: 235.725.672-97 | C57: FÍSICO | D57: 9188-LUCIANO FERRONATTO | E57: RUA MARIA JABOATÃO | G57: RECIFE | H57: PE | K57: ENCERRADO | L57: GERAL | M57: CONSULTORES | N57: REPRESENTANTE | P57: 9176 | Q57: CHRISTIAN SCHWARZ
A58: 9189 | B58: 444.386.284-66 | C58: FÍSICO | D58: 9189-MORGANA RAYCIK | E58: RUA MARIA JABOATÃO | G58: RECIFE | H58: PE | K58: ENCERRADO | L58: GERAL | M58: CONSULTORES | N58: REPRESENTANTE | P58: 9176 | Q58: CHRISTIAN SCHWARZ
A59: 9190 | B59: 371.568.845-90 | C59: FÍSICO | D59: 9190-NILO JESUS RODRIGUES SOARES | E59: RUA MARIA JABOATÃO | G59: RECIFE | H59: PE | K59: ENCERRADO | L59: GERAL | M59: CONSULTORES | N59: REPRESENTANTE | P59: 9176 | Q59: CHRISTIAN SCHWARZ
A60: 9191 | B60: 671.583.378-80 | C60: FÍSICO | D60: 9191-PAULO UMBELINO | E60: RUA MARIA JABOATÃO | G60: RECIFE | H60: PE | K60: ENCERRADO | L60: GERAL | M60: CONSULTORES | N60: REPRESENTANTE | P60: 9176 | Q60: CHRISTIAN SCHWARZ
A61: 9192 | B61: 164.168.695-27 | C61: FÍSICO | D61: 9192-SANDRA JACOBS | E61: RUA MARIA JABOATÃO | G61: RECIFE | H61: PE | K61: ENCERRADO | L61: GERAL | M61: CONSULTORES | N61: REPRESENTANTE | P61: 9176 | Q61: CHRISTIAN SCHWARZ
A62: 9193 | B62: 800.736.488-92 | C62: FÍSICO | D62: 9193-TIAGO KASPER | E62: RUA MARIA JABOATÃO | G62: RECIFE | H62: PE | K62: ENCERRADO | L62: GERAL | M62: CONSULTORES | N62: REPRESENTANTE | P62: 9176 | Q62: CHRISTIAN SCHWARZ
A63: 9194 | B63: 548.165.773-27 | C63: FÍSICO | D63: 9194-CRISTIANO GONÇALVES | E63: RUA MARIA JABOATÃO | F63: VÁRZEA | G63: RECIFE | H63: PE | K63: ENCERRADO | L63: GERAL | M63: CONSULTORES | N63: REPRESENTANTE | P63: 9184 | Q63: JULIO MARCOS DE ALMEIDA CRUZ
A64: 9195 | B64: 381.612.055-58 | C64: FÍSICO | D64: 9195-LUCIANO VIANA | E64: RUA MARIA JABOATÃO | G64: RECIFE | H64: PE | K64: ENCERRADO | L64: GERAL | M64: CONSULTORES | N64: REPRESENTANTE | P64: 9184 | Q64: JULIO MARCOS DE ALMEIDA CRUZ
A65: 9196 | B65: 376.225.834-13 | C65: FÍSICO | D65: 9196-LUIS EDUARDO | E65: RUA MARIA JABOATÃO | G65: RECIFE | H65: PE | K65: ENCERRADO | L65: GERAL | M65: CONSULTORES | N65: REPRESENTANTE | P65: 9184 | Q65: JULIO MARCOS DE ALMEIDA CRUZ
A66: 9197 | B66: 638.570.134-43 | C66: FÍSICO | D66: 9197-ISRAEL MOREIRA | E66: RUA MARIA JABOATÃO | G66: RECIFE | H66: PE | K66: ENCERRADO | L66: GERAL | M66: CONSULTORES | N66: REPRESENTANTE | P66: 9184 | Q66: JULIO MARCOS DE ALMEIDA CRUZ
A67: 9198 | B67: 533.336.547-41 | C67: FÍSICO | D67: 9198-MARCO FORTES | E67: RUA MARIA JABOATÃO | G67: RECIFE | H67: PE | K67: ENCERRADO | L67: GERAL | M67: CONSULTORES | N67: REPRESENTANTE | P67: 9184 | Q67: JULIO MARCOS DE ALMEIDA CRUZ
A68: 9199 | B68: 431.589.452-40 | C68: FÍSICO | D68: 9199-RANIERI SEIDI | E68: RUA MARIA JABOATÃO | G68: RECIFE | H68: PE | K68: ENCERRADO | L68: GERAL | M68: CONSULTORES | N68: REPRESENTANTE | P68: 9184 | Q68: JULIO MARCOS DE ALMEIDA CRUZ
A69: 9200 | B69: 214.084.865-98 | C69: FÍSICO | D69: 9200-RODRIGO FERNANDO | E69: RUA MARIA JABOATÃO | G69: RECIFE | H69: PE | K69: ENCERRADO | L69: GERAL | M69: CONSULTORES | N69: REPRESENTANTE | P69: 9184 | Q69: JULIO MARCOS DE ALMEIDA CRUZ
A70: 9201 | B70: 943.279.395-87 | C70: FÍSICO | D70: 9201-CARLOS EDUARDO CORREIA | E70: RUA MARIA JABOATÃO | F70: VÁRZEA | G70: RECIFE | H70: PE | K70: ENCERRADO | L70: GERAL | M70: CONSULTORES | N70: REPRESENTANTE | P70: 9183 | Q70: VALDI E. MELO JUNIOR
A71: 9202 | B71: 582.243.277-87 | C71: FÍSICO | D71: 9202-CLEBER CASSIO | E71: RUA MARIA JABOATÃO | G71: RECIFE | H71: PE | K71: ENCERRADO | L71: GERAL | M71: CONSULTORES | N71: REPRESENTANTE | P71: 9183 | Q71: VALDI E. MELO JUNIOR
A72: 9203 | B72: 272.316.539-60 | C72: FÍSICO | D72: 9203-DAVID CARVALHO | E72: RUA MARIA JABOATÃO | G72: RECIFE | H72: PE | K72: ENCERRADO | L72: GERAL | M72: CONSULTORES | N72: REPRESENTANTE | P72: 9183 | Q72: VALDI E. MELO JUNIOR
A73: 9204 | B73: 988.485.359-25 | C73: FÍSICO | D73: 9204-GILSON PAIXÃO | E73: RUA MARIA JABOATÃO | G73: RECIFE | H73: PE | K73: ENCERRADO | L73: GERAL | M73: CONSULTORES | N73: REPRESENTANTE | P73: 9183 | Q73: VALDI E. MELO JUNIOR
A74: 9205 | B74: 757.804.373-00 | C74: FÍSICO | D74: 9205-GUARACI MONTEIRO | E74: RUA MARIA JABOATÃO | G74: RECIFE | H74: PE | K74: ENCERRADO | L74: GERAL | M74: CONSULTORES | N74: REPRESENTANTE | P74: 9183 | Q74: VALDI E. MELO JUNIOR
A75: 9206 | B75: 844.963.453-90 | C75: FÍSICO | D75: 9206-HILÁRIO SIDNEI | E75: RUA MARIA JABOATÃO | G75: RECIFE | H75: PE | K75: ENCERRADO | L75: GERAL | M75: CONSULTORES | N75: REPRESENTANTE | P75: 9183 | Q75: VALDI E. MELO JUNIOR
A76: 9207 | B76: 614.885.852-53 | C76: FÍSICO | D76: 9207-MARO MARTINEZ | E76: RUA MARIA JABOATÃO | G76: RECIFE | H76: PE | K76: ENCERRADO | L76: GERAL | M76: CONSULTORES | N76: REPRESENTANTE | P76: 9183 | Q76: VALDI E. MELO JUNIOR
A77: 9208 | B77: 751.222.848-14 | C77: FÍSICO | D77: 9208-ORESTES DIAS | E77: RUA MARIA JABOATÃO | G77: RECIFE | H77: PE | K77: ENCERRADO | L77: GERAL | M77: CONSULTORES | N77: REPRESENTANTE | P77: 9183 | Q77: VALDI E. MELO JUNIOR
A78: 9209 | B78: 672.457.075-10 | C78: FÍSICO | D78: 9209-PLINIO MARCOS DE AZEVEDO | E78: RUA MARIA JABOATÃO | G78: RECIFE | H78: PE | K78: ENCERRADO | L78: GERAL | M78: CONSULTORES | N78: REPRESENTANTE | P78: 9183 | Q78: VALDI E. MELO JUNIOR
A79: 9210 | B79: 368.375.984-49 | C79: FÍSICO | D79: 9210-ARNALDO FIGUEIREDO | E79: RUA ITAÍ | F79: SANTA EFIGÊNIA | G79: BELO HORIZONTE | H79: MG | K79: ENCERRADO | L79: GERAL | M79: CONSULTORES | N79: REPRESENTANTE
A80: 9211 | B80: 476.117.511-74 | C80: FÍSICO | D80: 9211-HERLY DE MELO RODRIGUES | E80: RUA MARIA JABOATÃO ' | G80: RECIFE | H80: PE | K80: ENCERRADO | L80: GERAL | M80: CONSULTORES | N80: REPRESENTANTE | P80: 9181 | Q80: CARINE DA SILVA FREITAS
A81: 9212 | B81: 428.764.557-06 | C81: FÍSICO | D81: 9212-KATHIUSCIA SILVA FREITAS | E81: RUA MARIA JABOATÃO | G81: RECIFE | H81: PE | K81: ENCERRADO | L81: GERAL | M81: CONSULTORES | N81: REPRESENTANTE
A82: 9213 | B82: 537.625.375-93 | C82: FÍSICO | D82: 9213-RAFAEL GOMES | E82: RUA MARIA JABOATÃO | G82: RECIFE | H82: PE | K82: ENCERRADO | L82: GERAL | M82: CONSULTORES | N82: REPRESENTANTE
A83: 9214 | B83: 427.442.649-11 | C83: FÍSICO | D83: 9214-RODNEY NUNES | E83: RUA MARIA JABOATÃO | G83: RECIFE | H83: PE | K83: ENCERRADO | L83: GERAL | M83: CONSULTORES | N83: REPRESENTANTE | P83: 9181 | Q83: CARINE DA SILVA FREITAS
A84: 9215 | B84: 720.465.474-97 | C84: FÍSICO | D84: 9215-THAYNARA MARQUES GANDRA PARREIRAS | E84: RUA MARIA JABOATÃO | G84: RECIFE | H84: PE | K84: ENCERRADO | L84: GERAL | M84: CONSULTORES | N84: REPRESENTANTE | P84: 9181 | Q84: CARINE DA SILVA FREITAS
A85: 9216 | B85: 810.637.597-81 | C85: FÍSICO | D85: 9216-RODRIGO MARCELL | E85: RUA MARIA JABOATÃO | F85: VÁRZEA | G85: RECIFE | H85: PE | K85: ENCERRADO | L85: GERAL | M85: CONSULTORES | N85: REPRESENTANTE | P85: 9181 | Q85: CARINE DA SILVA FREITAS
A86: 9217 | B86: 710.322.644-03 | C86: FÍSICO | D86: 9217-ANDRÉ FERREIRA | E86: RUA CRUZ ALTA | F86: JARDIM NOVO MUNDO | G86: GOIÂNIA | H86: GO | K86: ENCERRADO | L86: GERAL | M86: CONSULTORES | N86: REPRESENTANTE | P86: 9182 | Q86: JANETE NÉVIA DE GODOY
A87: 9218 | B87: 128.247.438-32 | C87: FÍSICO | D87: 9218-ANDRÉ VIEIRA | E87: RUA ANDRÉ ROCHA, 372 | F87: TAQUARA | G87: RIO DE JANEIRO | H87: RJ | K87: ENCERRADO | L87: GERAL | M87: CONSULTORES | N87: REPRESENTANTE | P87: 9177 | Q87: BRUNO DIAS
A88: 9219 | B88: 628.127.122-01 | C88: FÍSICO | D88: 9219-CAMILA GRAÇA | E88: RUA SANTA ROSA- lado ímpar | F88: SANTA ROSA | G88: NITERÓI | H88: RJ | K88: ENCERRADO | L88: GERAL | M88: CONSULTORES | N88: REPRESENTANTE | P88: 9177 | Q88: BRUNO DIAS
A89: 9220 | B89: 643.655.094-11 | C89: FÍSICO | D89: 9220-CARLOS ADRIANO | G89: RECIFE | H89: PE | K89: ENCERRADO | L89: GERAL | M89: CONSULTORES | N89: REPRESENTANTE | P89: 9177 | Q89: BRUNO DIAS
A90: 9221 | B90: 657.215.767-90 | C90: FÍSICO | D90: 9221-DAVI HECKERT | G90: RECIFE | H90: PE | K90: ENCERRADO | L90: GERAL | M90: CONSULTORES | N90: REPRESENTANTE | P90: 9177 | Q90: BRUNO DIAS
A91: 9222 | B91: 535.437.465-02 | C91: FÍSICO | D91: 9222-DOUGLAS NARCISO | G91: RECIFE | H91: PE | K91: ENCERRADO | L91: GERAL | M91: CONSULTORES | N91: REPRESENTANTE | P91: 9177 | Q91: BRUNO DIAS
A92: 9223 | B92: 248.532.168-04 | C92: FÍSICO | D92: 9223-LUCAS NOBREGA MORGADO | G92: RECIFE | H92: PE | K92: ENCERRADO | L92: GERAL | M92: CONSULTORES | N92: REPRESENTANTE | P92: 9177 | Q92: BRUNO DIAS
A93: 9224 | B93: 052.719.242-20 | C93: FÍSICO | D93: 9224-RODRIGO VERVLOET | G93: RECIFE | H93: PE | K93: ENCERRADO | L93: GERAL | M93: CONSULTORES | N93: REPRESENTANTE | P93: 9177 | Q93: BRUNO DIAS
A94: 9225 | B94: 422.654.731-46 | C94: FÍSICO | D94: 9225-WILSON MARTINS | G94: RECIFE | H94: PE | K94: ENCERRADO | L94: GERAL | M94: CONSULTORES | N94: REPRESENTANTE | P94: 9177 | Q94: BRUNO DIAS
A95: 9226 | B95: 243.153.371-96 | C95: FÍSICO | D95: 9226-ARIANY BORGES | E95: RUA ALEGRETE | F95: CORONEL ANTONINO | G95: CAMPO GRANDE | H95: MS | K95: ENCERRADO | L95: GERAL | M95: CONSULTORES | N95: REPRESENTANTE | P95: 9182 | Q95: JANETE NÉVIA DE GODOY
A96: 9227 | B96: 511.409.270-78 | C96: FÍSICO | D96: 9227-BEATRIZ BARBOSA GOMES | E96: RUA 02 | F96: CENTRO | G96: PORTO NACIONAL | H96: TO | K96: ENCERRADO | L96: GERAL | M96: CONSULTORES | N96: REPRESENTANTE | P96: 9182 | Q96: JANETE NÉVIA DE GODOY
A97: 9228 | B97: 351.587.195-00 | C97: FÍSICO | D97: 9228-FERNANDA PIAZZA | G97: RECIFE | H97: PE | K97: ENCERRADO | L97: GERAL | M97: CONSULTORES | N97: REPRESENTANTE | P97: 9182 | Q97: JANETE NÉVIA DE GODOY
A98: 9229 | B98: 200.804.897-70 | C98: FÍSICO | D98: 9229-GILBERTO RABELO | G98: RECIFE | H98: PE | K98: ENCERRADO | L98: GERAL | M98: CONSULTORES | N98: REPRESENTANTE | P98: 9182 | Q98: JANETE NÉVIA DE GODOY
A99: 9230 | B99: 414.343.262-50 | C99: FÍSICO | D99: 9230-JULIANA SIRIO | G99: RECIFE | H99: PE | K99: ENCERRADO | L99: GERAL | M99: CONSULTORES | N99: REPRESENTANTE | P99: 9182 | Q99: JANETE NÉVIA DE GODOY
A100: 9231 | B100: 568.022.652-90 | C100: FÍSICO | D100: 9231-KEISY DANTAS | G100: RECIFE | H100: PE | K100: ENCERRADO | L100: GERAL | M100: CONSULTORES | N100: REPRESENTANTE | P100: 9182 | Q100: JANETE NÉVIA DE GODOY
...

Sheet VW_RelatorioViagensDesoesasCola
A1: DT_DESPESA | B1: NR_VIAGEM | C1: CD_ENTIDADE_FUNC | D1: NM_RAZAOSOC | E1: CD_CENTROCUSTO | F1: DS_CENTROCUSTO | G1: CD_PROJETO | H1: DS_PROJETO | I1: CD_TIPO_DESP_VIAGEM | J1: DS_TIPO_DESP_VIAGEM | K1: nr_despesa | L1: VR_DESPESA | M1: FG_SITUACAO | N1: CLIENTE
A2: 46024 | B2: 2400 | C2: 26136 | D2: JOANA MARIA TEIXEIRA DE OLIVEIRA | E2: 048 | F2: COMERCIAL | G2: 160 | H2: NA - NÃO POSSUI PROJETO | I2: 18 | J2: ALIMENTAÇÃO | K2: 1 | L2: 46.8 | M2: CON | N2: FIRSTLAB INDUSTRIA IMP E EXP DE PROD PARA LABS LTD
A3: 46024 | B3: 2400 | C3: 26136 | D3: JOANA MARIA TEIXEIRA DE OLIVEIRA | E3: 048 | F3: COMERCIAL | G3: 160 | H3: NA - NÃO POSSUI PROJETO | I3: 18 | J3: ALIMENTAÇÃO | K3: 2 | L3: 19.9 | M3: CON | N3: FIRSTLAB INDUSTRIA IMP E EXP DE PROD PARA LABS LTD
A4: 46024 | B4: 2400 | C4: 26136 | D4: JOANA MARIA TEIXEIRA DE OLIVEIRA | E4: 048 | F4: COMERCIAL | G4: 160 | H4: NA - NÃO POSSUI PROJETO | I4: 18 | J4: ALIMENTAÇÃO | K4: 3 | L4: 54.4 | M4: CON | N4: FIRSTLAB INDUSTRIA IMP E EXP DE PROD PARA LABS LTD
A5: 46024 | B5: 2400 | C5: 26136 | D5: JOANA MARIA TEIXEIRA DE OLIVEIRA | E5: 048 | F5: COMERCIAL | G5: 160 | H5: NA - NÃO POSSUI PROJETO | I5: 18 | J5: ALIMENTAÇÃO | K5: 4 | L5: 54.9 | M5: CON | N5: FIRSTLAB INDUSTRIA IMP E EXP DE PROD PARA LABS LTD
A6: 46024 | B6: 2400 | C6: 26136 | D6: JOANA MARIA TEIXEIRA DE OLIVEIRA | E6: 048 | F6: COMERCIAL | G6: 160 | H6: NA - NÃO POSSUI PROJETO | I6: 18 | J6: ALIMENTAÇÃO | K6: 6 | L6: 39.9 | M6: CON | N6: FIRSTLAB INDUSTRIA IMP E EXP DE PROD PARA LABS LTD
A7: 46024 | B7: 2400 | C7: 26136 | D7: JOANA MARIA TEIXEIRA DE OLIVEIRA | E7: 048 | F7: COMERCIAL | G7: 160 | H7: NA - NÃO POSSUI PROJETO | I7: 18 | J7: ALIMENTAÇÃO | K7: 7 | L7: 17 | M7: CON | N7: FIRSTLAB INDUSTRIA IMP E EXP DE PROD PARA LABS LTD
A8: 46024 | B8: 2400 | C8: 26136 | D8: JOANA MARIA TEIXEIRA DE OLIVEIRA | E8: 048 | F8: COMERCIAL | G8: 160 | H8: NA - NÃO POSSUI PROJETO | I8: 18 | J8: ALIMENTAÇÃO | K8: 9 | L8: 75.87 | M8: CON | N8: FIRSTLAB INDUSTRIA IMP E EXP DE PROD PARA LABS LTD
A9: 46024 | B9: 2400 | C9: 26136 | D9: JOANA MARIA TEIXEIRA DE OLIVEIRA | E9: 048 | F9: COMERCIAL | G9: 160 | H9: NA - NÃO POSSUI PROJETO | I9: 18 | J9: ALIMENTAÇÃO | K9: 13 | L9: 41.2 | M9: CON | N9: FIRSTLAB INDUSTRIA IMP E EXP DE PROD PARA LABS LTD
A10: 46024 | B10: 2400 | C10: 26136 | D10: JOANA MARIA TEIXEIRA DE OLIVEIRA | E10: 048 | F10: COMERCIAL | G10: 160 | H10: NA - NÃO POSSUI PROJETO | I10: 18 | J10: ALIMENTAÇÃO | K10: 14 | L10: 85.5 | M10: CON | N10: FIRSTLAB INDUSTRIA IMP E EXP DE PROD PARA LABS LTD
A11: 46024 | B11: 2400 | C11: 26136 | D11: JOANA MARIA TEIXEIRA DE OLIVEIRA | E11: 048 | F11: COMERCIAL | G11: 160 | H11: NA - NÃO POSSUI PROJETO | I11: 18 | J11: ALIMENTAÇÃO | K11: 16 | L11: 74 | M11: CON | N11: FIRSTLAB INDUSTRIA IMP E EXP DE PROD PARA LABS LTD
A12: 46024 | B12: 2400 | C12: 26136 | D12: JOANA MARIA TEIXEIRA DE OLIVEIRA | E12: 048 | F12: COMERCIAL | G12: 160 | H12: NA - NÃO POSSUI PROJETO | I12: 18 | J12: ALIMENTAÇÃO | K12: 17 | L12: 18 | M12: CON | N12: FIRSTLAB INDUSTRIA IMP E EXP DE PROD PARA LABS LTD
A13: 46024 | B13: 2400 | C13: 26136 | D13: JOANA MARIA TEIXEIRA DE OLIVEIRA | E13: 048 | F13: COMERCIAL | G13: 160 | H13: NA - NÃO POSSUI PROJETO | I13: 18 | J13: ALIMENTAÇÃO | K13: 19 | L13: 48.9 | M13: CON | N13: FIRSTLAB INDUSTRIA IMP E EXP DE PROD PARA LABS LTD
... A102: 46052 | B102: 2420 | C102: 25745 | D102: MARCIO ARRUDA LUZ | E102: 048 | F102: COMERCIAL | G102: 160 | H102: NA - NÃO POSSUI PROJETO | I102: 11 | J102: CONDUÇÃO | K102: 11 | L102: 150 | M102: CON | N102: FIRSTLAB INDUSTRIA IMP E EXP DE PROD PARA LABS LTD
A103: 46055 | B103: 2421 | C103: 27576 | D103: JULIANA FARIA GASPARIN | I103: 7 | J103: ALIMENTAÇÃO | K103: 2 | L103: 64.5 | M103: CON | N103: LIMED - MATERIAIS MEDICO HOSPITALAR E LABORATORIAL
A104: 46055 | B104: 2421 | C104: 27576 | D104: JULIANA FARIA GASPARIN | I104: 7 | J104: ALIMENTAÇÃO | K104: 3 | L104: 20.9 | M104: CON | N104: LICIMASTER DIST DE MED E PROD MÉDICO HOSP EIRELLI - EPP
A105: 46055 | B105: 2421 | C105: 27576 | D105: JULIANA FARIA GASPARIN | I105: 7 | J105: ALIMENTAÇÃO | K105: 4 | L105: 60 | M105: CON | N105: CONECT SOLUCOES DIAGNOSTICO LIMITADA
A106: 46055 | B106: 2421 | C106: 27576 | D106: JULIANA FARIA GASPARIN | I106: 7 | J106: ALIMENTAÇÃO | K106: 5 | L106: 70 | M106: CON | N106: CONECT SOLUCOES DIAGNOSTICO LIMITADA
A107: 46055 | B107: 2421 | C107: 27576 | D107: JULIANA FARIA GASPARIN | I107: 7 | J107: ALIMENTAÇÃO | K107: 6 | L107: 29.7 | M107: CON | N107: CONECT SOLUCOES DIAGNOSTICO LIMITADA
A108: 46055 | B108: 2421 | C108: 27576 | D108: JULIANA FARIA GASPARIN | I108: 7 | J108: ALIMENTAÇÃO | K108: 7 | L108: 86.09 | M108: CON | N108: CONECT SOLUCOES DIAGNOSTICO LIMITADA
A109: 46055 | B109: 2421 | C109: 27576 | D109: JULIANA FARIA GASPARIN | I109: 11 | J109: CONDUÇÃO | K109: 8 | L109: 421.1 | M109: CON | N109: CONECT SOLUCOES DIAGNOSTICO LIMITADA
A110: 46055 | B110: 2421 | C110: 27576 | D110: JULIANA FARIA GASPARIN | E110: 048 | F110: COMERCIAL | G110: 160 | H110: NA - NÃO POSSUI PROJETO | I110: 7 | J110: ALIMENTAÇÃO | K110: 1 | L110: 47.7 | M110: CON | N110: CONECT SOLUCOES DIAGNOSTICO LIMITADA
A111: 46055 | B111: 2422 | C111: 27576 | D111: JULIANA FARIA GASPARIN | I111: 7 | J111: ALIMENTAÇÃO | K111: 2 | L111: 60 | M111: CON | N111: LABSHOP LTDA ME
A112: 46055 | B112: 2422 | C112: 27576 | D112: JULIANA FARIA GASPARIN | I112: 7 | J112: ALIMENTAÇÃO | K112: 3 | L112: 45.43 | M112: CON | N112: LABSHOP LTDA ME
A113: 46055 | B113: 2422 | C113: 27576 | D113: JULIANA FARIA GASPARIN | I113: 7 | J113: ALIMENTAÇÃO | K113: 4 | L113: 60.47 | M113: CON | N113: LABSHOP LTDA ME
A114: 46055 | B114: 2422 | C114: 27576 | D114: JULIANA FARIA GASPARIN | I114: 7 | J114: ALIMENTAÇÃO | K114: 5 | L114: 23 | M114: CON | N114: LABSHOP LTDA ME
A115: 46055 | B115: 2422 | C115: 27576 | D115: JULIANA FARIA GASPARIN | I115: 7 | J115: ALIMENTAÇÃO | K115: 6 | L115: 82.8 | M115: CON | N115: LABSHOP LTDA ME
A116: 46055 | B116: 2422 | C116: 27576 | D116: JULIANA FARIA GASPARIN | I116: 7 | J116: ALIMENTAÇÃO | K116: 7 | L116: 48.36 | M116: CON | N116: LABSHOP LTDA ME
A117: 46055 | B117: 2422 | C117: 27576 | D117: JULIANA FARIA GASPARIN | I117: 7 | J117: ALIMENTAÇÃO | K117: 8 | L117: 10.36 | M117: CON | N117: LABSHOP LTDA ME
A118: 46055 | B118: 2422 | C118: 27576 | D118: JULIANA FARIA GASPARIN | I118: 7 | J118: ALIMENTAÇÃO | K118: 9 | L118: 49.63 | M118: CON | N118: LABSHOP LTDA ME
A119: 46055 | B119: 2422 | C119: 27576 | D119: JULIANA FARIA GASPARIN | I119: 10 | J119: ESTACIONAMENTO | K119: 10 | L119: 15.5 | M119: CON | N119: LABSHOP LTDA ME
A120: 46055 | B120: 2422 | C120: 27576 | D120: JULIANA FARIA GASPARIN | I120: 10 | J120: ESTACIONAMENTO | K120: 11 | L120: 8 | M120: CON | N120: LABSHOP LTDA ME
A121: 46055 | B121: 2422 | C121: 27576 | D121: JULIANA FARIA GASPARIN | I121: 25 | J121: COMBUSTÍVEL | K121: 12 | L121: 108.45 | M121: CON | N121: LABSHOP LTDA ME
A122: 46055 | B122: 2422 | C122: 27576 | D122: JULIANA FARIA GASPARIN | I122: 25 | J122: COMBUSTÍVEL | K122: 13 | L122: 92.91 | M122: CON | N122: LABSHOP LTDA ME
A123: 46055 | B123: 2422 | C123: 27576 | D123: JULIANA FARIA GASPARIN | E123: 048 | F123: COMERCIAL | G123: 160 | H123: NA - NÃO POSSUI PROJETO | I123: 7 | J123: ALIMENTAÇÃO | K123: 1 | L123: 21.51 | M123: CON | N123: LABSHOP LTDA ME
A124: 46055 | B124: 2423 | C124: 27576 | D124: JULIANA FARIA GASPARIN | I124: 7 | J124: ALIMENTAÇÃO | K124: 2 | L124: 54 | M124: CON | N124: FIRSTLAB INDUSTRIA IMP E EXP DE PROD PARA LABORATO
A125: 46055 | B125: 2423 | C125: 27576 | D125: JULIANA FARIA GASPARIN | I125: 7 | J125: ALIMENTAÇÃO | K125: 3 | L125: 44.9 | M125: CON | N125: FIRSTLAB INDUSTRIA IMP E EXP DE PROD PARA LABORATO
A126: 46055 | B126: 2423 | C126: 27576 | D126: JULIANA FARIA GASPARIN | I126: 7 | J126: ALIMENTAÇÃO | K126: 4 | L126: 43.32 | M126: CON | N126: FIRSTLAB INDUSTRIA IMP E EXP DE PROD PARA LABORATO
A127: 46055 | B127: 2423 | C127: 27576 | D127: JULIANA FARIA GASPARIN | I127: 7 | J127: ALIMENTAÇÃO | K127: 5 | L127: 240 | M127: CON | N127: FIRSTLAB INDUSTRIA IMP E EXP DE PROD PARA LABORATO
A128: 46055 | B128: 2423 | C128: 27576 | D128: JULIANA FARIA GASPARIN | I128: 7 | J128: ALIMENTAÇÃO | K128: 6 | L128: 33.86 | M128: CON | N128: FIRSTLAB INDUSTRIA IMP E EXP DE PROD PARA LABORATO
A129: 46055 | B129: 2423 | C129: 27576 | D129: JULIANA FARIA GASPARIN | I129: 7 | J129: ALIMENTAÇÃO | K129: 7 | L129: 57 | M129: CON | N129: FIRSTLAB INDUSTRIA IMP E EXP DE PROD PARA LABORATO
A130: 46052 | B130: 2423 | C130: 27576 | D130: JULIANA FARIA GASPARIN | I130: 11 | J130: CONDUÇÃO | K130: 8 | L130: 289.81 | M130: CON | N130: FIRSTLAB INDUSTRIA IMP E EXP DE PROD PARA LABORATO
A131: 46055 | B131: 2423 | C131: 27576 | D131: JULIANA FARIA GASPARIN | E131: 048 | F131: COMERCIAL | G131: 160 | H131: NA - NÃO POSSUI PROJETO | I131: 7 | J131: ALIMENTAÇÃO | K131: 1 | L131: 38.9 | M131: CON | N131: FIRSTLAB INDUSTRIA IMP E EXP DE PROD PARA LABORATO
A132: 46055 | B132: 2424 | C132: 27576 | D132: JULIANA FARIA GASPARIN | E132: 048 | F132: COMERCIAL | G132: 160 | H132: NA - NÃO POSSUI PROJETO | I132: 6 | J132: KM RODADO | K132: 1 | L132: 324.12 | M132: CON | N132: FIGUEIREDO FARMA COMERCIO DE PRODUTOS HOSPITALARES LTDA
A133: 46059 | B133: 2425 | C133: 23355 | D133: DIRLENE APARECIDA BRILHANTE | E133: 094 | F133: IN30 - SEGURANÇA E MEDICINA DO TRABALHO | G133: 160 | H133: NA - NÃO POSSUI PROJETO | I133: 11 | J133: CONDUÇÃO | K133: 1 | L133: 28.96 | M133: CON | N133: FIRSTLAB INDUSTRIA IMP E EXP DE PROD PARA LABS LTD
A134: 46059 | B134: 2426 | C134: 26387 | D134: FELIPE LUIZ RIBEIRO PEREIRA | E134: 048 | F134: COMERCIAL | G134: 160 | H134: NA - NÃO POSSUI PROJETO | I134: 6 | J134: KM RODADO | K134: 1 | L134: 177.6 | M134: CON | N134: FIRSTLAB INDUSTRIA IMP E EXP DE PROD PARA LABS LTD
A135: 46055 | B135: 2427 | C135: 25880 | D135: RAQUEL AICO SHINKAI | E135: 048 | F135: COMERCIAL | G135: 160 | H135: NA - NÃO POSSUI PROJETO | I135: 23 | J135: COMBUSTÍVEL | K135: 1 | L135: 237.82 | M135: CON | N135: FIRSTLAB INDUSTRIA IMP E EXP DE PROD PARA LABS LTD
A136: 46050 | B136: 2428 | C136: 27677 | D136: EDUARDA ELIS ARAUJO PINTO | E136: 040 | F136: QUALIDADE | G136: 160 | H136: NA - NÃO POSSUI PROJETO | I136: 11 | J136: CONDUÇÃO | K136: 1 | L136: 21.7 | M136: CON | N136: FIRSTLAB INDUSTRIA IMP E EXP DE PROD PARA LABS LTD
A137: 46054 | B137: 2428 | C137: 27677 | D137: EDUARDA ELIS ARAUJO PINTO | E137: 040 | F137: QUALIDADE | G137: 160 | H137: NA - NÃO POSSUI PROJETO | I137: 11 | J137: CONDUÇÃO | K137: 2 | L137: 20.57 | M137: CON | N137: FIRSTLAB INDUSTRIA IMP E EXP DE PROD PARA LABS LTD
A138: 46059 | B138: 2429 | C138: 25745 | D138: MARCIO ARRUDA LUZ | E138: 048 | F138: COMERCIAL | G138: 160 | H138: NA - NÃO POSSUI PROJETO | I138: 6 | J138: KM RODADO | K138: 1 | L138: 2933.36 | M138: CON | N138: FIRSTLAB INDUSTRIA IMP E EXP DE PROD PARA LABS LTD
A139: 46054 | B139: 2430 | C139: 27677 | D139: EDUARDA ELIS ARAUJO PINTO | E139: 040 | F139: QUALIDADE | G139: 160 | H139: NA - NÃO POSSUI PROJETO | I139: 11 | J139: CONDUÇÃO | K139: 1 | L139: 27.5 | M139: CON | N139: FIRSTLAB INDUSTRIA IMP E EXP DE PROD PARA LABS LTD
A140: 46054 | B140: 2430 | C140: 27677 | D140: EDUARDA ELIS ARAUJO PINTO | E140: 040 | F140: QUALIDADE | G140: 160 | H140: NA - NÃO POSSUI PROJETO | I140: 11 | J140: CONDUÇÃO | K140: 2 | L140: 23.2 | M140: CON | N140: FIRSTLAB INDUSTRIA IMP E EXP DE PROD PARA LABS LTD
A141: 46054 | B141: 2431 | C141: 27677 | D141: EDUARDA ELIS ARAUJO PINTO | E141: 040 | F141: QUALIDADE | G141: 160 | H141: NA - NÃO POSSUI PROJETO | I141: 11 | J141: CONDUÇÃO | K141: 1 | L141: 20.96 | M141: CON | N141: FIRSTLAB INDUSTRIA IMP E EXP DE PROD PARA LABS LTD
A142: 46054 | B142: 2431 | C142: 27677 | D142: EDUARDA ELIS ARAUJO PINTO | E142: 040 | F142: QUALIDADE | G142: 160 | H142: NA - NÃO POSSUI PROJETO | I142: 11 | J142: CONDUÇÃO | K142: 2 | L142: 23.21 | M142: CON | N142: FIRSTLAB INDUSTRIA IMP E EXP DE PROD PARA LABS LTD
... A450: 46107 | B450: 2464 | C450: 25745 | D450: MARCIO ARRUDA LUZ | E450: 048 | F450: COMERCIAL | G450: 160 | H450: NA - NÃO POSSUI PROJETO | I450: 11 | J450: CONDUÇÃO | K450: 2 | L450: 150 | M450: CON | N450: FIRSTLAB INDUSTRIA IMP E EXP DE PROD PARA LABS LTD
A451: 46085 | B451: 2465 | C451: 27576 | D451: JULIANA FARIA GASPARIN | E451: 048 | F451: COMERCIAL | I451: 10 | J451: ESTACIONAMENTO | K451: 4 | L451: 16 | M451: PEN | N451: FIGUEIREDO FARMA COMERCIO DE PRODUTOS HOSPITALARES LTDA
A452: 46085 | B452: 2465 | C452: 27576 | D452: JULIANA FARIA GASPARIN | E452: 048 | F452: COMERCIAL | I452: 36 | J452: DESPESA COM CLIENTES - DNH | K452: 2 | L452: 22.96 | M452: PEN | N452: FIGUEIREDO FARMA COMERCIO DE PRODUTOS HOSPITALARES LTDA
A453: 46085 | B453: 2465 | C453: 27576 | D453: JULIANA FARIA GASPARIN | E453: 048 | F453: COMERCIAL | I453: 36 | J453: DESPESA COM CLIENTES - DNH | K453: 3 | L453: 34.9 | M453: PEN | N453: FIGUEIREDO FARMA COMERCIO DE PRODUTOS HOSPITALARES LTDA
A454: 46085 | B454: 2465 | C454: 27576 | D454: JULIANA FARIA GASPARIN | E454: 048 | F454: COMERCIAL | I454: 36 | J454: DESPESA COM CLIENTES - DNH | K454: 5 | L454: 20 | M454: PEN | N454: FIGUEIREDO FARMA COMERCIO DE PRODUTOS HOSPITALARES LTDA
A455: 46085 | B455: 2465 | C455: 27576 | D455: JULIANA FARIA GASPARIN | E455: 048 | F455: COMERCIAL | I455: 38 | J455: FEIRAS E EVENTOS - DNH | K455: 1 | L455: 166 | M455: PEN | N455: FIGUEIREDO FARMA COMERCIO DE PRODUTOS HOSPITALARES LTDA
A456: 46100 | B456: 2466 | C456: 27576 | D456: JULIANA FARIA GASPARIN | E456: 048 | F456: COMERCIAL | I456: 7 | J456: ALIMENTAÇÃO | K456: 1 | L456: 30 | M456: PEN | N456: PMH PRODUTOS MEDICOS HOSPITALARES LTDA
A457: 46099 | B457: 2466 | C457: 27576 | D457: JULIANA FARIA GASPARIN | E457: 048 | F457: COMERCIAL | I457: 7 | J457: ALIMENTAÇÃO | K457: 2 | L457: 120 | M457: PEN | N457: PMH PRODUTOS MEDICOS HOSPITALARES LTDA
A458: 46100 | B458: 2466 | C458: 27576 | D458: JULIANA FARIA GASPARIN | E458: 048 | F458: COMERCIAL | I458: 9 | J458: HOSPEDAGEM - DNH | K458: 5 | L458: 154 | M458: PEN | N458: PMH PRODUTOS MEDICOS HOSPITALARES LTDA
A459: 46098 | B459: 2466 | C459: 27576 | D459: JULIANA FARIA GASPARIN | E459: 048 | F459: COMERCIAL | I459: 11 | J459: CONDUÇÃO | K459: 4 | L459: 652.95 | M459: PEN | N459: PMH PRODUTOS MEDICOS HOSPITALARES LTDA
A460: 46108 | B460: 2467 | C460: 27576 | D460: JULIANA FARIA GASPARIN | E460: 048 | F460: COMERCIAL | I460: 7 | J460: ALIMENTAÇÃO | K460: 1 | L460: 52 | M460: PEN | N460: SUPERMEDICA DISTRIBUIDORA HOSPITALAR
A461: 46105 | B461: 2467 | C461: 27576 | D461: JULIANA FARIA GASPARIN | E461: 048 | F461: COMERCIAL | I461: 7 | J461: ALIMENTAÇÃO | K461: 4 | L461: 31.99 | M461: PEN | N461: SUPERMEDICA DISTRIBUIDORA HOSPITALAR
A462: 46106 | B462: 2467 | C462: 27576 | D462: JULIANA FARIA GASPARIN | E462: 048 | F462: COMERCIAL | I462: 7 | J462: ALIMENTAÇÃO | K462: 5 | L462: 29 | M462: PEN | N462: SUPERMEDICA DISTRIBUIDORA HOSPITALAR
... A472: 46108 | B472: 2467 | C472: 27576 | D472: JULIANA FARIA GASPARIN | E472: 048 | F472: COMERCIAL | I472: 25 | J472: COMBUSTÍVEL | K472: 2 | L472: 185.99 | M472: PEN | N472: SUPERMEDICA DISTRIBUIDORA HOSPITALAR
A473: 46109 | B473: 2468 | C473: 27576 | D473: JULIANA FARIA GASPARIN | I473: 25 | J473: COMBUSTÍVEL | K473: 1 | L473: 87.38 | M473: PEN | N473: FIGUEIREDO FARMA COMERCIO DE PRODUTOS HOSPITALARES LTDA
A474: 46109 | B474: 2468 | C474: 27576 | D474: JULIANA FARIA GASPARIN | I474: 25 | J474: COMBUSTÍVEL | K474: 1 | L474: 87.38 | M474: PEN | N474: INSTRUMENTAL TECNICO LTDA
A475: 46109 | B475: 2468 | C475: 27576 | D475: JULIANA FARIA GASPARIN | I475: 25 | J475: COMBUSTÍVEL | K475: 1 | L475: 87.38 | M475: PEN | N475: MEGATONS SAUDE LTDA
A476: 46109 | B476: 2468 | C476: 27576 | D476: JULIANA FARIA GASPARIN | I476: 25 | J476: COMBUSTÍVEL | K476: 1 | L476: 87.38 | M476: PEN | N476: URTIFARMA COMERCIO DE INST E MATERIAIS MEDICO LTDA
A477: 46108 | B477: 2470 | C477: 26385 | D477: LETICIA CAMPOS DA SILVA VAZ | E477: 048 | F477: COMERCIAL | G477: 160 | H477: NA - NÃO POSSUI PROJETO | I477: 6 | J477: KM RODADO | K477: 1 | L477: 290.08 | M477: CON | N477: FIRSTLAB INDUSTRIA IMP E EXP DE PROD PARA LABS LTD
A478: 46113 | B478: 2471 | C478: 26136 | D478: JOANA MARIA TEIXEIRA DE OLIVEIRA | E478: 048 | F478: COMERCIAL | G478: 160 | H478: NA - NÃO POSSUI PROJETO | I478: 18 | J478: ALIMENTAÇÃO | K478: 1 | L478: 17.64 | M478: PEN | N478: FIRSTLAB INDUSTRIA IMP E EXP DE PROD PARA LABS LTD
A479: 46113 | B479: 2471 | C479: 26136 | D479: JOANA MARIA TEIXEIRA DE OLIVEIRA | E479: 048 | F479: COMERCIAL | G479: 160 | H479: NA - NÃO POSSUI PROJETO | I479: 18 | J479: ALIMENTAÇÃO | K479: 2 | L479: 56 | M479: PEN | N479: FIRSTLAB INDUSTRIA IMP E EXP DE PROD PARA LABS LTD
A480: 46113 | B480: 2471 | C480: 26136 | D480: JOANA MARIA TEIXEIRA DE OLIVEIRA | E480: 048 | F480: COMERCIAL | G480: 160 | H480: NA - NÃO POSSUI PROJETO | I480: 18 | J480: ALIMENTAÇÃO | K480: 3 | L480: 18 | M480: PEN | N480: FIRSTLAB INDUSTRIA IMP E EXP DE PROD PARA LABS LTD
A481: 46113 | B481: 2471 | C481: 26136 | D481: JOANA MARIA TEIXEIRA DE OLIVEIRA | E481: 048 | F481: COMERCIAL | G481: 160 | H481: NA - NÃO POSSUI PROJETO | I481: 18 | J481: ALIMENTAÇÃO | K481: 6 | L481: 63 | M481: PEN | N481: FIRSTLAB INDUSTRIA IMP E EXP DE PROD PARA LABS LTD
A482: 46113 | B482: 2471 | C482: 26136 | D482: JOANA MARIA TEIXEIRA DE OLIVEIRA | E482: 048 | F482: COMERCIAL | G482: 160 | H482: NA - NÃO POSSUI PROJETO | I482: 18 | J482: ALIMENTAÇÃO | K482: 8 | L482: 56.84 | M482: PEN | N482: FIRSTLAB INDUSTRIA IMP E EXP DE PROD PARA LABS LTD
A483: 46113 | B483: 2471 | C483: 26136 | D483: JOANA MARIA TEIXEIRA DE OLIVEIRA | E483: 048 | F483: COMERCIAL | G483: 160 | H483: NA - NÃO POSSUI PROJETO | I483: 18 | J483: ALIMENTAÇÃO | K483: 9 | L483: 35.76 | M483: PEN | N483: FIRSTLAB INDUSTRIA IMP E EXP DE PROD PARA LABS LTD
A484: 46113 | B484: 2471 | C484: 26136 | D484: JOANA MARIA TEIXEIRA DE OLIVEIRA | E484: 048 | F484: COMERCIAL | G484: 160 | H484: NA - NÃO POSSUI PROJETO | I484: 18 | J484: ALIMENTAÇÃO | K484: 12 | L484: 72.8 | M484: PEN | N484: FIRSTLAB INDUSTRIA IMP E EXP DE PROD PARA LABS LTD
A485: 46113 | B485: 2471 | C485: 26136 | D485: JOANA MARIA TEIXEIRA DE OLIVEIRA | E485: 048 | F485: COMERCIAL | G485: 160 | H485: NA - NÃO POSSUI PROJETO | I485: 18 | J485: ALIMENTAÇÃO | K485: 15 | L485: 22.05 | M485: PEN | N485: FIRSTLAB INDUSTRIA IMP E EXP DE PROD PARA LABS LTD
A486: 46113 | B486: 2471 | C486: 26136 | D486: JOANA MARIA TEIXEIRA DE OLIVEIRA | E486: 048 | F486: COMERCIAL | G486: 160 | H486: NA - NÃO POSSUI PROJETO | I486: 18 | J486: ALIMENTAÇÃO | K486: 16 | L486: 10 | M486: PEN | N486: FIRSTLAB INDUSTRIA IMP E EXP DE PROD PARA LABS LTD
A487: 46113 | B487: 2471 | C487: 26136 | D487: JOANA MARIA TEIXEIRA DE OLIVEIRA | E487: 048 | F487: COMERCIAL | G487: 160 | H487: NA - NÃO POSSUI PROJETO | I487: 18 | J487: ALIMENTAÇÃO | K487: 18 | L487: 32.44 | M487: PEN | N487: FIRSTLAB INDUSTRIA IMP E EXP DE PROD PARA LABS LTD
A488: 46113 | B488: 2471 | C488: 26136 | D488: JOANA MARIA TEIXEIRA DE OLIVEIRA | E488: 048 | F488: COMERCIAL | G488: 160 | H488: NA - NÃO POSSUI PROJETO | I488: 18 | J488: ALIMENTAÇÃO | K488: 19 | L488: 68.8 | M488: PEN | N488: FIRSTLAB INDUSTRIA IMP E EXP DE PROD PARA LABS LTD
... A508: 46113 | B508: 2471 | C508: 26136 | D508: JOANA MARIA TEIXEIRA DE OLIVEIRA | E508: 048 | F508: COMERCIAL | G508: 160 | H508: NA - NÃO POSSUI PROJETO | I508: 24 | J508: ESTACIONAMENTO | K508: 21 | L508: 19 | M508: PEN | N508: FIRSTLAB INDUSTRIA IMP E EXP DE PROD PARA LABS LTD
A509: 46106 | B509: 2473 | C509: 27813 | D509: RENATA LUCIANA MARTINS DE LIMA | E509: 048 | F509: COMERCIAL | I509: 7 | J509: ALIMENTAÇÃO | K509: 2 | L509: 80 | M509: CON | N509: FISHER LAB PRODUTOS PARA LABORATORIO LTDA
A510: 46106 | B510: 2473 | C510: 27813 | D510: RENATA LUCIANA MARTINS DE LIMA | E510: 048 | F510: COMERCIAL | I510: 7 | J510: ALIMENTAÇÃO | K510: 3 | L510: 36.9 | M510: CON | N510: FISHER LAB PRODUTOS PARA LABORATORIO LTDA
A511: 46107 | B511: 2473 | C511: 27813 | D511: RENATA LUCIANA MARTINS DE LIMA | E511: 048 | F511: COMERCIAL | I511: 7 | J511: ALIMENTAÇÃO | K511: 4 | L511: 69 | M511: CON | N511: FISHER LAB PRODUTOS PARA LABORATORIO LTDA
A512: 46107 | B512: 2473 | C512: 27813 | D512: RENATA LUCIANA MARTINS DE LIMA | E512: 048 | F512: COMERCIAL | I512: 7 | J512: ALIMENTAÇÃO | K512: 5 | L512: 35.06 | M512: CON | N512: FISHER LAB PRODUTOS PARA LABORATORIO LTDA
A513: 46108 | B513: 2473 | C513: 27813 | D513: RENATA LUCIANA MARTINS DE LIMA | E513: 048 | F513: COMERCIAL | I513: 7 | J513: ALIMENTAÇÃO | K513: 6 | L513: 82.8 | M513: CON | N513: FISHER LAB PRODUTOS PARA LABORATORIO LTDA
A514: 46108 | B514: 2473 | C514: 27813 | D514: RENATA LUCIANA MARTINS DE LIMA | E514: 048 | F514: COMERCIAL | I514: 7 | J514: ALIMENTAÇÃO | K514: 7 | L514: 27.8 | M514: CON | N514: FISHER LAB PRODUTOS PARA LABORATORIO LTDA
A515: 46105 | B515: 2473 | C515: 27813 | D515: RENATA LUCIANA MARTINS DE LIMA | E515: 048 | F515: COMERCIAL | I515: 11 | J515: CONDUÇÃO | K515: 8 | L515: 32.94 | M515: CON | N515: FISHER LAB PRODUTOS PARA LABORATORIO LTDA
A516: 46105 | B516: 2473 | C516: 27813 | D516: RENATA LUCIANA MARTINS DE LIMA | E516: 048 | F516: COMERCIAL | I516: 11 | J516: CONDUÇÃO | K516: 9 | L516: 39.94 | M516: CON | N516: FISHER LAB PRODUTOS PARA LABORATORIO LTDA
A517: 46106 | B517: 2473 | C517: 27813 | D517: RENATA LUCIANA MARTINS DE LIMA | E517: 048 | F517: COMERCIAL | I517: 11 | J517: CONDUÇÃO | K517: 10 | L517: 32.94 | M517: CON | N517: FISHER LAB PRODUTOS PARA LABORATORIO LTDA
A518: 46106 | B518: 2473 | C518: 27813 | D518: RENATA LUCIANA MARTINS DE LIMA | E518: 048 | F518: COMERCIAL | I518: 11 | J518: CONDUÇÃO | K518: 11 | L518: 38.94 | M518: CON | N518: FISHER LAB PRODUTOS PARA LABORATORIO LTDA
A519: 46107 | B519: 2473 | C519: 27813 | D519: RENATA LUCIANA MARTINS DE LIMA | E519: 048 | F519: COMERCIAL | I519: 11 | J519: CONDUÇÃO | K519: 12 | L519: 30.95 | M519: CON | N519: FISHER LAB PRODUTOS PARA LABORATORIO LTDA
A520: 46107 | B520: 2473 | C520: 27813 | D520: RENATA LUCIANA MARTINS DE LIMA | E520: 048 | F520: COMERCIAL | I520: 11 | J520: CONDUÇÃO | K520: 13 | L520: 62.93 | M520: CON | N520: FISHER LAB PRODUTOS PARA LABORATORIO LTDA
... A523: 46092 | B523: 2473 | C523: 27813 | D523: RENATA LUCIANA MARTINS DE LIMA | E523: 048 | F523: COMERCIAL | I523: 13 | J523: PASSAGEM - DNH | K523: 16 | L523: 280 | M523: CON | N523: FISHER LAB PRODUTOS PARA LABORATORIO LTDA
A524: 46113 | B524: 2473 | C524: 27813 | D524: RENATA LUCIANA MARTINS DE LIMA | E524: 048 | F524: COMERCIAL | G524: 160 | H524: NA - NÃO POSSUI PROJETO | I524: 7 | J524: ALIMENTAÇÃO | K524: 1 | L524: 62.93 | M524: CON | N524: FISHER LAB PRODUTOS PARA LABORATORIO LTDA
A525: 46120 | B525: 2475 | C525: 26385 | D525: LETICIA CAMPOS DA SILVA VAZ | E525: 048 | F525: COMERCIAL | G525: 160 | H525: NA - NÃO POSSUI PROJETO | I525: 18 | J525: ALIMENTAÇÃO | K525: 1 | L525: 34.8 | M525: PEN | N525: FIRSTLAB INDUSTRIA IMP E EXP DE PROD PARA LABS LTD
...

Sheet Base - AG1
A1: Data Venda | B1: Venda Nº | C1: Nrs. FT (Cli) | D1: Produto | E1: Nome Cia | F1: Conta | G1: Nome Cliente | H1: Desc. C. Custo Cliente | I1: Cód centro de custo | J1: Centro de Custo | K1: Departamento | L1: Motivo Viagem | M1: Solicitante | N1: Colaborador | O1: Colaborador - De Para | P1: Cód. Colaborador | Q1: SUB-REGIÃO | R1: CANAL | S1: Cidade Cia | T1: Rota Resumida | U1: Dt. Início Serviços | V1: Dt. Fim Serviços | W1: Form | X1: Nr. Doc | Y1: Total Tarifa | Z1: Total Taxas | AA1: Total Fee | AB1: Total Cliente
A2: 45838 | B2: 50382 | C2: 6699 | D2: CAR | E2: UNIDAS | F2: =_xlfn.XLOOKUP(E2,DEPARA!A:A,DEPARA!C:C,"Verificar") -> LOCAÇÃO DE VEÍCULOS | G2: FIRSTLAB IND. IMP. E EXP. DE PROD. PARA LAB. LTDA | H2: 055-EQUIPE COMERCIAL 3 | I2: =_xlfn.XLOOKUP(fatoG1[[#This Row],[Centro de Custo]],dimCentroCusto[Centro_Custo],dimCentroCusto[Codigo_CentroCusto]) -> #N/A | J2: =fatoG1[[#This Row],[Desc. C. Custo Cliente]] -> 055-EQUIPE COMERCIAL 3 | L2: VISITA CLIENTES DA REGIÃO | N2: LUZ/MARCIO ARRUDA | O2: =_xlfn.XLOOKUP(N2,DEPARA!F:F,DEPARA!H:H,0) -> MARCIO ARRUDA LUZ | P2: =_xlfn.XLOOKUP(O2,dimColaborador!A:A,dimColaborador!B:B,0) -> 25745 | Q2: =_xlfn.XLOOKUP(O2,dimColaborador!A:A,dimColaborador!C:C,) -> GC - MÉDIO/GRANDE PORTE - SE/CO | R2: =_xlfn.XLOOKUP(O2,dimColaborador!A:A,dimColaborador!D:D) -> GRANDES CONTAS | S2: CURITIBA | T2: 10/06/25 a 12/06/25 - VOLKSWAGEN POLO 200 TSI, PEUGEOT 208, | U2: 45818 | V2: 45820 | W2: 2118 | X2: 508546 | Y2: 364.76 | Z2: 32.9 | AA2: 0 | AB2: 397.66
A3: 45838 | B3: 50383 | C3: 6699 | D3: CAR | E3: UNIDAS | F3: =_xlfn.XLOOKUP(E3,DEPARA!A:A,DEPARA!C:C,"Verificar") -> LOCAÇÃO DE VEÍCULOS | G3: FIRSTLAB IND. IMP. E EXP. DE PROD. PARA LAB. LTDA | H3: 055-EQUIPE COMERCIAL 3 | I3: =_xlfn.XLOOKUP(fatoG1[[#This Row],[Centro de Custo]],dimCentroCusto[Centro_Custo],dimCentroCusto[Codigo_CentroCusto]) -> #N/A | J3: =fatoG1[[#This Row],[Desc. C. Custo Cliente]] -> 055-EQUIPE COMERCIAL 3 | L3: VISITA CLIENTES DA REGIÃO | N3: LUZ/MARCIO ARRUDA | O3: =_xlfn.XLOOKUP(N3,DEPARA!F:F,DEPARA!H:H,0) -> MARCIO ARRUDA LUZ | P3: =_xlfn.XLOOKUP(O3,dimColaborador!A:A,dimColaborador!B:B,0) -> 25745 | Q3: =_xlfn.XLOOKUP(O3,dimColaborador!A:A,dimColaborador!C:C,) -> GC - MÉDIO/GRANDE PORTE - SE/CO | R3: =_xlfn.XLOOKUP(O3,dimColaborador!A:A,dimColaborador!D:D) -> GRANDES CONTAS | S3: CURITIBA | T3: 12/06/25 a 13/06/25 - VOLKSWAGEN POLO 200 TSI, PEUGEOT 208, | U3: 45820 | V3: 45821 | W3: 2118 | X3: 508585 | Y3: 182.38 | Z3: 0 | AA3: 0 | AB3: 182.38
A4: 45832 | B4: 50395 | C4: 6699 | D4: HTL | E4: SCALA RESIDENCE HOTEL | F4: =_xlfn.XLOOKUP(E4,DEPARA!A:A,DEPARA!C:C,"Verificar") -> HOSPEDAGEM | G4: FIRSTLAB IND. IMP. E EXP. DE PROD. PARA LAB. LTDA | H4: 055-EQUIPE COMERCIAL 3 | I4: =_xlfn.XLOOKUP(fatoG1[[#This Row],[Centro de Custo]],dimCentroCusto[Centro_Custo],dimCentroCusto[Codigo_CentroCusto]) -> #N/A | J4: =fatoG1[[#This Row],[Desc. C. Custo Cliente]] -> 055-EQUIPE COMERCIAL 3 | L4: VISITA CLIENTES DA REGIÃO | N4: LUZ/MARCIO ARRUDA | O4: =_xlfn.XLOOKUP(N4,DEPARA!F:F,DEPARA!H:H,0) -> MARCIO ARRUDA LUZ | P4: =_xlfn.XLOOKUP(O4,dimColaborador!A:A,dimColaborador!B:B,0) -> 25745 | Q4: =_xlfn.XLOOKUP(O4,dimColaborador!A:A,dimColaborador!C:C,) -> GC - MÉDIO/GRANDE PORTE - SE/CO | R4: =_xlfn.XLOOKUP(O4,dimColaborador!A:A,dimColaborador!D:D) -> GRANDES CONTAS | S4: RESENDE | T4: 01 SUÍTES - 23/06/25 a 24/06/25 | U4: 45831 | V4: 45832 | W4: 4 | X4: 703598 | Y4: 274.67 | Z4: 0 | AA4: 0 | AB4: 274.67
A5: 45833 | B5: 50421 | C5: 6699 | D5: HTL | E5: FENIX POUSO ALEGRE HOTEL | F5: =_xlfn.XLOOKUP(E5,DEPARA!A:A,DEPARA!C:C,"Verificar") -> HOSPEDAGEM | G5: FIRSTLAB IND. IMP. E EXP. DE PROD. PARA LAB. LTDA | H5: 055-EQUIPE COMERCIAL 3 | I5: =_xlfn.XLOOKUP(fatoG1[[#This Row],[Centro de Custo]],dimCentroCusto[Centro_Custo],dimCentroCusto[Codigo_CentroCusto]) -> #N/A | J5: =fatoG1[[#This Row],[Desc. C. Custo Cliente]] -> 055-EQUIPE COMERCIAL 3 | L5: VISITA CLIENTES DA REGIÃO | N5: LUZ/MARCIO ARRUDA | O5: =_xlfn.XLOOKUP(N5,DEPARA!F:F,DEPARA!H:H,0) -> MARCIO ARRUDA LUZ | P5: =_xlfn.XLOOKUP(O5,dimColaborador!A:A,dimColaborador!B:B,0) -> 25745 | Q5: =_xlfn.XLOOKUP(O5,dimColaborador!A:A,dimColaborador!C:C,) -> GC - MÉDIO/GRANDE PORTE - SE/CO | R5: =_xlfn.XLOOKUP(O5,dimColaborador!A:A,dimColaborador!D:D) -> GRANDES CONTAS | S5: POUSO ALEGRE | T5: 01 QUARTO STANDARD CASAL - 24/06/25 a 25/06/25 | U5: 45832 | V5: 45833 | W5: 4 | X5: 704624 | Y5: 222 | Z5: 11.1 | AA5: 0 | AB5: 233.1
A6: 45834 | B6: 50423 | C6: 6699 | D6: HTL | E6: HOTEL DO PAPAI NOEL | F6: =_xlfn.XLOOKUP(E6,DEPARA!A:A,DEPARA!C:C,"Verificar") -> HOSPEDAGEM | G6: FIRSTLAB IND. IMP. E EXP. DE PROD. PARA LAB. LTDA | H6: 055-EQUIPE COMERCIAL 3 | I6: =_xlfn.XLOOKUP(fatoG1[[#This Row],[Centro de Custo]],dimCentroCusto[Centro_Custo],dimCentroCusto[Codigo_CentroCusto]) -> #N/A | J6: =fatoG1[[#This Row],[Desc. C. Custo Cliente]] -> 055-EQUIPE COMERCIAL 3 | N6: MARCIO ARRUDA LUZ | O6: =_xlfn.XLOOKUP(N6,DEPARA!F:F,DEPARA!H:H,0) -> MARCIO ARRUDA LUZ | P6: =_xlfn.XLOOKUP(O6,dimColaborador!A:A,dimColaborador!B:B,0) -> 25745 | Q6: =_xlfn.XLOOKUP(O6,dimColaborador!A:A,dimColaborador!C:C,) -> GC - MÉDIO/GRANDE PORTE - SE/CO | R6: =_xlfn.XLOOKUP(O6,dimColaborador!A:A,dimColaborador!D:D) -> GRANDES CONTAS | S6: ITATIAI | T6: 01 SUPER LUXO SINGLE - 25/06/25 a 26/06/25 | U6: 45833 | V6: 45834 | W6: 4 | X6: 704625 | Y6: 231.51 | Z6: 0 | AA6: 0 | AB6: 231.51
A7: 45838 | B7: 51762 | C7: 6699 | D7: CAR | E7: UNIDAS | F7: =_xlfn.XLOOKUP(E7,DEPARA!A:A,DEPARA!C:C,"Verificar") -> LOCAÇÃO DE VEÍCULOS | G7: FIRSTLAB IND. IMP. E EXP. DE PROD. PARA LAB. LTDA | H7: 056-EQUIPE COMERCIAL 4 | I7: =_xlfn.XLOOKUP(fatoG1[[#This Row],[Centro de Custo]],dimCentroCusto[Centro_Custo],dimCentroCusto[Codigo_CentroCusto]) -> #N/A | J7: =fatoG1[[#This Row],[Desc. C. Custo Cliente]] -> 056-EQUIPE COMERCIAL 4 | N7: GONCALVES/THIAGO NARCISO OLIVEIRA | O7: =_xlfn.XLOOKUP(N7,DEPARA!F:F,DEPARA!H:H,0) -> THIAGO NARCISO OLIVEIRA GONÇALVES | P7: =_xlfn.XLOOKUP(O7,dimColaborador!A:A,dimColaborador!B:B,0) -> 26516 | Q7: =_xlfn.XLOOKUP(O7,dimColaborador!A:A,dimColaborador!C:C,) -> DR - PRIME - CENTRO OESTE | R7: =_xlfn.XLOOKUP(O7,dimColaborador!A:A,dimColaborador!D:D) -> DISTRIBUIDOR | S7: CURITIBA | T7: 16/06/25 a 18/06/25 - FIAT ARGO, CHEVROLET ONIX, VW GOL (1. | U7: 45824 | V7: 45826 | W7: 2118 | X7: 615605 | Y7: 298 | Z7: 54.9 | AA7: 0 | AB7: 352.9
A8: 45833 | B8: 51764 | C8: 6699 | D8: HTL | E8: IBIS STYLES GOIANIA SHOPPING ESTACAO | F8: =_xlfn.XLOOKUP(E8,DEPARA!A:A,DEPARA!C:C,"Verificar") -> HOSPEDAGEM | G8: FIRSTLAB IND. IMP. E EXP. DE PROD. PARA LAB. LTDA | H8: 056-EQUIPE COMERCIAL 4 | I8: =_xlfn.XLOOKUP(fatoG1[[#This Row],[Centro de Custo]],dimCentroCusto[Centro_Custo],dimCentroCusto[Codigo_CentroCusto]) -> #N/A | J8: =fatoG1[[#This Row],[Desc. C. Custo Cliente]] -> 056-EQUIPE COMERCIAL 4 | N8: GONCALVES/THIAGO NARCISO OLIVEIRA | O8: =_xlfn.XLOOKUP(N8,DEPARA!F:F,DEPARA!H:H,0) -> THIAGO NARCISO OLIVEIRA GONÇALVES | P8: =_xlfn.XLOOKUP(O8,dimColaborador!A:A,dimColaborador!B:B,0) -> 26516 | Q8: =_xlfn.XLOOKUP(O8,dimColaborador!A:A,dimColaborador!C:C,) -> DR - PRIME - CENTRO OESTE | R8: =_xlfn.XLOOKUP(O8,dimColaborador!A:A,dimColaborador!D:D) -> DISTRIBUIDOR | S8: GOIANIA | T8: 01 DBC APARTAMENTO STANDARD COM 1 CAMA CASAL SEM - 23/06/ | U8: 45831 | V8: 45833 | W8: 4000 | X8: 430904 | Y8: 583.85 | Z8: 11.69 | AA8: 0 | AB8: 595.54
A9: 45835 | B9: 51766 | C9: 6699 | D9: HTL | E9: BRISA TOWER BRASILIA HOTEL | F9: =_xlfn.XLOOKUP(E9,DEPARA!A:A,DEPARA!C:C,"Verificar") -> HOSPEDAGEM | G9: FIRSTLAB IND. IMP. E EXP. DE PROD. PARA LAB. LTDA | H9: 056-EQUIPE COMERCIAL 4 | I9: =_xlfn.XLOOKUP(fatoG1[[#This Row],[Centro de Custo]],dimCentroCusto[Centro_Custo],dimCentroCusto[Codigo_CentroCusto]) -> #N/A | J9: =fatoG1[[#This Row],[Desc. C. Custo Cliente]] -> 056-EQUIPE COMERCIAL 4 | N9: GONCALVES/THIAGO NARCISO OLIVEIRA | O9: =_xlfn.XLOOKUP(N9,DEPARA!F:F,DEPARA!H:H,0) -> THIAGO NARCISO OLIVEIRA GONÇALVES | P9: =_xlfn.XLOOKUP(O9,dimColaborador!A:A,dimColaborador!B:B,0) -> 26516 | Q9: =_xlfn.XLOOKUP(O9,dimColaborador!A:A,dimColaborador!C:C,) -> DR - PRIME - CENTRO OESTE | R9: =_xlfn.XLOOKUP(O9,dimColaborador!A:A,dimColaborador!D:D) -> DISTRIBUIDOR | S9: BRASÍLIA | T9: 01 SUÍTE LUXO - 25/06/25 a 27/06/25 | U9: 45833 | V9: 45835 | W9: 2025 | X9: 60317 | Y9: 540 | Z9: 81 | AA9: 0 | AB9: 621
A10: 45838 | B10: 51872 | C10: 6699 | D10: CAR | E10: UNIDAS | F10: =_xlfn.XLOOKUP(E10,DEPARA!A:A,DEPARA!C:C,"Verificar") -> LOCAÇÃO DE VEÍCULOS | G10: FIRSTLAB IND. IMP. E EXP. DE PROD. PARA LAB. LTDA | H10: 056-EQUIPE COMERCIAL 4 | I10: =_xlfn.XLOOKUP(fatoG1[[#This Row],[Centro de Custo]],dimCentroCusto[Centro_Custo],dimCentroCusto[Codigo_CentroCusto]) -> #N/A | J10: =fatoG1[[#This Row],[Desc. C. Custo Cliente]] -> 056-EQUIPE COMERCIAL 4 | N10: ALMEIDA/KHARLA NAYARA ABRANTES | O10: =_xlfn.XLOOKUP(N10,DEPARA!F:F,DEPARA!H:H,0) -> KHARLA NAYARA ABRANTES DE ALMEIDA | P10: =_xlfn.XLOOKUP(O10,dimColaborador!A:A,dimColaborador!B:B,0) -> 26175 | Q10: =_xlfn.XLOOKUP(O10,dimColaborador!A:A,dimColaborador!C:C,) -> GC -MÉDIO/GRANDE PORTE - NO/NE | R10: =_xlfn.XLOOKUP(O10,dimColaborador!A:A,dimColaborador!D:D) -> GRANDES CONTAS | S10: CURITIBA | T10: 09/06/25 a 16/06/25 - VOLKSWAGEN POLO 200 TSI, PEUGEOT 208, | U10: 45817 | V10: 45824 | W10: 2118 | X10: 621530 | Y10: 1074.01 | Z10: 54.9 | AA10: 0 | AB10: 1128.91
A11: 45834 | B11: 52330 | C11: 6699 | D11: HTL | E11: HOTEL NACIONAL DE RIO PRETO | F11: =_xlfn.XLOOKUP(E11,DEPARA!A:A,DEPARA!C:C,"Verificar") -> HOSPEDAGEM | G11: FIRSTLAB IND. IMP. E EXP. DE PROD. PARA LAB. LTDA | H11: 048-COMERCIAL INTERNO | I11: =_xlfn.XLOOKUP(fatoG1[[#This Row],[Centro de Custo]],dimCentroCusto[Centro_Custo],dimCentroCusto[Codigo_CentroCusto]) -> #N/A | J11: =fatoG1[[#This Row],[Desc. C. Custo Cliente]] -> 048-COMERCIAL INTERNO | L11: VISITA COMERCIAL | N11: PEREIRA/FELIPE LUIZ RIBEIRO | O11: =_xlfn.XLOOKUP(N11,DEPARA!F:F,DEPARA!H:H,0) -> FELIPE LUIZ RIBEIRO PEREIRA | P11: =_xlfn.XLOOKUP(O11,dimColaborador!A:A,dimColaborador!B:B,0) -> 26387 | Q11: =_xlfn.XLOOKUP(O11,dimColaborador!A:A,dimColaborador!C:C,) -> GC - MÉDIO/GRANDE PORTE - SP | R11: =_xlfn.XLOOKUP(O11,dimColaborador!A:A,dimColaborador!D:D) -> GRANDES CONTAS | S11: SAO JOSE DO RIO PRETO | T11: 01 STANDARD CASAL 1 CAMA QUEEN - 24/06/25 a 26/06/25 | U11: 45832 | V11: 45834 | W11: 4000 | X11: 470873 | Y11: 610 | Z11: 79.3 | AA11: 0 | AB11: 689.3
A12: 45832 | B12: 52473 | C12: 6699 | D12: TKT | E12: GOL LINHAS AÉREAS | F12: =_xlfn.XLOOKUP(E12,DEPARA!A:A,DEPARA!C:C,"Verificar") -> PASSAGEM | G12: FIRSTLAB IND. IMP. E EXP. DE PROD. PARA LAB. LTDA | H12: 056-EQUIPE COMERCIAL 4 | I12: =_xlfn.XLOOKUP(fatoG1[[#This Row],[Centro de Custo]],dimCentroCusto[Centro_Custo],dimCentroCusto[Codigo_CentroCusto]) -> #N/A | J12: =fatoG1[[#This Row],[Desc. C. Custo Cliente]] -> 056-EQUIPE COMERCIAL 4 | L12: VISITA COMERCIAL | N12: ALMEIDA/KHARLA NAYARA ABRANTES | O12: =_xlfn.XLOOKUP(N12,DEPARA!F:F,DEPARA!H:H,0) -> KHARLA NAYARA ABRANTES DE ALMEIDA | P12: =_xlfn.XLOOKUP(O12,dimColaborador!A:A,dimColaborador!B:B,0) -> 26175 | Q12: =_xlfn.XLOOKUP(O12,dimColaborador!A:A,dimColaborador!C:C,) -> GC -MÉDIO/GRANDE PORTE - NO/NE | R12: =_xlfn.XLOOKUP(O12,dimColaborador!A:A,dimColaborador!D:D) -> GRANDES CONTAS | S12: SAO JOSE DOS PINHAIS | T12: JPA*GIG/CWB | U12: 45930 | V12: 45930 | W12: 2140 | X12: 116838 | Y12: 713.9 | Z12: 51.67 | AA12: 57.11 | AB12: 822.68
A13: 45832 | B13: 52474 | C13: 6699 | D13: TKT | E13: TAM LINHAS AÉREAS | F13: =_xlfn.XLOOKUP(E13,DEPARA!A:A,DEPARA!C:C,"Verificar") -> PASSAGEM | G13: FIRSTLAB IND. IMP. E EXP. DE PROD. PARA LAB. LTDA | H13: 056-EQUIPE COMERCIAL 4 | I13: =_xlfn.XLOOKUP(fatoG1[[#This Row],[Centro de Custo]],dimCentroCusto[Centro_Custo],dimCentroCusto[Codigo_CentroCusto]) -> #N/A | J13: =fatoG1[[#This Row],[Desc. C. Custo Cliente]] -> 056-EQUIPE COMERCIAL 4 | L13: VISITA COMERCIAL | N13: ALMEIDA/KHARLA NAYARA ABRANTES | O13: =_xlfn.XLOOKUP(N13,DEPARA!F:F,DEPARA!H:H,0) -> KHARLA NAYARA ABRANTES DE ALMEIDA | P13: =_xlfn.XLOOKUP(O13,dimColaborador!A:A,dimColaborador!B:B,0) -> 26175 | Q13: =_xlfn.XLOOKUP(O13,dimColaborador!A:A,dimColaborador!C:C,) -> GC -MÉDIO/GRANDE PORTE - NO/NE | R13: =_xlfn.XLOOKUP(O13,dimColaborador!A:A,dimColaborador!D:D) -> GRANDES CONTAS | S13: SAO JOSE DOS PINHAIS | T13: CWB*GRU/JPA | U13: 45934 | V13: 45935 | W13: 2238 | X13: 311683 | Y13: 549.54 | Z13: 46.72 | AA13: 43.96 | AB13: 640.22
A14: 45832 | B14: 52475 | C14: 6699 | D14: TKT | E14: TAM LINHAS AÉREAS | F14: =_xlfn.XLOOKUP(E14,DEPARA!A:A,DEPARA!C:C,"Verificar") -> PASSAGEM | G14: FIRSTLAB IND. IMP. E EXP. DE PROD. PARA LAB. LTDA | H14: 056-EQUIPE COMERCIAL 4 | I14: =_xlfn.XLOOKUP(fatoG1[[#This Row],[Centro de Custo]],dimCentroCusto[Centro_Custo],dimCentroCusto[Codigo_CentroCusto]) -> #N/A | J14: =fatoG1[[#This Row],[Desc. C. Custo Cliente]] -> 056-EQUIPE COMERCIAL 4 | N14: ALMEIDA/KHARLA NAYARA ABRANTES | O14: =_xlfn.XLOOKUP(N14,DEPARA!F:F,DEPARA!H:H,0) -> KHARLA NAYARA ABRANTES DE ALMEIDA | P14: =_xlfn.XLOOKUP(O14,dimColaborador!A:A,dimColaborador!B:B,0) -> 26175 | Q14: =_xlfn.XLOOKUP(O14,dimColaborador!A:A,dimColaborador!C:C,) -> GC -MÉDIO/GRANDE PORTE - NO/NE | R14: =_xlfn.XLOOKUP(O14,dimColaborador!A:A,dimColaborador!D:D) -> GRANDES CONTAS | S14: SAO JOSE DOS PINHAIS | T14: FOR/BEL | U14: 45861 | V14: 45861 | W14: 2238 | X14: 311778 | Y14: 779.07 | Z14: 53.57 | AA14: 62.33 | AB14: 894.97
A15: 45832 | B15: 52476 | C15: 6699 | D15: TKT | E15: AZUL LINHAS AÉREAS BRASILEIRAS | F15: =_xlfn.XLOOKUP(E15,DEPARA!A:A,DEPARA!C:C,"Verificar") -> PASSAGEM | G15: FIRSTLAB IND. IMP. E EXP. DE PROD. PARA LAB. LTDA | H15: 056-EQUIPE COMERCIAL 4 | I15: =_xlfn.XLOOKUP(fatoG1[[#This Row],[Centro de Custo]],dimCentroCusto[Centro_Custo],dimCentroCusto[Codigo_CentroCusto]) -> #N/A | J15: =fatoG1[[#This Row],[Desc. C. Custo Cliente]] -> 056-EQUIPE COMERCIAL 4 | N15: NAYARA ABRANTES DE ALMEIDA/KHARLA | O15: =_xlfn.XLOOKUP(N15,DEPARA!F:F,DEPARA!H:H,0) -> KHARLA NAYARA ABRANTES DE ALMEIDA | P15: =_xlfn.XLOOKUP(O15,dimColaborador!A:A,dimColaborador!B:B,0) -> 26175 | Q15: =_xlfn.XLOOKUP(O15,dimColaborador!A:A,dimColaborador!C:C,) -> GC -MÉDIO/GRANDE PORTE - NO/NE | R15: =_xlfn.XLOOKUP(O15,dimColaborador!A:A,dimColaborador!D:D) -> GRANDES CONTAS | S15: SAO PAULO | T15: BEL/REC | U15: 45863 | V15: 45863 | W15: ETKT | X15: OWRWPN | Y15: 718.17 | Z15: 54.45 | AA15: 57.45 | AB15: 830.07
A16: 45832 | B16: 52480 | C16: 6699 | D16: TKT | E16: TAM LINHAS AÉREAS | F16: =_xlfn.XLOOKUP(E16,DEPARA!A:A,DEPARA!C:C,"Verificar") -> PASSAGEM | G16: FIRSTLAB IND. IMP. E EXP. DE PROD. PARA LAB. LTDA | H16: 049-EQUIPE COMERCIAL 1 | I16: =_xlfn.XLOOKUP(fatoG1[[#This Row],[Centro de Custo]],dimCentroCusto[Centro_Custo],dimCentroCusto[Codigo_CentroCusto]) -> #N/A | J16: =fatoG1[[#This Row],[Desc. C. Custo Cliente]] -> 049-EQUIPE COMERCIAL 1 | N16: OLIVEIRA/JOANA MARIA TEIXEIRA DE | O16: =_xlfn.XLOOKUP(N16,DEPARA!F:F,DEPARA!H:H,0) -> JOANA MARIA TEIXEIRA DE OLIVEIRA | P16: =_xlfn.XLOOKUP(O16,dimColaborador!A:A,dimColaborador!B:B,0) -> 26136 | Q16: =_xlfn.XLOOKUP(O16,dimColaborador!A:A,dimColaborador!C:C,) -> GRANDES CONTAS NACIONAIS | R16: =_xlfn.XLOOKUP(O16,dimColaborador!A:A,dimColaborador!D:D) -> GRANDES CONTAS | S16: SAO JOSE DOS PINHAIS | T16: VCP*BSB/POA*BSB/VCP | U16: 45881 | V16: 45883 | W16: 2238 | X16: 355435 | Y16: 619.2 | Z16: 86.34 | AA16: 49.54 | AB16: 755.08
A17: 45832 | B17: 52481 | C17: 6699 | D17: TKT | E17: AZUL LINHAS AÉREAS BRASILEIRAS | F17: =_xlfn.XLOOKUP(E17,DEPARA!A:A,DEPARA!C:C,"Verificar") -> PASSAGEM | G17: FIRSTLAB IND. IMP. E EXP. DE PROD. PARA LAB. LTDA | H17: 049-EQUIPE COMERCIAL 1 | I17: =_xlfn.XLOOKUP(fatoG1[[#This Row],[Centro de Custo]],dimCentroCusto[Centro_Custo],dimCentroCusto[Codigo_CentroCusto]) -> #N/A | J17: =fatoG1[[#This Row],[Desc. C. Custo Cliente]] -> 049-EQUIPE COMERCIAL 1 | N17: MARIA TEIXEIRA DE OLIVEIRA/JOANA | O17: =_xlfn.XLOOKUP(N17,DEPARA!F:F,DEPARA!H:H,0) -> JOANA MARIA TEIXEIRA DE OLIVEIRA | P17: =_xlfn.XLOOKUP(O17,dimColaborador!A:A,dimColaborador!B:B,0) -> 26136 | Q17: =_xlfn.XLOOKUP(O17,dimColaborador!A:A,dimColaborador!C:C,) -> GRANDES CONTAS NACIONAIS | R17: =_xlfn.XLOOKUP(O17,dimColaborador!A:A,dimColaborador!D:D) -> GRANDES CONTAS | S17: SAO PAULO | T17: VCP/FLN/VCP | U17: 45894 | V17: 45897 | W17: ETKT | X17: YIRY4P | Y17: 613.9 | Z17: 81.24 | AA17: 49.11 | AB17: 744.25
A18: 45834 | B18: 52566 | C18: 6699 | D18: TKT | E18: TAM LINHAS AÉREAS | F18: =_xlfn.XLOOKUP(E18,DEPARA!A:A,DEPARA!C:C,"Verificar") -> PASSAGEM | G18: FIRSTLAB IND. IMP. E EXP. DE PROD. PARA LAB. LTDA | H18: 049-EQUIPE COMERCIAL 1 | I18: =_xlfn.XLOOKUP(fatoG1[[#This Row],[Centro de Custo]],dimCentroCusto[Centro_Custo],dimCentroCusto[Codigo_CentroCusto]) -> #N/A | J18: =fatoG1[[#This Row],[Desc. C. Custo Cliente]] -> 049-EQUIPE COMERCIAL 1 | N18: VAZ/LETICIA CAMPOS DA SILVA | O18: =_xlfn.XLOOKUP(N18,DEPARA!F:F,DEPARA!H:H,0) -> LETICIA CAMPOS DA SILVA VAZ | P18: =_xlfn.XLOOKUP(O18,dimColaborador!A:A,dimColaborador!B:B,0) -> 26385 | Q18: =_xlfn.XLOOKUP(O18,dimColaborador!A:A,dimColaborador!C:C,) -> GC - MÉDIO/GRANDE PORTE - SUL | R18: =_xlfn.XLOOKUP(O18,dimColaborador!A:A,dimColaborador!D:D) -> GRANDES CONTAS | S18: SAO JOSE DOS PINHAIS | T18: CWB/IGU/CWB | U18: 45901 | V18: 45904 | W18: 2238 | X18: 642120 | Y18: 567.42 | Z18: 93.74 | AA18: 45.39 | AB18: 706.55
A19: 45834 | B19: 52567 | C19: 6699 | D19: TKT | E19: AZUL LINHAS AÉREAS BRASILEIRAS | F19: =_xlfn.XLOOKUP(E19,DEPARA!A:A,DEPARA!C:C,"Verificar") -> PASSAGEM | G19: FIRSTLAB IND. IMP. E EXP. DE PROD. PARA LAB. LTDA | H19: 049-EQUIPE COMERCIAL 1 | I19: =_xlfn.XLOOKUP(fatoG1[[#This Row],[Centro de Custo]],dimCentroCusto[Centro_Custo],dimCentroCusto[Codigo_CentroCusto]) -> #N/A | J19: =fatoG1[[#This Row],[Desc. C. Custo Cliente]] -> 049-EQUIPE COMERCIAL 1 | N19: VAZ/LETICIA | O19: =_xlfn.XLOOKUP(N19,DEPARA!F:F,DEPARA!H:H,0) -> LETICIA CAMPOS DA SILVA VAZ | P19: =_xlfn.XLOOKUP(O19,dimColaborador!A:A,dimColaborador!B:B,0) -> 26385 | Q19: =_xlfn.XLOOKUP(O19,dimColaborador!A:A,dimColaborador!C:C,) -> GC - MÉDIO/GRANDE PORTE - SUL | R19: =_xlfn.XLOOKUP(O19,dimColaborador!A:A,dimColaborador!D:D) -> GRANDES CONTAS | S19: SAO PAULO | T19: CWB/POA/CWB | U19: 45881 | V19: 45883 | W19: ETKT | X19: LQDHQH | Y19: 546 | Z19: 102.74 | AA19: 43.68 | AB19: 692.42
A20: 45834 | B20: 52571 | C20: 6699 | D20: TKT | E20: TAM LINHAS AÉREAS | F20: =_xlfn.XLOOKUP(E20,DEPARA!A:A,DEPARA!C:C,"Verificar") -> PASSAGEM | G20: FIRSTLAB IND. IMP. E EXP. DE PROD. PARA LAB. LTDA | H20: 056-EQUIPE COMERCIAL 4 | I20: =_xlfn.XLOOKUP(fatoG1[[#This Row],[Centro de Custo]],dimCentroCusto[Centro_Custo],dimCentroCusto[Codigo_CentroCusto]) -> #N/A | J20: =fatoG1[[#This Row],[Desc. C. Custo Cliente]] -> 056-EQUIPE COMERCIAL 4 | N20: GONCALVES/THIAGO NARCISO OLIVEIRA | O20: =_xlfn.XLOOKUP(N20,DEPARA!F:F,DEPARA!H:H,0) -> THIAGO NARCISO OLIVEIRA GONÇALVES | P20: =_xlfn.XLOOKUP(O20,dimColaborador!A:A,dimColaborador!B:B,0) -> 26516 | Q20: =_xlfn.XLOOKUP(O20,dimColaborador!A:A,dimColaborador!C:C,) -> DR - PRIME - CENTRO OESTE | R20: =_xlfn.XLOOKUP(O20,dimColaborador!A:A,dimColaborador!D:D) -> DISTRIBUIDOR | S20: SAO JOSE DOS PINHAIS | T20: BEL*BSB/THE | U20: 45856 | V20: 45856 | W20: 2238 | X20: 682440 | Y20: 926.99 | Z20: 54.45 | AA20: 74.16 | AB20: 1055.6
A21: 45834 | B21: 52572 | C21: 6699 | D21: TKT | E21: TAM LINHAS AÉREAS | F21: =_xlfn.XLOOKUP(E21,DEPARA!A:A,DEPARA!C:C,"Verificar") -> PASSAGEM | G21: FIRSTLAB IND. IMP. E EXP. DE PROD. PARA LAB. LTDA | H21: 056-EQUIPE COMERCIAL 4 | I21: =_xlfn.XLOOKUP(fatoG1[[#This Row],[Centro de Custo]],dimCentroCusto[Centro_Custo],dimCentroCusto[Codigo_CentroCusto]) -> #N/A | J21: =fatoG1[[#This Row],[Desc. C. Custo Cliente]] -> 056-EQUIPE COMERCIAL 4 | N21: GONCALVES/THIAGO NARCISO OLIVEIRA | O21: =_xlfn.XLOOKUP(N21,DEPARA!F:F,DEPARA!H:H,0) -> THIAGO NARCISO OLIVEIRA GONÇALVES | P21: =_xlfn.XLOOKUP(O21,dimColaborador!A:A,dimColaborador!B:B,0) -> 26516 | Q21: =_xlfn.XLOOKUP(O21,dimColaborador!A:A,dimColaborador!C:C,) -> DR - PRIME - CENTRO OESTE | R21: =_xlfn.XLOOKUP(O21,dimColaborador!A:A,dimColaborador!D:D) -> DISTRIBUIDOR | S21: SAO JOSE DOS PINHAIS | T21: THE*FOR/SSA*BSB/THE | U21: 45859 | V21: 45862 | W21: 2238 | X21: 682552 | Y21: 1937.15 | Z21: 91.71 | AA21: 154.97 | AB21: 2183.83
A22: 45834 | B22: 52573 | C22: 6699 | D22: TKT | E22: AZUL LINHAS AÉREAS BRASILEIRAS | F22: =_xlfn.XLOOKUP(E22,DEPARA!A:A,DEPARA!C:C,"Verificar") -> PASSAGEM | G22: FIRSTLAB IND. IMP. E EXP. DE PROD. PARA LAB. LTDA | H22: 056-EQUIPE COMERCIAL 4 | I22: =_xlfn.XLOOKUP(fatoG1[[#This Row],[Centro de Custo]],dimCentroCusto[Centro_Custo],dimCentroCusto[Codigo_CentroCusto]) -> #N/A | J22: =fatoG1[[#This Row],[Desc. C. Custo Cliente]] -> 056-EQUIPE COMERCIAL 4 | N22: NARCISO OLIVEIRA GONCALVES/THIAGO | O22: =_xlfn.XLOOKUP(N22,DEPARA!F:F,DEPARA!H:H,0) -> THIAGO NARCISO OLIVEIRA GONÇALVES | P22: =_xlfn.XLOOKUP(O22,dimColaborador!A:A,dimColaborador!B:B,0) -> 26516 | Q22: =_xlfn.XLOOKUP(O22,dimColaborador!A:A,dimColaborador!C:C,) -> DR - PRIME - CENTRO OESTE | R22: =_xlfn.XLOOKUP(O22,dimColaborador!A:A,dimColaborador!D:D) -> DISTRIBUIDOR | S22: SAO PAULO | T22: MAO/BEL | U22: 45854 | V22: 45854 | W22: ETKT | X22: VDM3HR | Y22: 713.18 | Z22: 51.07 | AA22: 57.05 | AB22: 821.3
A23: 45834 | B23: 52574 | C23: 6699 | D23: TKT | E23: GOL LINHAS AÉREAS | F23: =_xlfn.XLOOKUP(E23,DEPARA!A:A,DEPARA!C:C,"Verificar") -> PASSAGEM | G23: FIRSTLAB IND. IMP. E EXP. DE PROD. PARA LAB. LTDA | H23: 056-EQUIPE COMERCIAL 4 | I23: =_xlfn.XLOOKUP(fatoG1[[#This Row],[Centro de Custo]],dimCentroCusto[Centro_Custo],dimCentroCusto[Codigo_CentroCusto]) -> #N/A | J23: =fatoG1[[#This Row],[Desc. C. Custo Cliente]] -> 056-EQUIPE COMERCIAL 4 | N23: GONCALVES/THIAGO NARCISO OLIVEIRA | O23: =_xlfn.XLOOKUP(N23,DEPARA!F:F,DEPARA!H:H,0) -> THIAGO NARCISO OLIVEIRA GONÇALVES | P23: =_xlfn.XLOOKUP(O23,dimColaborador!A:A,dimColaborador!B:B,0) -> 26516 | Q23: =_xlfn.XLOOKUP(O23,dimColaborador!A:A,dimColaborador!C:C,) -> DR - PRIME - CENTRO OESTE | R23: =_xlfn.XLOOKUP(O23,dimColaborador!A:A,dimColaborador!D:D) -> DISTRIBUIDOR | S23: SAO JOSE DOS PINHAIS | T23: THE*BSB/MAO | U23: 45852 | V23: 45852 | W23: 2140 | X23: 273116 | Y23: 1352.79 | Z23: 47.44 | AA23: 108.22 | AB23: 1508.45
A24: 45838 | B24: 52681 | C24: 6699 | D24: CAR | E24: MOVIDA RENT A CAR | F24: =_xlfn.XLOOKUP(E24,DEPARA!A:A,DEPARA!C:C,"Verificar") -> LOCAÇÃO DE VEÍCULOS | G24: FIRSTLAB IND. IMP. E EXP. DE PROD. PARA LAB. LTDA | H24: 049-EQUIPE COMERCIAL 1 | I24: =_xlfn.XLOOKUP(fatoG1[[#This Row],[Centro de Custo]],dimCentroCusto[Centro_Custo],dimCentroCusto[Codigo_CentroCusto]) -> #N/A | J24: =fatoG1[[#This Row],[Desc. C. Custo Cliente]] -> 049-EQUIPE COMERCIAL 1 | N24: LETICIA CAMPOS DA SILVA VAZ | O24: =_xlfn.XLOOKUP(N24,DEPARA!F:F,DEPARA!H:H,0) -> LETICIA CAMPOS DA SILVA VAZ | P24: =_xlfn.XLOOKUP(O24,dimColaborador!A:A,dimColaborador!B:B,0) -> 26385 | Q24: =_xlfn.XLOOKUP(O24,dimColaborador!A:A,dimColaborador!C:C,) -> GC - MÉDIO/GRANDE PORTE - SUL | R24: =_xlfn.XLOOKUP(O24,dimColaborador!A:A,dimColaborador!D:D) -> GRANDES CONTAS | S24: CURITIBA | T24: 09/12/24 a 13/12/24 - D - AEROP. INTER. PORTO ALEGRE - SALGA | U24: 45635 | V24: 45639 | X24: 0 | Y24: 0 | Z24: 58.4 | AA24: 0 | AB24: 58.4
A25: 45846 | B25: 51359 | C25: 6729 | D25: HTL | E25: NORTH HOTEL | F25: =_xlfn.XLOOKUP(E25,DEPARA!A:A,DEPARA!C:C,"Verificar") -> HOSPEDAGEM | G25: FIRSTLAB IND. IMP. E EXP. DE PROD. PARA LAB. LTDA | H25: 049-EQUIPE COMERCIAL 1 | I25: =_xlfn.XLOOKUP(fatoG1[[#This Row],[Centro de Custo]],dimCentroCusto[Centro_Custo],dimCentroCusto[Codigo_CentroCusto]) -> #N/A | J25: =fatoG1[[#This Row],[Desc. C. Custo Cliente]] -> 049-EQUIPE COMERCIAL 1 | N25: VAZ/LETICIA CAMPOS DA SILVA | O25: =_xlfn.XLOOKUP(N25,DEPARA!F:F,DEPARA!H:H,0) -> LETICIA CAMPOS DA SILVA VAZ | P25: =_xlfn.XLOOKUP(O25,dimColaborador!A:A,dimColaborador!B:B,0) -> 26385 | Q25: =_xlfn.XLOOKUP(O25,dimColaborador!A:A,dimColaborador!C:C,) -> GC - MÉDIO/GRANDE PORTE - SUL | R25: =_xlfn.XLOOKUP(O25,dimColaborador!A:A,dimColaborador!D:D) -> GRANDES CONTAS | S25: CHAPECÓ | T25: 01 SUITE EXECUTIVA LUXO - 07/07/25 a 08/07/25 | U25: 45845 | V25: 45846 | W25: 4 | X25: 771960 | Y25: 265.33 | Z25: 10.61 | AA25: 0 | AB25: 275.94
A26: 45841 | B26: 52413 | C26: 6729 | D26: HTL | E26: OMNIBEES | F26: =_xlfn.XLOOKUP(E26,DEPARA!A:A,DEPARA!C:C,"Verificar") -> HOSPEDAGEM | G26: FIRSTLAB IND. IMP. E EXP. DE PROD. PARA LAB. LTDA | H26: 055-EQUIPE COMERCIAL 3 | I26: =_xlfn.XLOOKUP(fatoG1[[#This Row],[Centro de Custo]],dimCentroCusto[Centro_Custo],dimCentroCusto[Codigo_CentroCusto]) -> #N/A | J26: =fatoG1[[#This Row],[Desc. C. Custo Cliente]] -> 055-EQUIPE COMERCIAL 3 | L26: VISITA CLIENTES DA REGIÃO | N26: LUZ/MARCIO ARRUDA | O26: =_xlfn.XLOOKUP(N26,DEPARA!F:F,DEPARA!H:H,0) -> MARCIO ARRUDA LUZ | P26: =_xlfn.XLOOKUP(O26,dimColaborador!A:A,dimColaborador!B:B,0) -> 25745 | Q26: =_xlfn.XLOOKUP(O26,dimColaborador!A:A,dimColaborador!C:C,) -> GC - MÉDIO/GRANDE PORTE - SE/CO | R26: =_xlfn.XLOOKUP(O26,dimColaborador!A:A,dimColaborador!D:D) -> GRANDES CONTAS | S26: SAO PAULO | T26: 01 APARTAMENTO VISTA PISCINA - 02/07/25 a 03/07/25 | U26: 45840 | V26: 45841 | W26: RES0 | X26: 00161- | Y26: 182.4 | Z26: 8 | AA26: 0 | AB26: 190.4
A27: 45842 | B27: 52414 | C27: 6729 | D27: HTL | E27: TRANSAMERICA FIT VITÓRIA RETA DA PENHA | F27: =_xlfn.XLOOKUP(E27,DEPARA!A:A,DEPARA!C:C,"Verificar") -> HOSPEDAGEM | G27: FIRSTLAB IND. IMP. E EXP. DE PROD. PARA LAB. LTDA | H27: 055-EQUIPE COMERCIAL 3 | I27: =_xlfn.XLOOKUP(fatoG1[[#This Row],[Centro de Custo]],dimCentroCusto[Centro_Custo],dimCentroCusto[Codigo_CentroCusto]) -> #N/A | J27: =fatoG1[[#This Row],[Desc. C. Custo Cliente]] -> 055-EQUIPE COMERCIAL 3 | L27: VISITA CLIENTES DA REGIÃO | N27: LUZ/MARCIO ARRUDA | O27: =_xlfn.XLOOKUP(N27,DEPARA!F:F,DEPARA!H:H,0) -> MARCIO ARRUDA LUZ | P27: =_xlfn.XLOOKUP(O27,dimColaborador!A:A,dimColaborador!B:B,0) -> 25745 | Q27: =_xlfn.XLOOKUP(O27,dimColaborador!A:A,dimColaborador!C:C,) -> GC - MÉDIO/GRANDE PORTE - SE/CO | R27: =_xlfn.XLOOKUP(O27,dimColaborador!A:A,dimColaborador!D:D) -> GRANDES CONTAS | S27: VITORIA | T27: 01 STANDARD QUEEN NÃO FUMANTE - 03/07/25 a 04/07/25 | U27: 45841 | V27: 45842 | W27: 4000 | X27: 474661 | Y27: 303.45 | Z27: 15.17 | AA27: 0 | AB27: 318.62
A28: 45839 | B28: 52534 | C28: 6729 | D28: HTL | E28: HOTEL SANTA CRUZ | F28: =_xlfn.XLOOKUP(E28,DEPARA!A:A,DEPARA!C:C,"Verificar") -> HOSPEDAGEM | G28: FIRSTLAB IND. IMP. E EXP. DE PROD. PARA LAB. LTDA | H28: 049-EQUIPE COMERCIAL 1 | I28: =_xlfn.XLOOKUP(fatoG1[[#This Row],[Centro de Custo]],dimCentroCusto[Centro_Custo],dimCentroCusto[Codigo_CentroCusto]) -> #N/A | J28: =fatoG1[[#This Row],[Desc. C. Custo Cliente]] -> 049-EQUIPE COMERCIAL 1 | N28: VAZ/LETICIA CAMPOS DA SILVA | O28: =_xlfn.XLOOKUP(N28,DEPARA!F:F,DEPARA!H:H,0) -> LETICIA CAMPOS DA SILVA VAZ | P28: =_xlfn.XLOOKUP(O28,dimColaborador!A:A,dimColaborador!B:B,0) -> 26385 | Q28: =_xlfn.XLOOKUP(O28,dimColaborador!A:A,dimColaborador!C:C,) -> GC - MÉDIO/GRANDE PORTE - SUL | R28: =_xlfn.XLOOKUP(O28,dimColaborador!A:A,dimColaborador!D:D) -> GRANDES CONTAS | S28: SANTA CRUZ DO SUL | T28: 01 SUPERIOR - 30/06/25 a 01/07/25 | U28: 45838 | V28: 45839 | W28: 4 | X28: 845934 | Y28: 312.19 | Z28: 0 | AA28: 0 | AB28: 312.19
A29: 45840 | B29: 52535 | C29: 6729 | D29: HTL | E29: TRI HOTEL SMART CAXIAS | F29: =_xlfn.XLOOKUP(E29,DEPARA!A:A,DEPARA!C:C,"Verificar") -> HOSPEDAGEM | G29: FIRSTLAB IND. IMP. E EXP. DE PROD. PARA LAB. LTDA | H29: 049-EQUIPE COMERCIAL 1 | I29: =_xlfn.XLOOKUP(fatoG1[[#This Row],[Centro de Custo]],dimCentroCusto[Centro_Custo],dimCentroCusto[Codigo_CentroCusto]) -> #N/A | J29: =fatoG1[[#This Row],[Desc. C. Custo Cliente]] -> 049-EQUIPE COMERCIAL 1 | N29: VAZ/LETICIA CAMPOS DA SILVA | O29: =_xlfn.XLOOKUP(N29,DEPARA!F:F,DEPARA!H:H,0) -> LETICIA CAMPOS DA SILVA VAZ | P29: =_xlfn.XLOOKUP(O29,dimColaborador!A:A,dimColaborador!B:B,0) -> 26385 | Q29: =_xlfn.XLOOKUP(O29,dimColaborador!A:A,dimColaborador!C:C,) -> GC - MÉDIO/GRANDE PORTE - SUL | R29: =_xlfn.XLOOKUP(O29,dimColaborador!A:A,dimColaborador!D:D) -> GRANDES CONTAS | S29: CAXIAS DO SUL | T29: 01 INDIVIDUAL LUXO - 01/07/25 a 02/07/25 | U29: 45839 | V29: 45840 | W29: 4000 | X29: 480881 | Y29: 229 | Z29: 0 | AA29: 0 | AB29: 229
A30: 45841 | B30: 52536 | C30: 6729 | D30: HTL | E30: IBIS STYLES PORTO ALEGRE CENTRO | F30: =_xlfn.XLOOKUP(E30,DEPARA!A:A,DEPARA!C:C,"Verificar") -> HOSPEDAGEM | G30: FIRSTLAB IND. IMP. E EXP. DE PROD. PARA LAB. LTDA | H30: 049-EQUIPE COMERCIAL 1 | I30: =_xlfn.XLOOKUP(fatoG1[[#This Row],[Centro de Custo]],dimCentroCusto[Centro_Custo],dimCentroCusto[Codigo_CentroCusto]) -> #N/A | J30: =fatoG1[[#This Row],[Desc. C. Custo Cliente]] -> 049-EQUIPE COMERCIAL 1 | N30: VAZ/LETICIA CAMPOS DA SILVA | O30: =_xlfn.XLOOKUP(N30,DEPARA!F:F,DEPARA!H:H,0) -> LETICIA CAMPOS DA SILVA VAZ | P30: =_xlfn.XLOOKUP(O30,dimColaborador!A:A,dimColaborador!B:B,0) -> 26385 | Q30: =_xlfn.XLOOKUP(O30,dimColaborador!A:A,dimColaborador!C:C,) -> GC - MÉDIO/GRANDE PORTE - SUL | R30: =_xlfn.XLOOKUP(O30,dimColaborador!A:A,dimColaborador!D:D) -> GRANDES CONTAS | S30: PORTO ALEGRE | T30: 01 QUARTO STANDARD COM 1 CAMA DE CASAL - 02/07/25 a 03/07/2 | U30: 45840 | V30: 45841 | W30: 4 | X30: 845944 | Y30: 309 | Z30: 15.45 | AA30: 0 | AB30: 324.45
A31: 45839 | B31: 52715 | C31: 6729 | D31: TKT | E31: GOL LINHAS AÉREAS | F31: =_xlfn.XLOOKUP(E31,DEPARA!A:A,DEPARA!C:C,"Verificar") -> PASSAGEM | G31: FIRSTLAB IND. IMP. E EXP. DE PROD. PARA LAB. LTDA | H31: 056-EQUIPE COMERCIAL 4 | I31: =_xlfn.XLOOKUP(fatoG1[[#This Row],[Centro de Custo]],dimCentroCusto[Centro_Custo],dimCentroCusto[Codigo_CentroCusto]) -> #N/A | J31: =fatoG1[[#This Row],[Desc. C. Custo Cliente]] -> 056-EQUIPE COMERCIAL 4 | L31: VISITA A CLIENTE | N31: NARCISO OLIVEIRA GONCALVES/THIAGO | O31: =_xlfn.XLOOKUP(N31,DEPARA!F:F,DEPARA!H:H,0) -> THIAGO NARCISO OLIVEIRA GONÇALVES | P31: =_xlfn.XLOOKUP(O31,dimColaborador!A:A,dimColaborador!B:B,0) -> 26516 | Q31: =_xlfn.XLOOKUP(O31,dimColaborador!A:A,dimColaborador!C:C,) -> DR - PRIME - CENTRO OESTE | R31: =_xlfn.XLOOKUP(O31,dimColaborador!A:A,dimColaborador!D:D) -> DISTRIBUIDOR | S31: SAO JOSE DOS PINHAIS | T31: THE*BSB/REC*SSA*BSB/THE | U31: 45846 | V31: 45850 | W31: 2140 | X31: 542776 | Y31: 3288.38 | Z31: 106.33 | AA31: 263.07 | AB31: 3657.78
A32: 45839 | B32: 52716 | C32: 6729 | D32: TKT | E32: TAM LINHAS AÉREAS | F32: =_xlfn.XLOOKUP(E32,DEPARA!A:A,DEPARA!C:C,"Verificar") -> PASSAGEM | G32: FIRSTLAB IND. IMP. E EXP. DE PROD. PARA LAB. LTDA | H32: 055-EQUIPE COMERCIAL 3 | I32: =_xlfn.XLOOKUP(fatoG1[[#This Row],[Centro de Custo]],dimCentroCusto[Centro_Custo],dimCentroCusto[Codigo_CentroCusto]) -> #N/A | J32: =fatoG1[[#This Row],[Desc. C. Custo Cliente]] -> 055-EQUIPE COMERCIAL 3 | L32: VISITA CLIENTES DA REGIÃO/ TREINAMENTO | N32: LUZ/MARCIO ARRUDA | O32: =_xlfn.XLOOKUP(N32,DEPARA!F:F,DEPARA!H:H,0) -> MARCIO ARRUDA LUZ | P32: =_xlfn.XLOOKUP(O32,dimColaborador!A:A,dimColaborador!B:B,0) -> 25745 | Q32: =_xlfn.XLOOKUP(O32,dimColaborador!A:A,dimColaborador!C:C,) -> GC - MÉDIO/GRANDE PORTE - SE/CO | R32: =_xlfn.XLOOKUP(O32,dimColaborador!A:A,dimColaborador!D:D) -> GRANDES CONTAS | S32: SAO JOSE DOS PINHAIS | T32: GIG*GRU/UDI | U32: 45868 | V32: 45868 | W32: 2239 | X32: 319469 | Y32: 401.58 | Z32: 34.11 | AA32: 32.13 | AB32: 467.82
A33: 45839 | B33: 52717 | C33: 6729 | D33: TKT | E33: GOL LINHAS AÉREAS | F33: =_xlfn.XLOOKUP(E33,DEPARA!A:A,DEPARA!C:C,"Verificar") -> PASSAGEM | G33: FIRSTLAB IND. IMP. E EXP. DE PROD. PARA LAB. LTDA | H33: 055-EQUIPE COMERCIAL 3 | I33: =_xlfn.XLOOKUP(fatoG1[[#This Row],[Centro de Custo]],dimCentroCusto[Centro_Custo],dimCentroCusto[Codigo_CentroCusto]) -> #N/A | J33: =fatoG1[[#This Row],[Desc. C. Custo Cliente]] -> 055-EQUIPE COMERCIAL 3 | L33: VISITA CLIENTES DA REGIÃO/ TREINAMENTO | N33: LUZ/MARCIO ARRUDA | O33: =_xlfn.XLOOKUP(N33,DEPARA!F:F,DEPARA!H:H,0) -> MARCIO ARRUDA LUZ | P33: =_xlfn.XLOOKUP(O33,dimColaborador!A:A,dimColaborador!B:B,0) -> 25745 | Q33: =_xlfn.XLOOKUP(O33,dimColaborador!A:A,dimColaborador!C:C,) -> GC - MÉDIO/GRANDE PORTE - SE/CO | R33: =_xlfn.XLOOKUP(O33,dimColaborador!A:A,dimColaborador!D:D) -> GRANDES CONTAS | S33: SAO JOSE DOS PINHAIS | T33: UDI*CGH/SDU | U33: 45870 | V33: 45870 | W33: 2140 | X33: 543838 | Y33: 445.9 | Z33: 40.96 | AA33: 35.67 | AB33: 522.53
A34: 45839 | B34: 52718 | C34: 6729 | D34: TKT | E34: TAM LINHAS AÉREAS | F34: =_xlfn.XLOOKUP(E34,DEPARA!A:A,DEPARA!C:C,"Verificar") -> PASSAGEM | G34: FIRSTLAB IND. IMP. E EXP. DE PROD. PARA LAB. LTDA | H34: 055-EQUIPE COMERCIAL 3 | I34: =_xlfn.XLOOKUP(fatoG1[[#This Row],[Centro de Custo]],dimCentroCusto[Centro_Custo],dimCentroCusto[Codigo_CentroCusto]) -> #N/A | J34: =fatoG1[[#This Row],[Desc. C. Custo Cliente]] -> 055-EQUIPE COMERCIAL 3 | L34: VISITA CLIENTES DA REGIÃO | N34: LUZ/MARCIO ARRUDA | O34: =_xlfn.XLOOKUP(N34,DEPARA!F:F,DEPARA!H:H,0) -> MARCIO ARRUDA LUZ | P34: =_xlfn.XLOOKUP(O34,dimColaborador!A:A,dimColaborador!B:B,0) -> 25745 | Q34: =_xlfn.XLOOKUP(O34,dimColaborador!A:A,dimColaborador!C:C,) -> GC - MÉDIO/GRANDE PORTE - SE/CO | R34: =_xlfn.XLOOKUP(O34,dimColaborador!A:A,dimColaborador!D:D) -> GRANDES CONTAS | S34: SAO JOSE DOS PINHAIS | T34: SDU*BSB/GYN | U34: 45944 | V34: 45944 | W34: 2239 | X34: 323151 | Y34: 301.86 | Z34: 59.95 | AA34: 24.15 | AB34: 385.96
A35: 45839 | B35: 52719 | C35: 6729 | D35: TKT | E35: GOL LINHAS AÉREAS | F35: =_xlfn.XLOOKUP(E35,DEPARA!A:A,DEPARA!C:C,"Verificar") -> PASSAGEM | G35: FIRSTLAB IND. IMP. E EXP. DE PROD. PARA LAB. LTDA | H35: 055-EQUIPE COMERCIAL 3 | I35: =_xlfn.XLOOKUP(fatoG1[[#This Row],[Centro de Custo]],dimCentroCusto[Centro_Custo],dimCentroCusto[Codigo_CentroCusto]) -> #N/A | J35: =fatoG1[[#This Row],[Desc. C. Custo Cliente]] -> 055-EQUIPE COMERCIAL 3 | L35: VISITA CLIENTES DA REGIÃO | N35: LUZ/MARCIO ARRUDA | O35: =_xlfn.XLOOKUP(N35,DEPARA!F:F,DEPARA!H:H,0) -> MARCIO ARRUDA LUZ | P35: =_xlfn.XLOOKUP(O35,dimColaborador!A:A,dimColaborador!B:B,0) -> 25745 | Q35: =_xlfn.XLOOKUP(O35,dimColaborador!A:A,dimColaborador!C:C,) -> GC - MÉDIO/GRANDE PORTE - SE/CO | R35: =_xlfn.XLOOKUP(O35,dimColaborador!A:A,dimColaborador!D:D) -> GRANDES CONTAS | S35: SAO JOSE DOS PINHAIS | T35: BSB/GIG | U35: 45947 | V35: 45947 | W35: 2140 | X35: 546648 | Y35: 319.9 | Z35: 30.95 | AA35: 25.59 | AB35: 376.44
A36: 45839 | B36: 52724 | C36: 6729 | D36: TKT | E36: TAM LINHAS AÉREAS | F36: =_xlfn.XLOOKUP(E36,DEPARA!A:A,DEPARA!C:C,"Verificar") -> PASSAGEM | G36: FIRSTLAB IND. IMP. E EXP. DE PROD. PARA LAB. LTDA | H36: 055-EQUIPE COMERCIAL 3 | I36: =_xlfn.XLOOKUP(fatoG1[[#This Row],[Centro de Custo]],dimCentroCusto[Centro_Custo],dimCentroCusto[Codigo_CentroCusto]) -> #N/A | J36: =fatoG1[[#This Row],[Desc. C. Custo Cliente]] -> 055-EQUIPE COMERCIAL 3 | L36: VISITA CLIENTES DA REGIÃO | N36: LUZ/MARCIO ARRUDA | O36: =_xlfn.XLOOKUP(N36,DEPARA!F:F,DEPARA!H:H,0) -> MARCIO ARRUDA LUZ | P36: =_xlfn.XLOOKUP(O36,dimColaborador!A:A,dimColaborador!B:B,0) -> 25745 | Q36: =_xlfn.XLOOKUP(O36,dimColaborador!A:A,dimColaborador!C:C,) -> GC - MÉDIO/GRANDE PORTE - SE/CO | R36: =_xlfn.XLOOKUP(O36,dimColaborador!A:A,dimColaborador!D:D) -> GRANDES CONTAS | S36: SAO JOSE DOS PINHAIS | T36: CGR*GRU/CGB | U36: 45953 | V36: 45953 | W36: 2239 | X36: 355175 | Y36: 426.56 | Z36: 36.67 | AA36: 34.12 | AB36: 497.35
A37: 45839 | B37: 52725 | C37: 6729 | D37: TKT | E37: TAM LINHAS AÉREAS | F37: =_xlfn.XLOOKUP(E37,DEPARA!A:A,DEPARA!C:C,"Verificar") -> PASSAGEM | G37: FIRSTLAB IND. IMP. E EXP. DE PROD. PARA LAB. LTDA | H37: 055-EQUIPE COMERCIAL 3 | I37: =_xlfn.XLOOKUP(fatoG1[[#This Row],[Centro de Custo]],dimCentroCusto[Centro_Custo],dimCentroCusto[Codigo_CentroCusto]) -> #N/A | J37: =fatoG1[[#This Row],[Desc. C. Custo Cliente]] -> 055-EQUIPE COMERCIAL 3 | L37: VISITA CLIENTES DA REGIÃO | N37: LUZ/MARCIO ARRUDA | O37: =_xlfn.XLOOKUP(N37,DEPARA!F:F,DEPARA!H:H,0) -> MARCIO ARRUDA LUZ | P37: =_xlfn.XLOOKUP(O37,dimColaborador!A:A,dimColaborador!B:B,0) -> 25745 | Q37: =_xlfn.XLOOKUP(O37,dimColaborador!A:A,dimColaborador!C:C,) -> GC - MÉDIO/GRANDE PORTE - SE/CO | R37: =_xlfn.XLOOKUP(O37,dimColaborador!A:A,dimColaborador!D:D) -> GRANDES CONTAS | S37: SAO JOSE DOS PINHAIS | T37: GIG*BSB/CGR | U37: 45951 | V37: 45951 | W37: 2239 | X37: 355198 | Y37: 335.4 | Z37: 34.11 | AA37: 26.83 | AB37: 396.34
A38: 45839 | B38: 52726 | C38: 6729 | D38: TKT | E38: TAM LINHAS AÉREAS | F38: =_xlfn.XLOOKUP(E38,DEPARA!A:A,DEPARA!C:C,"Verificar") -> PASSAGEM | G38: FIRSTLAB IND. IMP. E EXP. DE PROD. PARA LAB. LTDA | H38: 055-EQUIPE COMERCIAL 3 | I38: =_xlfn.XLOOKUP(fatoG1[[#This Row],[Centro de Custo]],dimCentroCusto[Centro_Custo],dimCentroCusto[Codigo_CentroCusto]) -> #N/A | J38: =fatoG1[[#This Row],[Desc. C. Custo Cliente]] -> 055-EQUIPE COMERCIAL 3 | L38: VISITA CLIENTES DA REGIÃO | N38: LUZ/MARCIO ARRUDA | O38: =_xlfn.XLOOKUP(N38,DEPARA!F:F,DEPARA!H:H,0) -> MARCIO ARRUDA LUZ | P38: =_xlfn.XLOOKUP(O38,dimColaborador!A:A,dimColaborador!B:B,0) -> 25745 | Q38: =_xlfn.XLOOKUP(O38,dimColaborador!A:A,dimColaborador!C:C,) -> GC - MÉDIO/GRANDE PORTE - SE/CO | R38: =_xlfn.XLOOKUP(O38,dimColaborador!A:A,dimColaborador!D:D) -> GRANDES CONTAS | S38: SAO JOSE DOS PINHAIS | T38: CGB*GRU/GIG | U38: 45954 | V38: 45954 | W38: 2239 | X38: 355944 | Y38: 444.53 | Z38: 48.75 | AA38: 35.56 | AB38: 528.84
A39: 45839 | B39: 52805 | C39: 6729 | D39: CAR | E39: MOVIDA RENT A CAR | F39: =_xlfn.XLOOKUP(E39,DEPARA!A:A,DEPARA!C:C,"Verificar") -> LOCAÇÃO DE VEÍCULOS | G39: FIRSTLAB IND. IMP. E EXP. DE PROD. PARA LAB. LTDA | H39: 054-EQUIPE COMERCIAL 2 | I39: =_xlfn.XLOOKUP(fatoG1[[#This Row],[Centro de Custo]],dimCentroCusto[Centro_Custo],dimCentroCusto[Codigo_CentroCusto]) -> #N/A | J39: =fatoG1[[#This Row],[Desc. C. Custo Cliente]] -> 054-EQUIPE COMERCIAL 2 | N39: NUEVO/IGOR MARIANO | O39: =_xlfn.XLOOKUP(N39,DEPARA!F:F,DEPARA!H:H,0) -> IGOR MARIANO NUEVO | P39: =_xlfn.XLOOKUP(O39,dimColaborador!A:A,dimColaborador!B:B,0) -> 24466 | Q39: =_xlfn.XLOOKUP(O39,dimColaborador!A:A,dimColaborador!C:C,) -> CONSULTOR DESLIGADO | R39: =_xlfn.XLOOKUP(O39,dimColaborador!A:A,dimColaborador!D:D) -> CONSULTOR DESLIGADO | S39: CURITIBA | T39: 22/12/23 a 22/12/23 - H - SÃO PAULO - TATUAPÉ - MARGINAL TIE | U39: 45282 | V39: 45282 | W39: MV2D | X39: CA4UHA | Y39: 0 | Z39: 130.16 | AA39: 0 | AB39: 130.16
A40: 45853 | B40: 50212 | C40: 6765 | D40: CAR | E40: LOCALIZA | F40: =_xlfn.XLOOKUP(E40,DEPARA!A:A,DEPARA!C:C,"Verificar") -> LOCAÇÃO DE VEÍCULOS | G40: FIRSTLAB IND. IMP. E EXP. DE PROD. PARA LAB. LTDA | H40: 056-EQUIPE COMERCIAL 4 | I40: =_xlfn.XLOOKUP(fatoG1[[#This Row],[Centro de Custo]],dimCentroCusto[Centro_Custo],dimCentroCusto[Codigo_CentroCusto]) -> #N/A | J40: =fatoG1[[#This Row],[Desc. C. Custo Cliente]] -> 056-EQUIPE COMERCIAL 4 | L40: VIAGEM PARA VISITA DE CLIENTES DA REGIÃO. | N40: ALMEIDA/KHARLA NAYARA ABRANTES | O40: =_xlfn.XLOOKUP(N40,DEPARA!F:F,DEPARA!H:H,0) -> KHARLA NAYARA ABRANTES DE ALMEIDA | P40: =_xlfn.XLOOKUP(O40,dimColaborador!A:A,dimColaborador!B:B,0) -> 26175 | Q40: =_xlfn.XLOOKUP(O40,dimColaborador!A:A,dimColaborador!C:C,) -> GC -MÉDIO/GRANDE PORTE - NO/NE | R40: =_xlfn.XLOOKUP(O40,dimColaborador!A:A,dimColaborador!D:D) -> GRANDES CONTAS | S40: SAO JOSE DOS PINHAIS | T40: 14/05/25 a 15/05/25 - FIAT ARGO, ONIX LT, VW POLO, PEUGEOT 2 | U40: 45791 | V40: 45792 | W40: 2118 | X40: 492533 | Y40: 373.75 | Z40: 204.99 | AA40: 0 | AB40: 578.74
A41: 45853 | B41: 51456 | C41: 6765 | D41: CAR | E41: LOCALIZA | F41: =_xlfn.XLOOKUP(E41,DEPARA!A:A,DEPARA!C:C,"Verificar") -> LOCAÇÃO DE VEÍCULOS | G41: FIRSTLAB IND. IMP. E EXP. DE PROD. PARA LAB. LTDA | H41: 049-EQUIPE COMERCIAL 1 | I41: =_xlfn.XLOOKUP(fatoG1[[#This Row],[Centro de Custo]],dimCentroCusto[Centro_Custo],dimCentroCusto[Codigo_CentroCusto]) -> #N/A | J41: =fatoG1[[#This Row],[Desc. C. Custo Cliente]] -> 049-EQUIPE COMERCIAL 1 | N41: OLIVEIRA/JOANA MARIA TEIXEIRA DE | O41: =_xlfn.XLOOKUP(N41,DEPARA!F:F,DEPARA!H:H,0) -> JOANA MARIA TEIXEIRA DE OLIVEIRA | P41: =_xlfn.XLOOKUP(O41,dimColaborador!A:A,dimColaborador!B:B,0) -> 26136 | Q41: =_xlfn.XLOOKUP(O41,dimColaborador!A:A,dimColaborador!C:C,) -> GRANDES CONTAS NACIONAIS | R41: =_xlfn.XLOOKUP(O41,dimColaborador!A:A,dimColaborador!D:D) -> GRANDES CONTAS | S41: SAO JOSE DOS PINHAIS | T41: 27/05/25 a 28/05/25 - RENAULT KWID, FIAT MOBI (1.0) OU SIMIL | U41: 45804 | V41: 45805 | W41: 2118 | X41: 592019 | Y41: 199.15 | Z41: 54.95 | AA41: 0 | AB41: 254.1
A42: 45847 | B42: 52842 | C42: 6765 | D42: HTL | E42: IBIS BUDGET RECIFE JABOATAO | F42: =_xlfn.XLOOKUP(E42,DEPARA!A:A,DEPARA!C:C,"Verificar") -> HOSPEDAGEM | G42: FIRSTLAB IND. IMP. E EXP. DE PROD. PARA LAB. LTDA | H42: 056-EQUIPE COMERCIAL 4 | I42: =_xlfn.XLOOKUP(fatoG1[[#This Row],[Centro de Custo]],dimCentroCusto[Centro_Custo],dimCentroCusto[Codigo_CentroCusto]) -> #N/A | J42: =fatoG1[[#This Row],[Desc. C. Custo Cliente]] -> 056-EQUIPE COMERCIAL 4 | N42: GONCALVES/THIAGO NARCISO OLIVEIRA | O42: =_xlfn.XLOOKUP(N42,DEPARA!F:F,DEPARA!H:H,0) -> THIAGO NARCISO OLIVEIRA GONÇALVES | P42: =_xlfn.XLOOKUP(O42,dimColaborador!A:A,dimColaborador!B:B,0) -> 26516 | Q42: =_xlfn.XLOOKUP(O42,dimColaborador!A:A,dimColaborador!C:C,) -> DR - PRIME - CENTRO OESTE | R42: =_xlfn.XLOOKUP(O42,dimColaborador!A:A,dimColaborador!D:D) -> DISTRIBUIDOR | S42: RECIFE | T42: 01 STANDARD COM 1 ÁGUA INCLUSA - 08/07/25 a 09/07/25 | U42: 45846 | V42: 45847 | W42: 4000 | X42: 499762 | Y42: 210 | Z42: 10.5 | AA42: 0 | AB42: 220.5
A43: 45849 | B43: 52848 | C43: 6765 | D43: HTL | E43: IBIS BUDGET RECIFE JABOATAO | F43: =_xlfn.XLOOKUP(E43,DEPARA!A:A,DEPARA!C:C,"Verificar") -> HOSPEDAGEM | G43: FIRSTLAB IND. IMP. E EXP. DE PROD. PARA LAB. LTDA | H43: 056-EQUIPE COMERCIAL 4 | I43: =_xlfn.XLOOKUP(fatoG1[[#This Row],[Centro de Custo]],dimCentroCusto[Centro_Custo],dimCentroCusto[Codigo_CentroCusto]) -> #N/A | J43: =fatoG1[[#This Row],[Desc. C. Custo Cliente]] -> 056-EQUIPE COMERCIAL 4 | N43: GONCALVES/THIAGO NARCISO OLIVEIRA | O43: =_xlfn.XLOOKUP(N43,DEPARA!F:F,DEPARA!H:H,0) -> THIAGO NARCISO OLIVEIRA GONÇALVES | P43: =_xlfn.XLOOKUP(O43,dimColaborador!A:A,dimColaborador!B:B,0) -> 26516 | Q43: =_xlfn.XLOOKUP(O43,dimColaborador!A:A,dimColaborador!C:C,) -> DR - PRIME - CENTRO OESTE | R43: =_xlfn.XLOOKUP(O43,dimColaborador!A:A,dimColaborador!D:D) -> DISTRIBUIDOR | S43: RECIFE | T43: 01 STANDARD COM 1 ÁGUA INCLUSA - 10/07/25 a 11/07/25 | U43: 45848 | V43: 45849 | W43: 4000 | X43: 499772 | Y43: 210 | Z43: 10.5 | AA43: 0 | AB43: 220.5
A44: 45848 | B44: 52853 | C44: 6765 | D44: HTL | E44: BESSA BEACH HOTEL | F44: =_xlfn.XLOOKUP(E44,DEPARA!A:A,DEPARA!C:C,"Verificar") -> HOSPEDAGEM | G44: FIRSTLAB IND. IMP. E EXP. DE PROD. PARA LAB. LTDA | H44: 056-EQUIPE COMERCIAL 4 | I44: =_xlfn.XLOOKUP(fatoG1[[#This Row],[Centro de Custo]],dimCentroCusto[Centro_Custo],dimCentroCusto[Codigo_CentroCusto]) -> #N/A | J44: =fatoG1[[#This Row],[Desc. C. Custo Cliente]] -> 056-EQUIPE COMERCIAL 4 | N44: THIAGO NARCISO OLIVEIRA GONCALVES | O44: =_xlfn.XLOOKUP(N44,DEPARA!F:F,DEPARA!H:H,0) -> THIAGO NARCISO OLIVEIRA GONÇALVES | P44: =_xlfn.XLOOKUP(O44,dimColaborador!A:A,dimColaborador!B:B,0) -> 26516 | Q44: =_xlfn.XLOOKUP(O44,dimColaborador!A:A,dimColaborador!C:C,) -> DR - PRIME - CENTRO OESTE | R44: =_xlfn.XLOOKUP(O44,dimColaborador!A:A,dimColaborador!D:D) -> DISTRIBUIDOR | S44: JOÃO PESSOA | T44: 01 STANDARD SINGLE - 09/07/25 a 10/07/25 | U44: 45847 | V44: 45848 | W44: 4 | X44: 864709 | Y44: 235.63 | Z44: 23.56 | AA44: 0 | AB44: 259.19
A45: 45848 | B45: 52981 | C45: 6765 | D45: HTL | E45: BESSA BEACH HOTEL | F45: =_xlfn.XLOOKUP(E45,DEPARA!A:A,DEPARA!C:C,"Verificar") -> HOSPEDAGEM | G45: FIRSTLAB IND. IMP. E EXP. DE PROD. PARA LAB. LTDA | H45: 048-COMERCIAL INTERNO | I45: =_xlfn.XLOOKUP(fatoG1[[#This Row],[Centro de Custo]],dimCentroCusto[Centro_Custo],dimCentroCusto[Codigo_CentroCusto]) -> #N/A | J45: =fatoG1[[#This Row],[Desc. C. Custo Cliente]] -> 048-COMERCIAL INTERNO | L45: VISITAÇÃO DE CLIENTES | N45: SANTOS/LAURA | O45: =_xlfn.XLOOKUP(N45,DEPARA!F:F,DEPARA!H:H,0) -> LAURA BENTO DOS SANTOS | P45: =_xlfn.XLOOKUP(O45,dimColaborador!A:A,dimColaborador!B:B,0) -> 9999999910 | Q45: =_xlfn.XLOOKUP(O45,dimColaborador!A:A,dimColaborador!C:C,) -> COORDENADORA FIRSTLAB | R45: =_xlfn.XLOOKUP(O45,dimColaborador!A:A,dimColaborador!D:D) -> COORDENADORA FIRSTLAB | S45: JOÃO PESSOA | T45: 01 DUPLO STANDARD - 09/07/25 a 10/07/25 | U45: 45847 | V45: 45848 | W45: 4000 | X45: 508083 | Y45: 208.04 | Z45: 20.8 | AA45: 0 | AB45: 228.84
A46: 45848 | B46: 53027 | C46: 6765 | D46: HTL | E46: PORTO SUITES NATAL | F46: =_xlfn.XLOOKUP(E46,DEPARA!A:A,DEPARA!C:C,"Verificar") -> HOSPEDAGEM | G46: FIRSTLAB IND. IMP. E EXP. DE PROD. PARA LAB. LTDA | H46: 056-EQUIPE COMERCIAL 4 | I46: =_xlfn.XLOOKUP(fatoG1[[#This Row],[Centro de Custo]],dimCentroCusto[Centro_Custo],dimCentroCusto[Codigo_CentroCusto]) -> #N/A | J46: =fatoG1[[#This Row],[Desc. C. Custo Cliente]] -> 056-EQUIPE COMERCIAL 4 | L46: VIAGEM PARA VISITA DE CLIENTES DA REGIÃO. | N46: ALMEIDA/KHARLA NAYARA ABRANTES | O46: =_xlfn.XLOOKUP(N46,DEPARA!F:F,DEPARA!H:H,0) -> KHARLA NAYARA ABRANTES DE ALMEIDA | P46: =_xlfn.XLOOKUP(O46,dimColaborador!A:A,dimColaborador!B:B,0) -> 26175 | Q46: =_xlfn.XLOOKUP(O46,dimColaborador!A:A,dimColaborador!C:C,) -> GC -MÉDIO/GRANDE PORTE - NO/NE | R46: =_xlfn.XLOOKUP(O46,dimColaborador!A:A,dimColaborador!D:D) -> GRANDES CONTAS | S46: NATAL | T46: 01 STANDARD - 09/07/25 a 10/07/25 | U46: 45847 | V46: 45848 | W46: 4000 | X46: 510884 | Y46: 210 | Z46: 0 | AA46: 0 | AB46: 210
A47: 45852 | B47: 53191 | C47: 6765 | D47: TKT | E47: TAM LINHAS AÉREAS | F47: =_xlfn.XLOOKUP(E47,DEPARA!A:A,DEPARA!C:C,"Verificar") -> PASSAGEM | G47: FIRSTLAB IND. IMP. E EXP. DE PROD. PARA LAB. LTDA | H47: 056-EQUIPE COMERCIAL 4 | I47: =_xlfn.XLOOKUP(fatoG1[[#This Row],[Centro de Custo]],dimCentroCusto[Centro_Custo],dimCentroCusto[Codigo_CentroCusto]) -> #N/A | J47: =fatoG1[[#This Row],[Desc. C. Custo Cliente]] -> 056-EQUIPE COMERCIAL 4 | L47: SOL. POR EMAIL | N47: GONCALVES/THIAGO NARCISO OLIVEIRA | O47: =_xlfn.XLOOKUP(N47,DEPARA!F:F,DEPARA!H:H,0) -> THIAGO NARCISO OLIVEIRA GONÇALVES | P47: =_xlfn.XLOOKUP(O47,dimColaborador!A:A,dimColaborador!B:B,0) -> 26516 | Q47: =_xlfn.XLOOKUP(O47,dimColaborador!A:A,dimColaborador!C:C,) -> DR - PRIME - CENTRO OESTE | R47: =_xlfn.XLOOKUP(O47,dimColaborador!A:A,dimColaborador!D:D) -> DISTRIBUIDOR | S47: SAO JOSE DOS PINHAIS | T47: BSB/MAO | U47: 45852 | V47: 45852 | W47: 2241 | X47: 208355 | Y47: 2299.49 | Z47: 0 | AA47: 0 | AB47: 2299.49
A48: 45853 | B48: 53272 | C48: 6765 | D48: CAR | E48: UNIDAS | F48: =_xlfn.XLOOKUP(E48,DEPARA!A:A,DEPARA!C:C,"Verificar") -> LOCAÇÃO DE VEÍCULOS | G48: FIRSTLAB IND. IMP. E EXP. DE PROD. PARA LAB. LTDA | H48: 049-EQUIPE COMERCIAL 1 | I48: =_xlfn.XLOOKUP(fatoG1[[#This Row],[Centro de Custo]],dimCentroCusto[Centro_Custo],dimCentroCusto[Codigo_CentroCusto]) -> #N/A | J48: =fatoG1[[#This Row],[Desc. C. Custo Cliente]] -> 049-EQUIPE COMERCIAL 1 | N48: OLIVEIRA/JOANA MARIA TEIXEIRA DE | O48: =_xlfn.XLOOKUP(N48,DEPARA!F:F,DEPARA!H:H,0) -> JOANA MARIA TEIXEIRA DE OLIVEIRA | P48: =_xlfn.XLOOKUP(O48,dimColaborador!A:A,dimColaborador!B:B,0) -> 26136 | Q48: =_xlfn.XLOOKUP(O48,dimColaborador!A:A,dimColaborador!C:C,) -> GRANDES CONTAS NACIONAIS | R48: =_xlfn.XLOOKUP(O48,dimColaborador!A:A,dimColaborador!D:D) -> GRANDES CONTAS | S48: CURITIBA | T48: 13/05/25 a 15/05/25 - RENAULT KWID, FIAT MOBI (1.0) OU SIMIL | U48: 45790 | V48: 45792 | X48: 0 | Y48: 0 | Z48: 124.96 | AA48: 0 | AB48: 124.96
A49: 45860 | B49: 50379 | C49: 6801 | D49: CAR | E49: UNIDAS | F49: =_xlfn.XLOOKUP(E49,DEPARA!A:A,DEPARA!C:C,"Verificar") -> LOCAÇÃO DE VEÍCULOS | G49: FIRSTLAB IND. IMP. E EXP. DE PROD. PARA LAB. LTDA | H49: 055-EQUIPE COMERCIAL 3 | I49: =_xlfn.XLOOKUP(fatoG1[[#This Row],[Centro de Custo]],dimCentroCusto[Centro_Custo],dimCentroCusto[Codigo_CentroCusto]) -> #N/A | J49: =fatoG1[[#This Row],[Desc. C. Custo Cliente]] -> 055-EQUIPE COMERCIAL 3 | L49: VISITA CLIENTES DA REGIÃO | N49: LUZ/MARCIO ARRUDA | O49: =_xlfn.XLOOKUP(N49,DEPARA!F:F,DEPARA!H:H,0) -> MARCIO ARRUDA LUZ | P49: =_xlfn.XLOOKUP(O49,dimColaborador!A:A,dimColaborador!B:B,0) -> 25745 | Q49: =_xlfn.XLOOKUP(O49,dimColaborador!A:A,dimColaborador!C:C,) -> GC - MÉDIO/GRANDE PORTE - SE/CO | R49: =_xlfn.XLOOKUP(O49,dimColaborador!A:A,dimColaborador!D:D) -> GRANDES CONTAS | S49: CURITIBA | T49: 27/05/25 a 30/05/25 - NOVO VERSA, HB20S, ONIX PLUS (1.4 OU 1 | U49: 45804 | V49: 45807 | W49: 2118 | X49: 508487 | Y49: 439.41 | Z49: 487.76 | AA49: 0 | AB49: 927.17
A50: 45860 | B50: 51760 | C50: 6801 | D50: CAR | E50: MOVIDA RENT A CAR | F50: =_xlfn.XLOOKUP(E50,DEPARA!A:A,DEPARA!C:C,"Verificar") -> LOCAÇÃO DE VEÍCULOS | G50: FIRSTLAB IND. IMP. E EXP. DE PROD. PARA LAB. LTDA | H50: 056-EQUIPE COMERCIAL 4 | I50: =_xlfn.XLOOKUP(fatoG1[[#This Row],[Centro de Custo]],dimCentroCusto[Centro_Custo],dimCentroCusto[Codigo_CentroCusto]) -> #N/A | J50: =fatoG1[[#This Row],[Desc. C. Custo Cliente]] -> 056-EQUIPE COMERCIAL 4 | N50: GONCALVES/THIAGO NARCISO OLIVEIRA | O50: =_xlfn.XLOOKUP(N50,DEPARA!F:F,DEPARA!H:H,0) -> THIAGO NARCISO OLIVEIRA GONÇALVES | P50: =_xlfn.XLOOKUP(O50,dimColaborador!A:A,dimColaborador!B:B,0) -> 26516 | Q50: =_xlfn.XLOOKUP(O50,dimColaborador!A:A,dimColaborador!C:C,) -> DR - PRIME - CENTRO OESTE | R50: =_xlfn.XLOOKUP(O50,dimColaborador!A:A,dimColaborador!D:D) -> DISTRIBUIDOR | S50: CURITIBA | T50: 09/06/25 a 13/06/25 - POLO, HB20, 208 (1.0) OU SIMILAR / DIR | U50: 45817 | V50: 45821 | W50: 2118 | X50: 615505 | Y50: 488.96 | Z50: 73.34 | AA50: 0 | AB50: 562.3
A51: 45860 | B51: 52841 | C51: 6801 | D51: CAR | E51: UNIDAS | F51: =_xlfn.XLOOKUP(E51,DEPARA!A:A,DEPARA!C:C,"Verificar") -> LOCAÇÃO DE VEÍCULOS | G51: FIRSTLAB IND. IMP. E EXP. DE PROD. PARA LAB. LTDA | H51: 056-EQUIPE COMERCIAL 4 | I51: =_xlfn.XLOOKUP(fatoG1[[#This Row],[Centro de Custo]],dimCentroCusto[Centro_Custo],dimCentroCusto[Codigo_CentroCusto]) -> #N/A | J51: =fatoG1[[#This Row],[Desc. C. Custo Cliente]] -> 056-EQUIPE COMERCIAL 4 | N51: GONCALVES/THIAGO NARCISO OLIVEIRA | O51: =_xlfn.XLOOKUP(N51,DEPARA!F:F,DEPARA!H:H,0) -> THIAGO NARCISO OLIVEIRA GONÇALVES | P51: =_xlfn.XLOOKUP(O51,dimColaborador!A:A,dimColaborador!B:B,0) -> 26516 | Q51: =_xlfn.XLOOKUP(O51,dimColaborador!A:A,dimColaborador!C:C,) -> DR - PRIME - CENTRO OESTE | R51: =_xlfn.XLOOKUP(O51,dimColaborador!A:A,dimColaborador!D:D) -> DISTRIBUIDOR | S51: CURITIBA | T51: 08/07/25 a 11/07/25 - FIAT ARGO, CHEVROLET ONIX, VW GOL (1. | U51: 45846 | V51: 45849 | W51: 2118 | X51: 700411 | Y51: 447 | Z51: 54.9 | AA51: 0 | AB51: 501.9
A52: 45856 | B52: 52843 | C52: 6801 | D52: HTL | E52: IBIS STYLES BELEM DO PARA | F52: =_xlfn.XLOOKUP(E52,DEPARA!A:A,DEPARA!C:C,"Verificar") -> HOSPEDAGEM | G52: FIRSTLAB IND. IMP. E EXP. DE PROD. PARA LAB. LTDA | H52: 056-EQUIPE COMERCIAL 4 | I52: =_xlfn.XLOOKUP(fatoG1[[#This Row],[Centro de Custo]],dimCentroCusto[Centro_Custo],dimCentroCusto[Codigo_CentroCusto]) -> #N/A | J52: =fatoG1[[#This Row],[Desc. C. Custo Cliente]] -> 056-EQUIPE COMERCIAL 4 | N52: GONCALVES/THIAGO NARCISO OLIVEIRA | O52: =_xlfn.XLOOKUP(N52,DEPARA!F:F,DEPARA!H:H,0) -> THIAGO NARCISO OLIVEIRA GONÇALVES | P52: =_xlfn.XLOOKUP(O52,dimColaborador!A:A,dimColaborador!B:B,0) -> 26516 | Q52: =_xlfn.XLOOKUP(O52,dimColaborador!A:A,dimColaborador!C:C,) -> DR - PRIME - CENTRO OESTE | R52: =_xlfn.XLOOKUP(O52,dimColaborador!A:A,dimColaborador!D:D) -> DISTRIBUIDOR | S52: BELEM | T52: 01 TWC QUARTO PADRÃO COM 2 CAMAS DE SOLTEIRO - 16/07/25 a | U52: 45854 | V52: 45856 | W52: 4000 | X52: 499759 | Y52: 605.88 | Z52: 30.3 | AA52: 0 | AB52: 636.18
A53: 45854 | B53: 52844 | C53: 6801 | D53: HTL | E53: AMAZONIA HOTEL REDE ANDRADE | F53: =_xlfn.XLOOKUP(E53,DEPARA!A:A,DEPARA!C:C,"Verificar") -> HOSPEDAGEM | G53: FIRSTLAB IND. IMP. E EXP. DE PROD. PARA LAB. LTDA | H53: 056-EQUIPE COMERCIAL 4 | I53: =_xlfn.XLOOKUP(fatoG1[[#This Row],[Centro de Custo]],dimCentroCusto[Centro_Custo],dimCentroCusto[Codigo_CentroCusto]) -> #N/A | J53: =fatoG1[[#This Row],[Desc. C. Custo Cliente]] -> 056-EQUIPE COMERCIAL 4 | N53: GONCALVES/THIAGO NARCISO OLIVEIRA | O53: =_xlfn.XLOOKUP(N53,DEPARA!F:F,DEPARA!H:H,0) -> THIAGO NARCISO OLIVEIRA GONÇALVES | P53: =_xlfn.XLOOKUP(O53,dimColaborador!A:A,dimColaborador!B:B,0) -> 26516 | Q53: =_xlfn.XLOOKUP(O53,dimColaborador!A:A,dimColaborador!C:C,) -> DR - PRIME - CENTRO OESTE | R53: =_xlfn.XLOOKUP(O53,dimColaborador!A:A,dimColaborador!D:D) -> DISTRIBUIDOR | S53: MANAUS | T53: 01 QUARTO SINGLE - 14/07/25 a 16/07/25 | U53: 45852 | V53: 45854 | W53: 4000 | X53: 499745 | Y53: 354.38 | Z53: 0 | AA53: 0 | AB53: 354.38
A54: 45856 | B54: 53114 | C54: 6801 | D54: HTL | E54: HOTEL NACIONAL INN GUARUJÁ | F54: =_xlfn.XLOOKUP(E54,DEPARA!A:A,DEPARA!C:C,"Verificar") -> HOSPEDAGEM | G54: FIRSTLAB IND. IMP. E EXP. DE PROD. PARA LAB. LTDA | H54: 049-EQUIPE COMERCIAL 1 | I54: =_xlfn.XLOOKUP(fatoG1[[#This Row],[Centro de Custo]],dimCentroCusto[Centro_Custo],dimCentroCusto[Codigo_CentroCusto]) -> #N/A | J54: =fatoG1[[#This Row],[Desc. C. Custo Cliente]] -> 049-EQUIPE COMERCIAL 1 | N54: OLIVEIRA/JOANA MARIA TEIXEIRA DE | O54: =_xlfn.XLOOKUP(N54,DEPARA!F:F,DEPARA!H:H,0) -> JOANA MARIA TEIXEIRA DE OLIVEIRA | P54: =_xlfn.XLOOKUP(O54,dimColaborador!A:A,dimColaborador!B:B,0) -> 26136 | Q54: =_xlfn.XLOOKUP(O54,dimColaborador!A:A,dimColaborador!C:C,) -> GRANDES CONTAS NACIONAIS | R54: =_xlfn.XLOOKUP(O54,dimColaborador!A:A,dimColaborador!D:D) -> GRANDES CONTAS | S54: GUARUJÁ | T54: 01 APARTAMENTO SUPERIOR - 17/07/25 a 18/07/25 | U54: 45855 | V54: 45856 | W54: 4000 | X54: 516506 | Y54: 245.11 | Z54: 12.26 | AA54: 0 | AB54: 257.37
A55: 45861 | B55: 53383 | C55: 6801 | D55: HTL | E55: OMNIBEES | F55: =_xlfn.XLOOKUP(E55,DEPARA!A:A,DEPARA!C:C,"Verificar") -> HOSPEDAGEM | G55: FIRSTLAB IND. IMP. E EXP. DE PROD. PARA LAB. LTDA | H55: 056-EQUIPE COMERCIAL 4 | I55: =_xlfn.XLOOKUP(fatoG1[[#This Row],[Centro de Custo]],dimCentroCusto[Centro_Custo],dimCentroCusto[Codigo_CentroCusto]) -> #N/A | J55: =fatoG1[[#This Row],[Desc. C. Custo Cliente]] -> 056-EQUIPE COMERCIAL 4 | N55: ALMEIDA/KHARLA NAYARA ABRANTES | O55: =_xlfn.XLOOKUP(N55,DEPARA!F:F,DEPARA!H:H,0) -> KHARLA NAYARA ABRANTES DE ALMEIDA | P55: =_xlfn.XLOOKUP(O55,dimColaborador!A:A,dimColaborador!B:B,0) -> 26175 | Q55: =_xlfn.XLOOKUP(O55,dimColaborador!A:A,dimColaborador!C:C,) -> GC -MÉDIO/GRANDE PORTE - NO/NE | R55: =_xlfn.XLOOKUP(O55,dimColaborador!A:A,dimColaborador!D:D) -> GRANDES CONTAS | S55: SAO PAULO | T55: 01 APTO SINGLE STANDARD - 21/07/25 a 23/07/25 | U55: 45859 | V55: 45861 | W55: RES0 | X55: 32031- | Y55: 453.72 | Z55: 0 | AA55: 0 | AB55: 453.72
A56: 45862 | B56: 51721 | C56: 6834 | D56: HTL | E56: DAYRELL HOTEL | F56: =_xlfn.XLOOKUP(E56,DEPARA!A:A,DEPARA!C:C,"Verificar") -> HOSPEDAGEM | G56: FIRSTLAB IND. IMP. E EXP. DE PROD. PARA LAB. LTDA | H56: 049-EQUIPE COMERCIAL 1 | I56: =_xlfn.XLOOKUP(fatoG1[[#This Row],[Centro de Custo]],dimCentroCusto[Centro_Custo],dimCentroCusto[Codigo_CentroCusto]) -> #N/A | J56: =fatoG1[[#This Row],[Desc. C. Custo Cliente]] -> 049-EQUIPE COMERCIAL 1 | L56: VISITA | N56: SHINKAI/RAQUEL AICO | O56: =_xlfn.XLOOKUP(N56,DEPARA!F:F,DEPARA!H:H,0) -> RAQUEL AICO SHINKAI | P56: =_xlfn.XLOOKUP(O56,dimColaborador!A:A,dimColaborador!B:B,0) -> 25880 | Q56: =_xlfn.XLOOKUP(O56,dimColaborador!A:A,dimColaborador!C:C,) -> DR - PRIME - SUL | R56: =_xlfn.XLOOKUP(O56,dimColaborador!A:A,dimColaborador!D:D) -> DISTRIBUIDOR | S56: BELO HORIZONTE | T56: 01 STANDARD CASAL - 21/07/25 a 24/07/25 | U56: 45859 | V56: 45862 | W56: 4 | X56: 793099 | Y56: 798 | Z56: 119.7 | AA56: 0 | AB56: 917.7
A57: 45863 | B57: 51722 | C57: 6834 | D57: HTL | E57: ESUITES HOTEL RECREIO SHOPPING | F57: =_xlfn.XLOOKUP(E57,DEPARA!A:A,DEPARA!C:C,"Verificar") -> HOSPEDAGEM | G57: FIRSTLAB IND. IMP. E EXP. DE PROD. PARA LAB. LTDA | H57: 049-EQUIPE COMERCIAL 1 | I57: =_xlfn.XLOOKUP(fatoG1[[#This Row],[Centro de Custo]],dimCentroCusto[Centro_Custo],dimCentroCusto[Codigo_CentroCusto]) -> #N/A | J57: =fatoG1[[#This Row],[Desc. C. Custo Cliente]] -> 049-EQUIPE COMERCIAL 1 | L57: VISITA | N57: SHINKAI/RAQUEL AICO | O57: =_xlfn.XLOOKUP(N57,DEPARA!F:F,DEPARA!H:H,0) -> RAQUEL AICO SHINKAI | P57: =_xlfn.XLOOKUP(O57,dimColaborador!A:A,dimColaborador!B:B,0) -> 25880 | Q57: =_xlfn.XLOOKUP(O57,dimColaborador!A:A,dimColaborador!C:C,) -> DR - PRIME - SUL | R57: =_xlfn.XLOOKUP(O57,dimColaborador!A:A,dimColaborador!D:D) -> DISTRIBUIDOR | S57: RIO DE JANEIRO | T57: 01 SUPERIOR QUEEN NÃO FUMANTE - 23/07/25 a 25/07/25 | U57: 45861 | V57: 45863 | W57: 4000 | X57: 427603 | Y57: 577.04 | Z57: 86.56 | AA57: 0 | AB57: 663.6
A58: 45862 | B58: 52157 | C58: 6834 | D58: HTL | E58: PAMPULHA DESIGN HOTEL | F58: =_xlfn.XLOOKUP(E58,DEPARA!A:A,DEPARA!C:C,"Verificar") -> HOSPEDAGEM | G58: FIRSTLAB IND. IMP. E EXP. DE PROD. PARA LAB. LTDA | H58: 049-EQUIPE COMERCIAL 1 | I58: =_xlfn.XLOOKUP(fatoG1[[#This Row],[Centro de Custo]],dimCentroCusto[Centro_Custo],dimCentroCusto[Codigo_CentroCusto]) -> #N/A | J58: =fatoG1[[#This Row],[Desc. C. Custo Cliente]] -> 049-EQUIPE COMERCIAL 1 | N58: OLIVEIRA/JOANA MARIA TEIXEIRA DE | O58: =_xlfn.XLOOKUP(N58,DEPARA!F:F,DEPARA!H:H,0) -> JOANA MARIA TEIXEIRA DE OLIVEIRA | P58: =_xlfn.XLOOKUP(O58,dimColaborador!A:A,dimColaborador!B:B,0) -> 26136 | Q58: =_xlfn.XLOOKUP(O58,dimColaborador!A:A,dimColaborador!C:C,) -> GRANDES CONTAS NACIONAIS | R58: =_xlfn.XLOOKUP(O58,dimColaborador!A:A,dimColaborador!D:D) -> GRANDES CONTAS | S58: BELO HORIZONTE | T58: 01 STANDARD CASAL - 22/07/25 a 24/07/25 | U58: 45860 | V58: 45862 | W58: 4000 | X58: 456838 | Y58: 411.75 | Z58: 20.59 | AA58: 0 | AB58: 432.34
A59: 45862 | B59: 52852 | C59: 6834 | D59: HTL | E59: B HOTEL | F59: =_xlfn.XLOOKUP(E59,DEPARA!A:A,DEPARA!C:C,"Verificar") -> HOSPEDAGEM | G59: FIRSTLAB IND. IMP. E EXP. DE PROD. PARA LAB. LTDA | H59: 056-EQUIPE COMERCIAL 4 | I59: =_xlfn.XLOOKUP(fatoG1[[#This Row],[Centro de Custo]],dimCentroCusto[Centro_Custo],dimCentroCusto[Codigo_CentroCusto]) -> #N/A | J59: =fatoG1[[#This Row],[Desc. C. Custo Cliente]] -> 056-EQUIPE COMERCIAL 4 | N59: THIAGO NARCISO OLIVEIRA GONCALVES | O59: =_xlfn.XLOOKUP(N59,DEPARA!F:F,DEPARA!H:H,0) -> THIAGO NARCISO OLIVEIRA GONÇALVES | P59: =_xlfn.XLOOKUP(O59,dimColaborador!A:A,dimColaborador!B:B,0) -> 26516 | Q59: =_xlfn.XLOOKUP(O59,dimColaborador!A:A,dimColaborador!C:C,) -> DR - PRIME - CENTRO OESTE | R59: =_xlfn.XLOOKUP(O59,dimColaborador!A:A,dimColaborador!D:D) -> DISTRIBUIDOR | S59: SALVADOR | T59: 01 QUARTO SUPERIOR SINGLE - 21/07/25 a 24/07/25 | U59: 45859 | V59: 45862 | W59: 4 | X59: 864694 | Y59: 528.99 | Z59: 26.45 | AA59: 0 | AB59: 555.44
A60: 45862 | B60: 53340 | C60: 6834 | D60: HTL | E60: IBIS MARILIA | F60: =_xlfn.XLOOKUP(E60,DEPARA!A:A,DEPARA!C:C,"Verificar") -> HOSPEDAGEM | G60: FIRSTLAB IND. IMP. E EXP. DE PROD. PARA LAB. LTDA | H60: 048-COMERCIAL INTERNO | I60: =_xlfn.XLOOKUP(fatoG1[[#This Row],[Centro de Custo]],dimCentroCusto[Centro_Custo],dimCentroCusto[Codigo_CentroCusto]) -> #N/A | J60: =fatoG1[[#This Row],[Desc. C. Custo Cliente]] -> 048-COMERCIAL INTERNO | L60: VISITA COMERCIAL | N60: PEREIRA/FELIPE LUIZ RIBEIRO | O60: =_xlfn.XLOOKUP(N60,DEPARA!F:F,DEPARA!H:H,0) -> FELIPE LUIZ RIBEIRO PEREIRA | P60: =_xlfn.XLOOKUP(O60,dimColaborador!A:A,dimColaborador!B:B,0) -> 26387 | Q60: =_xlfn.XLOOKUP(O60,dimColaborador!A:A,dimColaborador!C:C,) -> GC - MÉDIO/GRANDE PORTE - SP | R60: =_xlfn.XLOOKUP(O60,dimColaborador!A:A,dimColaborador!D:D) -> GRANDES CONTAS | S60: MARILIA | T60: 01 QUARTO PADRÃO COM 1 CAMA DE CASAL - 22/07/25 a 24/07/25 | U60: 45860 | V60: 45862 | W60: 4000 | X60: 535866 | Y60: 475.8 | Z60: 14.28 | AA60: 0 | AB60: 490.08
A61: 45863 | B61: 53382 | C61: 6834 | D61: HTL | E61: OMNIBEES | F61: =_xlfn.XLOOKUP(E61,DEPARA!A:A,DEPARA!C:C,"Verificar") -> HOSPEDAGEM | G61: FIRSTLAB IND. IMP. E EXP. DE PROD. PARA LAB. LTDA | H61: 056-EQUIPE COMERCIAL 4 | I61: =_xlfn.XLOOKUP(fatoG1[[#This Row],[Centro de Custo]],dimCentroCusto[Centro_Custo],dimCentroCusto[Codigo_CentroCusto]) -> #N/A | J61: =fatoG1[[#This Row],[Desc. C. Custo Cliente]] -> 056-EQUIPE COMERCIAL 4 | N61: ALMEIDA/KHARLA NAYARA ABRANTES | O61: =_xlfn.XLOOKUP(N61,DEPARA!F:F,DEPARA!H:H,0) -> KHARLA NAYARA ABRANTES DE ALMEIDA | P61: =_xlfn.XLOOKUP(O61,dimColaborador!A:A,dimColaborador!B:B,0) -> 26175 | Q61: =_xlfn.XLOOKUP(O61,dimColaborador!A:A,dimColaborador!C:C,) -> GC -MÉDIO/GRANDE PORTE - NO/NE | R61: =_xlfn.XLOOKUP(O61,dimColaborador!A:A,dimColaborador!D:D) -> GRANDES CONTAS | S61: SAO PAULO | T61: 01 DBD QUARTO CLÁSSICO COM 1 CAMA DE CASAL - 23/07/25 a 25 | U61: 45861 | V61: 45863 | W61: RES0 | X61: 68731- | Y61: 704.52 | Z61: 30.9 | AA61: 0 | AB61: 735.42
A62: 45868 | B62: 53538 | C62: 6834 | D62: HTL | E62: PLAZA SAN RAFAEL | F62: =_xlfn.XLOOKUP(E62,DEPARA!A:A,DEPARA!C:C,"Verificar") -> HOSPEDAGEM | G62: FIRSTLAB IND. IMP. E EXP. DE PROD. PARA LAB. LTDA | H62: 049-EQUIPE COMERCIAL 1 | I62: =_xlfn.XLOOKUP(fatoG1[[#This Row],[Centro de Custo]],dimCentroCusto[Centro_Custo],dimCentroCusto[Codigo_CentroCusto]) -> #N/A | J62: =fatoG1[[#This Row],[Desc. C. Custo Cliente]] -> 049-EQUIPE COMERCIAL 1 | N62: LETICIA CAMPOS DA SILVA VAZ | O62: =_xlfn.XLOOKUP(N62,DEPARA!F:F,DEPARA!H:H,0) -> LETICIA CAMPOS DA SILVA VAZ | P62: =_xlfn.XLOOKUP(O62,dimColaborador!A:A,dimColaborador!B:B,0) -> 26385 | Q62: =_xlfn.XLOOKUP(O62,dimColaborador!A:A,dimColaborador!C:C,) -> GC - MÉDIO/GRANDE PORTE - SUL | R62: =_xlfn.XLOOKUP(O62,dimColaborador!A:A,dimColaborador!D:D) -> GRANDES CONTAS | S62: PORTO ALEGRE | T62: 01 QUARTO SEMI-EXECUTIVO SINGLE - 29/07/25 a 30/07/25 | U62: 45867 | V62: 45868 | W62: 4 | X62: 915717 | Y62: 253.33 | Z62: 0 | AA62: 0 | AB62: 253.33
A63: 45869 | B63: 53539 | C63: 6834 | D63: HTL | E63: HOTEL JOAÇABA | F63: =_xlfn.XLOOKUP(E63,DEPARA!A:A,DEPARA!C:C,"Verificar") -> HOSPEDAGEM | G63: FIRSTLAB IND. IMP. E EXP. DE PROD. PARA LAB. LTDA | H63: 049-EQUIPE COMERCIAL 1 | I63: =_xlfn.XLOOKUP(fatoG1[[#This Row],[Centro de Custo]],dimCentroCusto[Centro_Custo],dimCentroCusto[Codigo_CentroCusto]) -> #N/A | J63: =fatoG1[[#This Row],[Desc. C. Custo Cliente]] -> 049-EQUIPE COMERCIAL 1 | N63: LETICIA CAMPOS DA SILVA VAZ | O63: =_xlfn.XLOOKUP(N63,DEPARA!F:F,DEPARA!H:H,0) -> LETICIA CAMPOS DA SILVA VAZ | P63: =_xlfn.XLOOKUP(O63,dimColaborador!A:A,dimColaborador!B:B,0) -> 26385 | Q63: =_xlfn.XLOOKUP(O63,dimColaborador!A:A,dimColaborador!C:C,) -> GC - MÉDIO/GRANDE PORTE - SUL | R63: =_xlfn.XLOOKUP(O63,dimColaborador!A:A,dimColaborador!D:D) -> GRANDES CONTAS | S63: JOAÇABA | T63: 01 QUARTO SUPERIOR SINGLE - 30/07/25 a 31/07/25 | U63: 45868 | V63: 45869 | W63: 4 | X63: 915728 | Y63: 280 | Z63: 0 | AA63: 0 | AB63: 280
A64: 45867 | B64: 53667 | C64: 6834 | D64: TKT | E64: AZUL LINHAS AÉREAS BRASILEIRAS | F64: =_xlfn.XLOOKUP(E64,DEPARA!A:A,DEPARA!C:C,"Verificar") -> PASSAGEM | G64: FIRSTLAB IND. IMP. E EXP. DE PROD. PARA LAB. LTDA | H64: 056-EQUIPE COMERCIAL 4 | I64: =_xlfn.XLOOKUP(fatoG1[[#This Row],[Centro de Custo]],dimCentroCusto[Centro_Custo],dimCentroCusto[Codigo_CentroCusto]) -> #N/A | J64: =fatoG1[[#This Row],[Desc. C. Custo Cliente]] -> 056-EQUIPE COMERCIAL 4 | L64: PROSPECTAR REGIÃO | N64: NAYARA ABRANTES DE ALMEIDA/KHARLA | O64: =_xlfn.XLOOKUP(N64,DEPARA!F:F,DEPARA!H:H,0) -> KHARLA NAYARA ABRANTES DE ALMEIDA | P64: =_xlfn.XLOOKUP(O64,dimColaborador!A:A,dimColaborador!B:B,0) -> 26175 | Q64: =_xlfn.XLOOKUP(O64,dimColaborador!A:A,dimColaborador!C:C,) -> GC -MÉDIO/GRANDE PORTE - NO/NE | R64: =_xlfn.XLOOKUP(O64,dimColaborador!A:A,dimColaborador!D:D) -> GRANDES CONTAS | S64: SAO PAULO | T64: REC*VCP/PMW*VCP/REC | U64: 45887 | V64: 45891 | W64: ETKT | X64: AP4IHX | Y64: 1163.12 | Z64: 105.25 | AA64: 93.05 | AB64: 1361.42
A65: 45867 | B65: 53668 | C65: 6834 | D65: TKT | E65: AZUL LINHAS AÉREAS BRASILEIRAS | F65: =_xlfn.XLOOKUP(E65,DEPARA!A:A,DEPARA!C:C,"Verificar") -> PASSAGEM | G65: FIRSTLAB IND. IMP. E EXP. DE PROD. PARA LAB. LTDA | H65: 056-EQUIPE COMERCIAL 4 | I65: =_xlfn.XLOOKUP(fatoG1[[#This Row],[Centro de Custo]],dimCentroCusto[Centro_Custo],dimCentroCusto[Codigo_CentroCusto]) -> #N/A | J65: =fatoG1[[#This Row],[Desc. C. Custo Cliente]] -> 056-EQUIPE COMERCIAL 4 | L65: VISITAR CEDRO E ETC | N65: NAYARA ABRANTES DE ALMEIDA/KHARLA | O65: =_xlfn.XLOOKUP(N65,DEPARA!F:F,DEPARA!H:H,0) -> KHARLA NAYARA ABRANTES DE ALMEIDA | P65: =_xlfn.XLOOKUP(O65,dimColaborador!A:A,dimColaborador!B:B,0) -> 26175 | Q65: =_xlfn.XLOOKUP(O65,dimColaborador!A:A,dimColaborador!C:C,) -> GC -MÉDIO/GRANDE PORTE - NO/NE | R65: =_xlfn.XLOOKUP(O65,dimColaborador!A:A,dimColaborador!D:D) -> GRANDES CONTAS | S65: SAO PAULO | T65: REC/SLZ/REC | U65: 45895 | V65: 45897 | W65: ETKT | X65: PHQVVF | Y65: 1510.19 | Z65: 105.25 | AA65: 120.82 | AB65: 1736.26
A66: 45867 | B66: 53669 | C66: 6834 | D66: TKT | E66: AZUL LINHAS AÉREAS BRASILEIRAS | F66: =_xlfn.XLOOKUP(E66,DEPARA!A:A,DEPARA!C:C,"Verificar") -> PASSAGEM | G66: FIRSTLAB IND. IMP. E EXP. DE PROD. PARA LAB. LTDA | H66: 056-EQUIPE COMERCIAL 4 | I66: =_xlfn.XLOOKUP(fatoG1[[#This Row],[Centro de Custo]],dimCentroCusto[Centro_Custo],dimCentroCusto[Codigo_CentroCusto]) -> #N/A | J66: =fatoG1[[#This Row],[Desc. C. Custo Cliente]] -> 056-EQUIPE COMERCIAL 4 | L66: RETORNO VISITA DE CLIENTES | N66: NAYARA ABRANTES DE ALMEIDA/KHARLA | O66: =_xlfn.XLOOKUP(N66,DEPARA!F:F,DEPARA!H:H,0) -> KHARLA NAYARA ABRANTES DE ALMEIDA | P66: =_xlfn.XLOOKUP(O66,dimColaborador!A:A,dimColaborador!B:B,0) -> 26175 | Q66: =_xlfn.XLOOKUP(O66,dimColaborador!A:A,dimColaborador!C:C,) -> GC -MÉDIO/GRANDE PORTE - NO/NE | R66: =_xlfn.XLOOKUP(O66,dimColaborador!A:A,dimColaborador!D:D) -> GRANDES CONTAS | S66: SAO PAULO | T66: REC/BEL/REC | U66: 45943 | V66: 45946 | W66: ETKT | X66: EKLW2G | Y66: 947.13 | Z66: 113.34 | AA66: 75.77 | AB66: 1136.24
A67: 45868 | B67: 53782 | C67: 6834 | D67: CAR | E67: MOVIDA RENT A CAR | F67: =_xlfn.XLOOKUP(E67,DEPARA!A:A,DEPARA!C:C,"Verificar") -> LOCAÇÃO DE VEÍCULOS | G67: FIRSTLAB IND. IMP. E EXP. DE PROD. PARA LAB. LTDA | H67: 049-EQUIPE COMERCIAL 1 | I67: =_xlfn.XLOOKUP(fatoG1[[#This Row],[Centro de Custo]],dimCentroCusto[Centro_Custo],dimCentroCusto[Codigo_CentroCusto]) -> #N/A | J67: =fatoG1[[#This Row],[Desc. C. Custo Cliente]] -> 049-EQUIPE COMERCIAL 1 | N67: RAQUEL AICO SHINKAI | O67: =_xlfn.XLOOKUP(N67,DEPARA!F:F,DEPARA!H:H,0) -> RAQUEL AICO SHINKAI | P67: =_xlfn.XLOOKUP(O67,dimColaborador!A:A,dimColaborador!B:B,0) -> 25880 | Q67: =_xlfn.XLOOKUP(O67,dimColaborador!A:A,dimColaborador!C:C,) -> DR - PRIME - SUL | R67: =_xlfn.XLOOKUP(O67,dimColaborador!A:A,dimColaborador!D:D) -> DISTRIBUIDOR | S67: CURITIBA | T67: 03/02/25 a 07/02/25 - FX - SÃO PAULO - AEROP. CONGONHAS | U67: 45691 | V67: 45695 | X67: 0 | Y67: 0 | Z67: 34.5 | AA67: 0 | AB67: 34.5
A68: 45868 | B68: 53783 | C68: 6834 | D68: CAR | E68: MOVIDA RENT A CAR | F68: =_xlfn.XLOOKUP(E68,DEPARA!A:A,DEPARA!C:C,"Verificar") -> LOCAÇÃO DE VEÍCULOS | G68: FIRSTLAB IND. IMP. E EXP. DE PROD. PARA LAB. LTDA | H68: 056-EQUIPE COMERCIAL 4 | I68: =_xlfn.XLOOKUP(fatoG1[[#This Row],[Centro de Custo]],dimCentroCusto[Centro_Custo],dimCentroCusto[Codigo_CentroCusto]) -> #N/A | J68: =fatoG1[[#This Row],[Desc. C. Custo Cliente]] -> 056-EQUIPE COMERCIAL 4 | N68: GONCALVES/THIAGO NARCISO OLIVEIRA | O68: =_xlfn.XLOOKUP(N68,DEPARA!F:F,DEPARA!H:H,0) -> THIAGO NARCISO OLIVEIRA GONÇALVES | P68: =_xlfn.XLOOKUP(O68,dimColaborador!A:A,dimColaborador!B:B,0) -> 26516 | Q68: =_xlfn.XLOOKUP(O68,dimColaborador!A:A,dimColaborador!C:C,) -> DR - PRIME - CENTRO OESTE | R68: =_xlfn.XLOOKUP(O68,dimColaborador!A:A,dimColaborador!D:D) -> DISTRIBUIDOR | S68: CURITIBA | T68: 31/03/25 a 04/04/25 - POLO, HB20, 208 (1.0) OU SIMILAR / DIR | U68: 45747 | V68: 45751 | X68: 0 | Y68: 0 | Z68: 195.23 | AA68: 0 | AB68: 195.23
A69: 45868 | B69: 53788 | C69: 6834 | D69: CAR | E69: UNIDAS | F69: =_xlfn.XLOOKUP(E69,DEPARA!A:A,DEPARA!C:C,"Verificar") -> LOCAÇÃO DE VEÍCULOS | G69: FIRSTLAB IND. IMP. E EXP. DE PROD. PARA LAB. LTDA | H69: 056-EQUIPE COMERCIAL 4 | I69: =_xlfn.XLOOKUP(fatoG1[[#This Row],[Centro de Custo]],dimCentroCusto[Centro_Custo],dimCentroCusto[Codigo_CentroCusto]) -> #N/A | J69: =fatoG1[[#This Row],[Desc. C. Custo Cliente]] -> 056-EQUIPE COMERCIAL 4 | L69: VIAGEM LABCHECAP | N69: ALMEIDA/KHARLA NAYARA ABRANTES | O69: =_xlfn.XLOOKUP(N69,DEPARA!F:F,DEPARA!H:H,0) -> KHARLA NAYARA ABRANTES DE ALMEIDA | P69: =_xlfn.XLOOKUP(O69,dimColaborador!A:A,dimColaborador!B:B,0) -> 26175 | Q69: =_xlfn.XLOOKUP(O69,dimColaborador!A:A,dimColaborador!C:C,) -> GC -MÉDIO/GRANDE PORTE - NO/NE | R69: =_xlfn.XLOOKUP(O69,dimColaborador!A:A,dimColaborador!D:D) -> GRANDES CONTAS | S69: CURITIBA | T69: 27/05/25 a 29/05/25 - VOLKSWAGEN POLO 200 TSI, PEUGEOT 208, | U69: 45804 | V69: 45806 | X69: 0 | Y69: 0 | Z69: 187.42 | AA69: 0 | AB69: 187.42
A70: 45877 | B70: 50716 | C70: 6865 | D70: CAR | E70: LOCALIZA | F70: =_xlfn.XLOOKUP(E70,DEPARA!A:A,DEPARA!C:C,"Verificar") -> LOCAÇÃO DE VEÍCULOS | G70: FIRSTLAB IND. IMP. E EXP. DE PROD. PARA LAB. LTDA | H70: 049-EQUIPE COMERCIAL 1 | I70: =_xlfn.XLOOKUP(fatoG1[[#This Row],[Centro de Custo]],dimCentroCusto[Centro_Custo],dimCentroCusto[Codigo_CentroCusto]) -> #N/A | J70: =fatoG1[[#This Row],[Desc. C. Custo Cliente]] -> 049-EQUIPE COMERCIAL 1 | N70: VAZ/LETICIA CAMPOS DA SILVA | O70: =_xlfn.XLOOKUP(N70,DEPARA!F:F,DEPARA!H:H,0) -> LETICIA CAMPOS DA SILVA VAZ | P70: =_xlfn.XLOOKUP(O70,dimColaborador!A:A,dimColaborador!B:B,0) -> 26385 | Q70: =_xlfn.XLOOKUP(O70,dimColaborador!A:A,dimColaborador!C:C,) -> GC - MÉDIO/GRANDE PORTE - SUL | R70: =_xlfn.XLOOKUP(O70,dimColaborador!A:A,dimColaborador!D:D) -> GRANDES CONTAS | S70: SAO JOSE DOS PINHAIS | T70: 10/06/25 a 12/06/25 - FIAT ARGO, ONIX LT, VW POLO, PEUGEOT 2 | U70: 45818 | V70: 45820 | W70: 2118 | X70: 534102 | Y70: 803.5 | Z70: 54.95 | AA70: 0 | AB70: 858.45
A71: 45876 | B71: 52415 | C71: 6865 | D71: HTL | E71: OMNIBEES | F71: =_xlfn.XLOOKUP(E71,DEPARA!A:A,DEPARA!C:C,"Verificar") -> HOSPEDAGEM | G71: FIRSTLAB IND. IMP. E EXP. DE PROD. PARA LAB. LTDA | H71: 055-EQUIPE COMERCIAL 3 | I71: =_xlfn.XLOOKUP(fatoG1[[#This Row],[Centro de Custo]],dimCentroCusto[Centro_Custo],dimCentroCusto[Codigo_CentroCusto]) -> #N/A | J71: =fatoG1[[#This Row],[Desc. C. Custo Cliente]] -> 055-EQUIPE COMERCIAL 3 | L71: VISITA CLIENTES DA REGIÃO | N71: LUZ/MARCIO ARRUDA | O71: =_xlfn.XLOOKUP(N71,DEPARA!F:F,DEPARA!H:H,0) -> MARCIO ARRUDA LUZ | P71: =_xlfn.XLOOKUP(O71,dimColaborador!A:A,dimColaborador!B:B,0) -> 25745 | Q71: =_xlfn.XLOOKUP(O71,dimColaborador!A:A,dimColaborador!C:C,) -> GC - MÉDIO/GRANDE PORTE - SE/CO | R71: =_xlfn.XLOOKUP(O71,dimColaborador!A:A,dimColaborador!D:D) -> GRANDES CONTAS | S71: SAO PAULO | T71: 01 CLASSIC CAMA QUEEN - 05/08/25 a 07/08/25 | U71: 45874 | V71: 45876 | W71: RES0 | X71: 40847- | Y71: 528.96 | Z71: 55.68 | AA71: 0 | AB71: 584.64
A72: 45877 | B72: 52416 | C72: 6865 | D72: HTL | E72: MULTIPARQUE HPLUS LONG STAY | F72: =_xlfn.XLOOKUP(E72,DEPARA!A:A,DEPARA!C:C,"Verificar") -> HOSPEDAGEM | G72: FIRSTLAB IND. IMP. E EXP. DE PROD. PARA LAB. LTDA | H72: 055-EQUIPE COMERCIAL 3 | I72: =_xlfn.XLOOKUP(fatoG1[[#This Row],[Centro de Custo]],dimCentroCusto[Centro_Custo],dimCentroCusto[Codigo_CentroCusto]) -> #N/A | J72: =fatoG1[[#This Row],[Desc. C. Custo Cliente]] -> 055-EQUIPE COMERCIAL 3 | L72: VISITA CLIENTES DA REGIÃO | N72: LUZ/MARCIO ARRUDA | O72: =_xlfn.XLOOKUP(N72,DEPARA!F:F,DEPARA!H:H,0) -> MARCIO ARRUDA LUZ | P72: =_xlfn.XLOOKUP(O72,dimColaborador!A:A,dimColaborador!B:B,0) -> 25745 | Q72: =_xlfn.XLOOKUP(O72,dimColaborador!A:A,dimColaborador!C:C,) -> GC - MÉDIO/GRANDE PORTE - SE/CO | R72: =_xlfn.XLOOKUP(O72,dimColaborador!A:A,dimColaborador!D:D) -> GRANDES CONTAS | T72: 01 LUXO - 07/08/25 a 08/08/25 | U72: 45876 | V72: 45877 | W72: 4 | X72: 840022 | Y72: 294 | Z72: 29.4 | AA72: 0 | AB72: 323.4
A73: 45876 | B73: 52418 | C73: 6865 | D73: HTL | E73: OMNIBEES | F73: =_xlfn.XLOOKUP(E73,DEPARA!A:A,DEPARA!C:C,"Verificar") -> HOSPEDAGEM | G73: FIRSTLAB IND. IMP. E EXP. DE PROD. PARA LAB. LTDA | H73: 049-EQUIPE COMERCIAL 1 | I73: =_xlfn.XLOOKUP(fatoG1[[#This Row],[Centro de Custo]],dimCentroCusto[Centro_Custo],dimCentroCusto[Codigo_CentroCusto]) -> #N/A | J73: =fatoG1[[#This Row],[Desc. C. Custo Cliente]] -> 049-EQUIPE COMERCIAL 1 | L73: VISITAÇÃO DE CLIENTES | N73: SCALON/AMANDA | O73: =_xlfn.XLOOKUP(N73,DEPARA!F:F,DEPARA!H:H,0) -> AMANDA BRANCHER SCALON | P73: =_xlfn.XLOOKUP(O73,dimColaborador!A:A,dimColaborador!B:B,0) -> 8254 | Q73: =_xlfn.XLOOKUP(O73,dimColaborador!A:A,dimColaborador!C:C,) -> SUPERVISORA EXTERNA FIRSTLAB | R73: =_xlfn.XLOOKUP(O73,dimColaborador!A:A,dimColaborador!D:D) -> SUPERVISORA EXTERNA FIRSTLAB | S73: SAO PAULO | T73: 01 SUPERIOR TWIN NÃO FUMANTE SUTN - 04/08/25 a 07/08/25 | U73: 45873 | V73: 45876 | W73: RES0 | X73: 12086- | Y73: 906.02 | Z73: 39.74 | AA73: 0 | AB73: 945.76
A74: 45876 | B74: 52419 | C74: 6865 | D74: HTL | E74: OMNIBEES | F74: =_xlfn.XLOOKUP(E74,DEPARA!A:A,DEPARA!C:C,"Verificar") -> HOSPEDAGEM | G74: FIRSTLAB IND. IMP. E EXP. DE PROD. PARA LAB. LTDA | H74: 048-COMERCIAL INTERNO | I74: =_xlfn.XLOOKUP(fatoG1[[#This Row],[Centro de Custo]],dimCentroCusto[Centro_Custo],dimCentroCusto[Codigo_CentroCusto]) -> #N/A | J74: =fatoG1[[#This Row],[Desc. C. Custo Cliente]] -> 048-COMERCIAL INTERNO | L74: VISITA COMERCIAL | N74: PEREIRA/FELIPE LUIZ RIBEIRO | O74: =_xlfn.XLOOKUP(N74,DEPARA!F:F,DEPARA!H:H,0) -> FELIPE LUIZ RIBEIRO PEREIRA | P74: =_xlfn.XLOOKUP(O74,dimColaborador!A:A,dimColaborador!B:B,0) -> 26387 | Q74: =_xlfn.XLOOKUP(O74,dimColaborador!A:A,dimColaborador!C:C,) -> GC - MÉDIO/GRANDE PORTE - SP | R74: =_xlfn.XLOOKUP(O74,dimColaborador!A:A,dimColaborador!D:D) -> GRANDES CONTAS | S74: SAO PAULO | T74: 01 SUPERIOR TWIN NÃO FUMANTE SUTN - 04/08/25 a 07/08/25 | U74: 45873 | V74: 45876 | W74: RES0 | X74: 12094- | Y74: 906.02 | Z74: 39.74 | AA74: 0 | AB74: 945.76
A75: 45870 | B75: 52728 | C75: 6865 | D75: HTL | E75: OMNIBEES | F75: =_xlfn.XLOOKUP(E75,DEPARA!A:A,DEPARA!C:C,"Verificar") -> HOSPEDAGEM | G75: FIRSTLAB IND. IMP. E EXP. DE PROD. PARA LAB. LTDA | H75: 055-EQUIPE COMERCIAL 3 | I75: =_xlfn.XLOOKUP(fatoG1[[#This Row],[Centro de Custo]],dimCentroCusto[Centro_Custo],dimCentroCusto[Codigo_CentroCusto]) -> #N/A | J75: =fatoG1[[#This Row],[Desc. C. Custo Cliente]] -> 055-EQUIPE COMERCIAL 3 | L75: VISITA CLIENTES DA REGIÃO/ TREINAMENTO | N75: LUZ/MARCIO ARRUDA | O75: =_xlfn.XLOOKUP(N75,DEPARA!F:F,DEPARA!H:H,0) -> MARCIO ARRUDA LUZ | P75: =_xlfn.XLOOKUP(O75,dimColaborador!A:A,dimColaborador!B:B,0) -> 25745 | Q75: =_xlfn.XLOOKUP(O75,dimColaborador!A:A,dimColaborador!C:C,) -> GC - MÉDIO/GRANDE PORTE - SE/CO | R75: =_xlfn.XLOOKUP(O75,dimColaborador!A:A,dimColaborador!D:D) -> GRANDES CONTAS | S75: SAO PAULO | T75: 01 VIP - 30/07/25 a 01/08/25 | U75: 45868 | V75: 45870 | W75: RES0 | X75: 10416- | Y75: 536.51 | Z75: 0 | AA75: 0 | AB75: 536.51
A76: 45874 | B76: 53863 | C76: 6865 | D76: HTL | E76: HOTEL INTERCITY PORTOFINO FLORIANÓPOLIS | F76: =_xlfn.XLOOKUP(E76,DEPARA!A:A,DEPARA!C:C,"Verificar") -> HOSPEDAGEM | G76: FIRSTLAB IND. IMP. E EXP. DE PROD. PARA LAB. LTDA | H76: 048-COMERCIAL INTERNO | I76: =_xlfn.XLOOKUP(fatoG1[[#This Row],[Centro de Custo]],dimCentroCusto[Centro_Custo],dimCentroCusto[Codigo_CentroCusto]) -> #N/A | J76: =fatoG1[[#This Row],[Desc. C. Custo Cliente]] -> 048-COMERCIAL INTERNO | N76: SANTOS/LAURA | O76: =_xlfn.XLOOKUP(N76,DEPARA!F:F,DEPARA!H:H,0) -> LAURA BENTO DOS SANTOS | P76: =_xlfn.XLOOKUP(O76,dimColaborador!A:A,dimColaborador!B:B,0) -> 9999999910 | Q76: =_xlfn.XLOOKUP(O76,dimColaborador!A:A,dimColaborador!C:C,) -> COORDENADORA FIRSTLAB | R76: =_xlfn.XLOOKUP(O76,dimColaborador!A:A,dimColaborador!D:D) -> COORDENADORA FIRSTLAB | S76: FLORIANOPOLIS | T76: 01 STANDARD TWIN - 2 CAMAS SOLTEIRO - 04/08/25 a 05/08/25 | U76: 45873 | V76: 45874 | W76: 4000 | X76: 581178 | Y76: 352.5 | Z76: 8.81 | AA76: 0 | AB76: 361.31
A77: 45875 | B77: 54004 | C77: 6865 | D77: HTL | E77: SLIM GUARAPUAVA | F77: =_xlfn.XLOOKUP(E77,DEPARA!A:A,DEPARA!C:C,"Verificar") -> HOSPEDAGEM | G77: FIRSTLAB IND. IMP. E EXP. DE PROD. PARA LAB. LTDA | H77: 049-EQUIPE COMERCIAL 1 | I77: =_xlfn.XLOOKUP(fatoG1[[#This Row],[Centro de Custo]],dimCentroCusto[Centro_Custo],dimCentroCusto[Codigo_CentroCusto]) -> #N/A | J77: =fatoG1[[#This Row],[Desc. C. Custo Cliente]] -> 049-EQUIPE COMERCIAL 1 | N77: VAZ/LETICIA CAMPOS DA SILVA | O77: =_xlfn.XLOOKUP(N77,DEPARA!F:F,DEPARA!H:H,0) -> LETICIA CAMPOS DA SILVA VAZ | P77: =_xlfn.XLOOKUP(O77,dimColaborador!A:A,dimColaborador!B:B,0) -> 26385 | Q77: =_xlfn.XLOOKUP(O77,dimColaborador!A:A,dimColaborador!C:C,) -> GC - MÉDIO/GRANDE PORTE - SUL | R77: =_xlfn.XLOOKUP(O77,dimColaborador!A:A,dimColaborador!D:D) -> GRANDES CONTAS | S77: GUARAPUAVA | T77: 01 STANDARD TWIN - 05/08/25 a 06/08/25 | U77: 45874 | V77: 45875 | W77: RES0 | X77: 39577- | Y77: 287.79 | Z77: 12.62 | AA77: 0 | AB77: 300.41
A78: 45877 | B78: 54083 | C78: 6865 | D78: TKT | E78: GOL LINHAS AÉREAS | F78: =_xlfn.XLOOKUP(E78,DEPARA!A:A,DEPARA!C:C,"Verificar") -> PASSAGEM | G78: FIRSTLAB IND. IMP. E EXP. DE PROD. PARA LAB. LTDA | H78: 049-EQUIPE COMERCIAL 1 | I78: =_xlfn.XLOOKUP(fatoG1[[#This Row],[Centro de Custo]],dimCentroCusto[Centro_Custo],dimCentroCusto[Codigo_CentroCusto]) -> #N/A | J78: =fatoG1[[#This Row],[Desc. C. Custo Cliente]] -> 049-EQUIPE COMERCIAL 1 | N78: OLIVEIRA/JOANA MARIA TEIXEIRA DE | O78: =_xlfn.XLOOKUP(N78,DEPARA!F:F,DEPARA!H:H,0) -> JOANA MARIA TEIXEIRA DE OLIVEIRA | P78: =_xlfn.XLOOKUP(O78,dimColaborador!A:A,dimColaborador!B:B,0) -> 26136 | Q78: =_xlfn.XLOOKUP(O78,dimColaborador!A:A,dimColaborador!C:C,) -> GRANDES CONTAS NACIONAIS | R78: =_xlfn.XLOOKUP(O78,dimColaborador!A:A,dimColaborador!D:D) -> GRANDES CONTAS | S78: SAO JOSE DOS PINHAIS | T78: VCP/GIG/VCP | U78: 45889 | V78: 45891 | W78: 2142 | X78: 978198 | Y78: 1104.22 | Z78: 64.43 | AA78: 88.34 | AB78: 1256.99
A79: 45882 | B79: 39505 | C79: 6895 | D79: CAR | E79: UNIDAS | F79: =_xlfn.XLOOKUP(E79,DEPARA!A:A,DEPARA!C:C,"Verificar") -> LOCAÇÃO DE VEÍCULOS | G79: FIRSTLAB IND. IMP. E EXP. DE PROD. PARA LAB. LTDA | H79: 056-EQUIPE COMERCIAL 4 | I79: =_xlfn.XLOOKUP(fatoG1[[#This Row],[Centro de Custo]],dimCentroCusto[Centro_Custo],dimCentroCusto[Codigo_CentroCusto]) -> #N/A | J79: =fatoG1[[#This Row],[Desc. C. Custo Cliente]] -> 056-EQUIPE COMERCIAL 4 | N79: GUIBYSON SILVA FERREIRA | O79: =_xlfn.XLOOKUP(N79,DEPARA!F:F,DEPARA!H:H,0) -> GUIBYSON SILVA FERREIRA | P79: =_xlfn.XLOOKUP(O79,dimColaborador!A:A,dimColaborador!B:B,0) -> 25808 | Q79: =_xlfn.XLOOKUP(O79,dimColaborador!A:A,dimColaborador!C:C,) -> CONSULTOR DESLIGADO | R79: =_xlfn.XLOOKUP(O79,dimColaborador!A:A,dimColaborador!D:D) -> CONSULTOR DESLIGADO | S79: CURITIBA | T79: 01/07/24 a 05/07/24 - EA - AEROPORTO INTERNACIONAL DEPUTADO | U79: 45474 | V79: 45478 | W79: 2117 | X79: 665752 | Y79: 1250.01 | Z79: 41.9 | AA79: 0 | AB79: 1291.91
A80: 45882 | B80: 41395 | C80: 6895 | D80: CAR | E80: UNIDAS | F80: =_xlfn.XLOOKUP(E80,DEPARA!A:A,DEPARA!C:C,"Verificar") -> LOCAÇÃO DE VEÍCULOS | G80: FIRSTLAB IND. IMP. E EXP. DE PROD. PARA LAB. LTDA | H80: 055-EQUIPE COMERCIAL 3 | I80: =_xlfn.XLOOKUP(fatoG1[[#This Row],[Centro de Custo]],dimCentroCusto[Centro_Custo],dimCentroCusto[Codigo_CentroCusto]) -> #N/A | J80: =fatoG1[[#This Row],[Desc. C. Custo Cliente]] -> 055-EQUIPE COMERCIAL 3 | N80: MARCIO ARRUDA LUZ | O80: =_xlfn.XLOOKUP(N80,DEPARA!F:F,DEPARA!H:H,0) -> MARCIO ARRUDA LUZ | P80: =_xlfn.XLOOKUP(O80,dimColaborador!A:A,dimColaborador!B:B,0) -> 25745 | Q80: =_xlfn.XLOOKUP(O80,dimColaborador!A:A,dimColaborador!C:C,) -> GC - MÉDIO/GRANDE PORTE - SE/CO | R80: =_xlfn.XLOOKUP(O80,dimColaborador!A:A,dimColaborador!D:D) -> GRANDES CONTAS | S80: CURITIBA | T80: 02/09/24 a 06/09/24 - EA - AEROPORTO INTER. GOIANIA - SANTA | U80: 45537 | V80: 45541 | W80: 2117 | X80: 795207 | Y80: 1044.21 | Z80: 462.74 | AA80: 0 | AB80: 1506.95
A81: 45883 | B81: 52417 | C81: 6895 | D81: HTL | E81: NOBILE HOTEL BELO HORIZONTE | F81: =_xlfn.XLOOKUP(E81,DEPARA!A:A,DEPARA!C:C,"Verificar") -> HOSPEDAGEM | G81: FIRSTLAB IND. IMP. E EXP. DE PROD. PARA LAB. LTDA | H81: 055-EQUIPE COMERCIAL 3 | I81: =_xlfn.XLOOKUP(fatoG1[[#This Row],[Centro de Custo]],dimCentroCusto[Centro_Custo],dimCentroCusto[Codigo_CentroCusto]) -> #N/A | J81: =fatoG1[[#This Row],[Desc. C. Custo Cliente]] -> 055-EQUIPE COMERCIAL 3 | L81: VISITA CLIENTES DA REGIÃO | N81: LUZ/MARCIO ARRUDA | O81: =_xlfn.XLOOKUP(N81,DEPARA!F:F,DEPARA!H:H,0) -> MARCIO ARRUDA LUZ | P81: =_xlfn.XLOOKUP(O81,dimColaborador!A:A,dimColaborador!B:B,0) -> 25745 | Q81: =_xlfn.XLOOKUP(O81,dimColaborador!A:A,dimColaborador!C:C,) -> GC - MÉDIO/GRANDE PORTE - SE/CO | R81: =_xlfn.XLOOKUP(O81,dimColaborador!A:A,dimColaborador!D:D) -> GRANDES CONTAS | S81: BELO HORIZONTE | T81: 01 SUPERIOR CASAL - 12/08/25 a 14/08/25 | U81: 45881 | V81: 45883 | W81: 4000 | X81: 474936 | Y81: 464 | Z81: 23.2 | AA81: 0 | AB81: 487.2
A82: 45883 | B82: 52493 | C82: 6895 | D82: HTL | E82: MASTER COSMOPOLITAN HOTEL MOINHOS DE VENTO | F82: =_xlfn.XLOOKUP(E82,DEPARA!A:A,DEPARA!C:C,"Verificar") -> HOSPEDAGEM | G82: FIRSTLAB IND. IMP. E EXP. DE PROD. PARA LAB. LTDA | H82: 049-EQUIPE COMERCIAL 1 | I82: =_xlfn.XLOOKUP(fatoG1[[#This Row],[Centro de Custo]],dimCentroCusto[Centro_Custo],dimCentroCusto[Codigo_CentroCusto]) -> #N/A | J82: =fatoG1[[#This Row],[Desc. C. Custo Cliente]] -> 049-EQUIPE COMERCIAL 1 | N82: OLIVEIRA/JOANA MARIA TEIXEIRA DE | O82: =_xlfn.XLOOKUP(N82,DEPARA!F:F,DEPARA!H:H,0) -> JOANA MARIA TEIXEIRA DE OLIVEIRA | P82: =_xlfn.XLOOKUP(O82,dimColaborador!A:A,dimColaborador!B:B,0) -> 26136 | Q82: =_xlfn.XLOOKUP(O82,dimColaborador!A:A,dimColaborador!C:C,) -> GRANDES CONTAS NACIONAIS | R82: =_xlfn.XLOOKUP(O82,dimColaborador!A:A,dimColaborador!D:D) -> GRANDES CONTAS | S82: PORTO ALEGRE | T82: 01 EXPRESS DUAS CAMAS - 12/08/25 a 14/08/25 | U82: 45881 | V82: 45883 | W82: 4 | X82: 842728 | Y82: 533.89 | Z82: 0.01 | AA82: 0 | AB82: 533.9
A83: 45882 | B83: 53836 | C83: 6895 | D83: HTL | E83: PAJUÇARA HOTEL EXPRESS | F83: =_xlfn.XLOOKUP(E83,DEPARA!A:A,DEPARA!C:C,"Verificar") -> HOSPEDAGEM | G83: FIRSTLAB IND. IMP. E EXP. DE PROD. PARA LAB. LTDA | H83: 056-EQUIPE COMERCIAL 4 | I83: =_xlfn.XLOOKUP(fatoG1[[#This Row],[Centro de Custo]],dimCentroCusto[Centro_Custo],dimCentroCusto[Codigo_CentroCusto]) -> #N/A | J83: =fatoG1[[#This Row],[Desc. C. Custo Cliente]] -> 056-EQUIPE COMERCIAL 4 | N83: ALMEIDA/KHARLA NAYARA ABRANTES | O83: =_xlfn.XLOOKUP(N83,DEPARA!F:F,DEPARA!H:H,0) -> KHARLA NAYARA ABRANTES DE ALMEIDA | P83: =_xlfn.XLOOKUP(O83,dimColaborador!A:A,dimColaborador!B:B,0) -> 26175 | Q83: =_xlfn.XLOOKUP(O83,dimColaborador!A:A,dimColaborador!C:C,) -> GC -MÉDIO/GRANDE PORTE - NO/NE | R83: =_xlfn.XLOOKUP(O83,dimColaborador!A:A,dimColaborador!D:D) -> GRANDES CONTAS | S83: MACEIÓ | T83: 01 FRENTE MAR - 11/08/25 a 13/08/25 | U83: 45880 | V83: 45882 | W83: RES0 | X83: 33815- | Y83: 492.48 | Z83: 17.28 | AA83: 0 | AB83: 509.76
A84: 45884 | B84: 53837 | C84: 6895 | D84: HTL | E84: VILA AJU POUSADA TEMATICA | F84: =_xlfn.XLOOKUP(E84,DEPARA!A:A,DEPARA!C:C,"Verificar") -> HOSPEDAGEM | G84: FIRSTLAB IND. IMP. E EXP. DE PROD. PARA LAB. LTDA | H84: 056-EQUIPE COMERCIAL 4 | I84: =_xlfn.XLOOKUP(fatoG1[[#This Row],[Centro de Custo]],dimCentroCusto[Centro_Custo],dimCentroCusto[Codigo_CentroCusto]) -> #N/A | J84: =fatoG1[[#This Row],[Desc. C. Custo Cliente]] -> 056-EQUIPE COMERCIAL 4 | N84: ALMEIDA/KHARLA NAYARA ABRANTES | O84: =_xlfn.XLOOKUP(N84,DEPARA!F:F,DEPARA!H:H,0) -> KHARLA NAYARA ABRANTES DE ALMEIDA | P84: =_xlfn.XLOOKUP(O84,dimColaborador!A:A,dimColaborador!B:B,0) -> 26175 | Q84: =_xlfn.XLOOKUP(O84,dimColaborador!A:A,dimColaborador!C:C,) -> GC -MÉDIO/GRANDE PORTE - NO/NE | R84: =_xlfn.XLOOKUP(O84,dimColaborador!A:A,dimColaborador!D:D) -> GRANDES CONTAS | S84: ARACAJU | T84: 01 SUÍTE STANDARD DUPLO - 13/08/25 a 15/08/25 | U84: 45882 | V84: 45884 | W84: 4000 | X84: 579014 | Y84: 387.17 | Z84: 0 | AA84: 0 | AB84: 387.17
A85: 45883 | B85: 54006 | C85: 6895 | D85: HTL | E85: IBIS BUDGET PORTO ALEGRE | F85: =_xlfn.XLOOKUP(E85,DEPARA!A:A,DEPARA!C:C,"Verificar") -> HOSPEDAGEM | G85: FIRSTLAB IND. IMP. E EXP. DE PROD. PARA LAB. LTDA | H85: 049-EQUIPE COMERCIAL 1 | I85: =_xlfn.XLOOKUP(fatoG1[[#This Row],[Centro de Custo]],dimCentroCusto[Centro_Custo],dimCentroCusto[Codigo_CentroCusto]) -> #N/A | J85: =fatoG1[[#This Row],[Desc. C. Custo Cliente]] -> 049-EQUIPE COMERCIAL 1 | N85: VAZ/LETICIA CAMPOS DA SILVA | O85: =_xlfn.XLOOKUP(N85,DEPARA!F:F,DEPARA!H:H,0) -> LETICIA CAMPOS DA SILVA VAZ | P85: =_xlfn.XLOOKUP(O85,dimColaborador!A:A,dimColaborador!B:B,0) -> 26385 | Q85: =_xlfn.XLOOKUP(O85,dimColaborador!A:A,dimColaborador!C:C,) -> GC - MÉDIO/GRANDE PORTE - SUL | R85: =_xlfn.XLOOKUP(O85,dimColaborador!A:A,dimColaborador!D:D) -> GRANDES CONTAS | S85: PORTO ALEGRE | T85: 01 DBD STANDARD COM 1 CAMA CASAL - 12/08/25 a 14/08/25 | U85: 45881 | V85: 45883 | W85: 4000 | X85: 586489 | Y85: 528 | Z85: 26.4 | AA85: 0 | AB85: 554.4
A86: 45883 | B86: 54123 | C86: 6895 | D86: HTL | E86: HOTEL NACIONAL INN BAURU | F86: =_xlfn.XLOOKUP(E86,DEPARA!A:A,DEPARA!C:C,"Verificar") -> HOSPEDAGEM | G86: FIRSTLAB IND. IMP. E EXP. DE PROD. PARA LAB. LTDA | H86: 048-COMERCIAL INTERNO | I86: =_xlfn.XLOOKUP(fatoG1[[#This Row],[Centro de Custo]],dimCentroCusto[Centro_Custo],dimCentroCusto[Codigo_CentroCusto]) -> #N/A | J86: =fatoG1[[#This Row],[Desc. C. Custo Cliente]] -> 048-COMERCIAL INTERNO | L86: VISITA COMERCIAL | N86: PEREIRA/FELIPE LUIZ RIBEIRO | O86: =_xlfn.XLOOKUP(N86,DEPARA!F:F,DEPARA!H:H,0) -> FELIPE LUIZ RIBEIRO PEREIRA | P86: =_xlfn.XLOOKUP(O86,dimColaborador!A:A,dimColaborador!B:B,0) -> 26387 | Q86: =_xlfn.XLOOKUP(O86,dimColaborador!A:A,dimColaborador!C:C,) -> GC - MÉDIO/GRANDE PORTE - SP | R86: =_xlfn.XLOOKUP(O86,dimColaborador!A:A,dimColaborador!D:D) -> GRANDES CONTAS | S86: BAURU | T86: 01 STANDARD TWIN - 13/08/25 a 14/08/25 | U86: 45882 | V86: 45883 | W86: 4000 | X86: 600508 | Y86: 251.1 | Z86: 0 | AA86: 0 | AB86: 251.1
A87: 45881 | B87: 54194 | C87: 6895 | D87: TKT | E87: TAM LINHAS AÉREAS | F87: =_xlfn.XLOOKUP(E87,DEPARA!A:A,DEPARA!C:C,"Verificar") -> PASSAGEM | G87: FIRSTLAB IND. IMP. E EXP. DE PROD. PARA LAB. LTDA | H87: 056-EQUIPE COMERCIAL 4 | I87: =_xlfn.XLOOKUP(fatoG1[[#This Row],[Centro de Custo]],dimCentroCusto[Centro_Custo],dimCentroCusto[Codigo_CentroCusto]) -> #N/A | J87: =fatoG1[[#This Row],[Desc. C. Custo Cliente]] -> 056-EQUIPE COMERCIAL 4 | L87: FIRSTDAY - DNA CENTER | N87: ALMEIDA/KHARLA NAYARA ABRANTES | O87: =_xlfn.XLOOKUP(N87,DEPARA!F:F,DEPARA!H:H,0) -> KHARLA NAYARA ABRANTES DE ALMEIDA | P87: =_xlfn.XLOOKUP(O87,dimColaborador!A:A,dimColaborador!B:B,0) -> 26175 | Q87: =_xlfn.XLOOKUP(O87,dimColaborador!A:A,dimColaborador!C:C,) -> GC -MÉDIO/GRANDE PORTE - NO/NE | R87: =_xlfn.XLOOKUP(O87,dimColaborador!A:A,dimColaborador!D:D) -> GRANDES CONTAS | S87: SAO JOSE DOS PINHAIS | T87: JPA*GRU/CWB | U87: 45952 | V87: 45952 | W87: 2245 | X87: 503646 | Y87: 567.85 | Z87: 51.67 | AA87: 45.43 | AB87: 664.95
A88: 45881 | B88: 54195 | C88: 6895 | D88: TKT | E88: GOL LINHAS AÉREAS | F88: =_xlfn.XLOOKUP(E88,DEPARA!A:A,DEPARA!C:C,"Verificar") -> PASSAGEM | G88: FIRSTLAB IND. IMP. E EXP. DE PROD. PARA LAB. LTDA | H88: 056-EQUIPE COMERCIAL 4 | I88: =_xlfn.XLOOKUP(fatoG1[[#This Row],[Centro de Custo]],dimCentroCusto[Centro_Custo],dimCentroCusto[Codigo_CentroCusto]) -> #N/A | J88: =fatoG1[[#This Row],[Desc. C. Custo Cliente]] -> 056-EQUIPE COMERCIAL 4 | L88: FIRSTDAY - DNA CENTER | N88: ALMEIDA/KHARLA NAYARA ABRANTES | O88: =_xlfn.XLOOKUP(N88,DEPARA!F:F,DEPARA!H:H,0) -> KHARLA NAYARA ABRANTES DE ALMEIDA | P88: =_xlfn.XLOOKUP(O88,dimColaborador!A:A,dimColaborador!B:B,0) -> 26175 | Q88: =_xlfn.XLOOKUP(O88,dimColaborador!A:A,dimColaborador!C:C,) -> GC -MÉDIO/GRANDE PORTE - NO/NE | R88: =_xlfn.XLOOKUP(O88,dimColaborador!A:A,dimColaborador!D:D) -> GRANDES CONTAS | S88: SAO JOSE DOS PINHAIS | T88: CWB*GIG/JPA | U88: 45954 | V88: 45955 | W88: 2143 | X88: 295520 | Y88: 906.32 | Z88: 46.72 | AA88: 72.51 | AB88: 1025.55
A89: 45891 | B89: 48294 | C89: 6932 | D89: CAR | E89: MOVIDA RENT A CAR | F89: =_xlfn.XLOOKUP(E89,DEPARA!A:A,DEPARA!C:C,"Verificar") -> LOCAÇÃO DE VEÍCULOS | G89: FIRSTLAB IND. IMP. E EXP. DE PROD. PARA LAB. LTDA | H89: 049-EQUIPE COMERCIAL 1 | I89: =_xlfn.XLOOKUP(fatoG1[[#This Row],[Centro de Custo]],dimCentroCusto[Centro_Custo],dimCentroCusto[Codigo_CentroCusto]) -> #N/A | J89: =fatoG1[[#This Row],[Desc. C. Custo Cliente]] -> 049-EQUIPE COMERCIAL 1 | L89: VISITAÇÃO A CLIENTES, VALIDADO POR AMANDA | N89: VAZ/LETICIA CAMPOS DA SILVA | O89: =_xlfn.XLOOKUP(N89,DEPARA!F:F,DEPARA!H:H,0) -> LETICIA CAMPOS DA SILVA VAZ | P89: =_xlfn.XLOOKUP(O89,dimColaborador!A:A,dimColaborador!B:B,0) -> 26385 | Q89: =_xlfn.XLOOKUP(O89,dimColaborador!A:A,dimColaborador!C:C,) -> GC - MÉDIO/GRANDE PORTE - SUL | R89: =_xlfn.XLOOKUP(O89,dimColaborador!A:A,dimColaborador!D:D) -> GRANDES CONTAS | S89: CURITIBA | T89: 24/03/25 a 28/03/25 - 208, HB20, POLO OU SIMILAR (1.0 TURBO, | U89: 45740 | V89: 45744 | W89: 2118 | X89: 346843 | Y89: 764.97 | Z89: 353.13 | AA89: 0 | AB89: 1118.1
A90: 45891 | B90: 51356 | C90: 6932 | D90: CAR | E90: UNIDAS | F90: =_xlfn.XLOOKUP(E90,DEPARA!A:A,DEPARA!C:C,"Verificar") -> LOCAÇÃO DE VEÍCULOS | G90: FIRSTLAB IND. IMP. E EXP. DE PROD. PARA LAB. LTDA | H90: 049-EQUIPE COMERCIAL 1 | I90: =_xlfn.XLOOKUP(fatoG1[[#This Row],[Centro de Custo]],dimCentroCusto[Centro_Custo],dimCentroCusto[Codigo_CentroCusto]) -> #N/A | J90: =fatoG1[[#This Row],[Desc. C. Custo Cliente]] -> 049-EQUIPE COMERCIAL 1 | N90: VAZ/LETICIA CAMPOS DA SILVA | O90: =_xlfn.XLOOKUP(N90,DEPARA!F:F,DEPARA!H:H,0) -> LETICIA CAMPOS DA SILVA VAZ | P90: =_xlfn.XLOOKUP(O90,dimColaborador!A:A,dimColaborador!B:B,0) -> 26385 | Q90: =_xlfn.XLOOKUP(O90,dimColaborador!A:A,dimColaborador!C:C,) -> GC - MÉDIO/GRANDE PORTE - SUL | R90: =_xlfn.XLOOKUP(O90,dimColaborador!A:A,dimColaborador!D:D) -> GRANDES CONTAS | S90: CURITIBA | T90: 30/06/25 a 03/07/25 - VOLKSWAGEN POLO 200 TSI, PEUGEOT 208, | U90: 45838 | V90: 45841 | W90: 2118 | X90: 585986 | Y90: 537 | Z90: 112.1 | AA90: 0 | AB90: 649.1
A91: 45889 | B91: 52420 | C91: 6932 | D91: HTL | E91: OMNIBEES | F91: =_xlfn.XLOOKUP(E91,DEPARA!A:A,DEPARA!C:C,"Verificar") -> HOSPEDAGEM | G91: FIRSTLAB IND. IMP. E EXP. DE PROD. PARA LAB. LTDA | H91: 055-EQUIPE COMERCIAL 3 | I91: =_xlfn.XLOOKUP(fatoG1[[#This Row],[Centro de Custo]],dimCentroCusto[Centro_Custo],dimCentroCusto[Codigo_CentroCusto]) -> #N/A | J91: =fatoG1[[#This Row],[Desc. C. Custo Cliente]] -> 055-EQUIPE COMERCIAL 3 | L91: VISITA CLIENTES DA REGIÃO | N91: LUZ/MARCIO ARRUDA | O91: =_xlfn.XLOOKUP(N91,DEPARA!F:F,DEPARA!H:H,0) -> MARCIO ARRUDA LUZ | P91: =_xlfn.XLOOKUP(O91,dimColaborador!A:A,dimColaborador!B:B,0) -> 25745 | Q91: =_xlfn.XLOOKUP(O91,dimColaborador!A:A,dimColaborador!C:C,) -> GC - MÉDIO/GRANDE PORTE - SE/CO | R91: =_xlfn.XLOOKUP(O91,dimColaborador!A:A,dimColaborador!D:D) -> GRANDES CONTAS | S91: SAO PAULO | T91: 01 APARTAMENTO LUXO SINGLE - 19/08/25 a 20/08/25 | U91: 45888 | V91: 45889 | W91: RES0 | X91: 00961- | Y91: 180.58 | Z91: 0 | AA91: 0 | AB91: 180.58
A92: 45890 | B92: 52421 | C92: 6932 | D92: HTL | E92: IBIS BUDGET CAMPO GRANDE | F92: =_xlfn.XLOOKUP(E92,DEPARA!A:A,DEPARA!C:C,"Verificar") -> HOSPEDAGEM | G92: FIRSTLAB IND. IMP. E EXP. DE PROD. PARA LAB. LTDA | H92: 055-EQUIPE COMERCIAL 3 | I92: =_xlfn.XLOOKUP(fatoG1[[#This Row],[Centro de Custo]],dimCentroCusto[Centro_Custo],dimCentroCusto[Codigo_CentroCusto]) -> #N/A | J92: =fatoG1[[#This Row],[Desc. C. Custo Cliente]] -> 055-EQUIPE COMERCIAL 3 | L92: VISITA CLIENTES DA REGIÃO | N92: LUZ/MARCIO ARRUDA | O92: =_xlfn.XLOOKUP(N92,DEPARA!F:F,DEPARA!H:H,0) -> MARCIO ARRUDA LUZ | P92: =_xlfn.XLOOKUP(O92,dimColaborador!A:A,dimColaborador!B:B,0) -> 25745 | Q92: =_xlfn.XLOOKUP(O92,dimColaborador!A:A,dimColaborador!C:C,) -> GC - MÉDIO/GRANDE PORTE - SE/CO | R92: =_xlfn.XLOOKUP(O92,dimColaborador!A:A,dimColaborador!D:D) -> GRANDES CONTAS | S92: CAMPO GRANDE | T92: 01 APARTAMENTO STANDARD COM CAMA CASAL - 20/08/25 a 21/08/2 | U92: 45889 | V92: 45890 | W92: 4000 | X92: 475119 | Y92: 229.78 | Z92: 11.49 | AA92: 0 | AB92: 241.27
A93: 45891 | B93: 52422 | C93: 6932 | D93: HTL | E93: HOTEL 365 CUIABA ANTIGO HOTEL PRESIDENCIAL | F93: =_xlfn.XLOOKUP(E93,DEPARA!A:A,DEPARA!C:C,"Verificar") -> HOSPEDAGEM | G93: FIRSTLAB IND. IMP. E EXP. DE PROD. PARA LAB. LTDA | H93: 055-EQUIPE COMERCIAL 3 | I93: =_xlfn.XLOOKUP(fatoG1[[#This Row],[Centro de Custo]],dimCentroCusto[Centro_Custo],dimCentroCusto[Codigo_CentroCusto]) -> #N/A | J93: =fatoG1[[#This Row],[Desc. C. Custo Cliente]] -> 055-EQUIPE COMERCIAL 3 | L93: VISITA CLIENTES DA REGIÃO | N93: LUZ/MARCIO ARRUDA | O93: =_xlfn.XLOOKUP(N93,DEPARA!F:F,DEPARA!H:H,0) -> MARCIO ARRUDA LUZ | P93: =_xlfn.XLOOKUP(O93,dimColaborador!A:A,dimColaborador!B:B,0) -> 25745 | Q93: =_xlfn.XLOOKUP(O93,dimColaborador!A:A,dimColaborador!C:C,) -> GC - MÉDIO/GRANDE PORTE - SE/CO | R93: =_xlfn.XLOOKUP(O93,dimColaborador!A:A,dimColaborador!D:D) -> GRANDES CONTAS | S93: CUIABÁ | T93: 01 LUXO CASAL - 21/08/25 a 22/08/25 | U93: 45890 | V93: 45891 | W93: 4 | X93: 840361 | Y93: 258.75 | Z93: 25.88 | AA93: 0 | AB93: 284.63
A94: 45888 | B94: 52555 | C94: 6932 | D94: HTL | E94: HUS HOTEL MARINGA (ANTIGO IBIS MARINGÁ) | F94: =_xlfn.XLOOKUP(E94,DEPARA!A:A,DEPARA!C:C,"Verificar") -> HOSPEDAGEM | G94: FIRSTLAB IND. IMP. E EXP. DE PROD. PARA LAB. LTDA | H94: 049-EQUIPE COMERCIAL 1 | I94: =_xlfn.XLOOKUP(fatoG1[[#This Row],[Centro de Custo]],dimCentroCusto[Centro_Custo],dimCentroCusto[Codigo_CentroCusto]) -> #N/A | J94: =fatoG1[[#This Row],[Desc. C. Custo Cliente]] -> 049-EQUIPE COMERCIAL 1 | N94: SCALON/AMANDA | O94: =_xlfn.XLOOKUP(N94,DEPARA!F:F,DEPARA!H:H,0) -> AMANDA BRANCHER SCALON | P94: =_xlfn.XLOOKUP(O94,dimColaborador!A:A,dimColaborador!B:B,0) -> 8254 | Q94: =_xlfn.XLOOKUP(O94,dimColaborador!A:A,dimColaborador!C:C,) -> SUPERVISORA EXTERNA FIRSTLAB | R94: =_xlfn.XLOOKUP(O94,dimColaborador!A:A,dimColaborador!D:D) -> SUPERVISORA EXTERNA FIRSTLAB | S94: MARINGÁ | T94: 01 APARTAMENTO STANDARD DUPLO : CAMA CASAL DBD - 18/08/25 a | U94: 45887 | V94: 45888 | W94: 4000 | X94: 482783 | Y94: 266.67 | Z94: 8 | AA94: 0 | AB94: 274.67
A95: 45888 | B95: 52556 | C95: 6932 | D95: HTL | E95: HUS HOTEL MARINGA (ANTIGO IBIS MARINGÁ) | F95: =_xlfn.XLOOKUP(E95,DEPARA!A:A,DEPARA!C:C,"Verificar") -> HOSPEDAGEM | G95: FIRSTLAB IND. IMP. E EXP. DE PROD. PARA LAB. LTDA | H95: 049-EQUIPE COMERCIAL 1 | I95: =_xlfn.XLOOKUP(fatoG1[[#This Row],[Centro de Custo]],dimCentroCusto[Centro_Custo],dimCentroCusto[Codigo_CentroCusto]) -> #N/A | J95: =fatoG1[[#This Row],[Desc. C. Custo Cliente]] -> 049-EQUIPE COMERCIAL 1 | N95: VAZ/LETICIA | O95: =_xlfn.XLOOKUP(N95,DEPARA!F:F,DEPARA!H:H,0) -> LETICIA CAMPOS DA SILVA VAZ | P95: =_xlfn.XLOOKUP(O95,dimColaborador!A:A,dimColaborador!B:B,0) -> 26385 | Q95: =_xlfn.XLOOKUP(O95,dimColaborador!A:A,dimColaborador!C:C,) -> GC - MÉDIO/GRANDE PORTE - SUL | R95: =_xlfn.XLOOKUP(O95,dimColaborador!A:A,dimColaborador!D:D) -> GRANDES CONTAS | S95: MARINGÁ | T95: 01 APARTAMENTO STANDARD DUPLO : CAMA CASAL DBD - 18/08/25 a | U95: 45887 | V95: 45888 | W95: 4000 | X95: 482789 | Y95: 266.67 | Z95: 8 | AA95: 0 | AB95: 274.67
A96: 45889 | B96: 52557 | C96: 6932 | D96: HTL | E96: OMNIBEES | F96: =_xlfn.XLOOKUP(E96,DEPARA!A:A,DEPARA!C:C,"Verificar") -> HOSPEDAGEM | G96: FIRSTLAB IND. IMP. E EXP. DE PROD. PARA LAB. LTDA | H96: 049-EQUIPE COMERCIAL 1 | I96: =_xlfn.XLOOKUP(fatoG1[[#This Row],[Centro de Custo]],dimCentroCusto[Centro_Custo],dimCentroCusto[Codigo_CentroCusto]) -> #N/A | J96: =fatoG1[[#This Row],[Desc. C. Custo Cliente]] -> 049-EQUIPE COMERCIAL 1 | N96: SCALON/AMANDA | O96: =_xlfn.XLOOKUP(N96,DEPARA!F:F,DEPARA!H:H,0) -> AMANDA BRANCHER SCALON | P96: =_xlfn.XLOOKUP(O96,dimColaborador!A:A,dimColaborador!B:B,0) -> 8254 | Q96: =_xlfn.XLOOKUP(O96,dimColaborador!A:A,dimColaborador!C:C,) -> SUPERVISORA EXTERNA FIRSTLAB | R96: =_xlfn.XLOOKUP(O96,dimColaborador!A:A,dimColaborador!D:D) -> SUPERVISORA EXTERNA FIRSTLAB | S96: SAO PAULO | T96: 01 SUÍTE CAMA CASAL - 19/08/25 a 20/08/25 | U96: 45888 | V96: 45889 | W96: RES0 | X96: 06942- | Y96: 243.32 | Z96: 0 | AA96: 0 | AB96: 243.32
A97: 45889 | B97: 52558 | C97: 6932 | D97: HTL | E97: OMNIBEES | F97: =_xlfn.XLOOKUP(E97,DEPARA!A:A,DEPARA!C:C,"Verificar") -> HOSPEDAGEM | G97: FIRSTLAB IND. IMP. E EXP. DE PROD. PARA LAB. LTDA | H97: 049-EQUIPE COMERCIAL 1 | I97: =_xlfn.XLOOKUP(fatoG1[[#This Row],[Centro de Custo]],dimCentroCusto[Centro_Custo],dimCentroCusto[Codigo_CentroCusto]) -> #N/A | J97: =fatoG1[[#This Row],[Desc. C. Custo Cliente]] -> 049-EQUIPE COMERCIAL 1 | N97: VAZ/LETICIA | O97: =_xlfn.XLOOKUP(N97,DEPARA!F:F,DEPARA!H:H,0) -> LETICIA CAMPOS DA SILVA VAZ | P97: =_xlfn.XLOOKUP(O97,dimColaborador!A:A,dimColaborador!B:B,0) -> 26385 | Q97: =_xlfn.XLOOKUP(O97,dimColaborador!A:A,dimColaborador!C:C,) -> GC - MÉDIO/GRANDE PORTE - SUL | R97: =_xlfn.XLOOKUP(O97,dimColaborador!A:A,dimColaborador!D:D) -> GRANDES CONTAS | S97: SAO PAULO | T97: 01 SUÍTE CAMA CASAL - 19/08/25 a 20/08/25 | U97: 45888 | V97: 45889 | W97: RES0 | X97: 06914- | Y97: 243.32 | Z97: 0 | AA97: 0 | AB97: 243.32
A98: 45891 | B98: 52847 | C98: 6932 | D98: CAR | E98: MOVIDA RENT A CAR | F98: =_xlfn.XLOOKUP(E98,DEPARA!A:A,DEPARA!C:C,"Verificar") -> LOCAÇÃO DE VEÍCULOS | G98: FIRSTLAB IND. IMP. E EXP. DE PROD. PARA LAB. LTDA | H98: 056-EQUIPE COMERCIAL 4 | I98: =_xlfn.XLOOKUP(fatoG1[[#This Row],[Centro de Custo]],dimCentroCusto[Centro_Custo],dimCentroCusto[Codigo_CentroCusto]) -> #N/A | J98: =fatoG1[[#This Row],[Desc. C. Custo Cliente]] -> 056-EQUIPE COMERCIAL 4 | N98: GONCALVES/THIAGO NARCISO OLIVEIRA | O98: =_xlfn.XLOOKUP(N98,DEPARA!F:F,DEPARA!H:H,0) -> THIAGO NARCISO OLIVEIRA GONÇALVES | P98: =_xlfn.XLOOKUP(O98,dimColaborador!A:A,dimColaborador!B:B,0) -> 26516 | Q98: =_xlfn.XLOOKUP(O98,dimColaborador!A:A,dimColaborador!C:C,) -> DR - PRIME - CENTRO OESTE | R98: =_xlfn.XLOOKUP(O98,dimColaborador!A:A,dimColaborador!D:D) -> DISTRIBUIDOR | S98: CURITIBA | T98: 15/07/25 a 16/07/25 - MOBI LIKE (1.0) OU SIMILAR/ 2/4 PORTAS | U98: 45853 | V98: 45854 | W98: 2118 | X98: 700420 | Y98: 301.89 | Z98: 45.28 | AA98: 0 | AB98: 347.17
A99: 45891 | B99: 53385 | C99: 6932 | D99: CAR | E99: UNIDAS | F99: =_xlfn.XLOOKUP(E99,DEPARA!A:A,DEPARA!C:C,"Verificar") -> LOCAÇÃO DE VEÍCULOS | G99: FIRSTLAB IND. IMP. E EXP. DE PROD. PARA LAB. LTDA | H99: 056-EQUIPE COMERCIAL 4 | I99: =_xlfn.XLOOKUP(fatoG1[[#This Row],[Centro de Custo]],dimCentroCusto[Centro_Custo],dimCentroCusto[Codigo_CentroCusto]) -> #N/A | J99: =fatoG1[[#This Row],[Desc. C. Custo Cliente]] -> 056-EQUIPE COMERCIAL 4 | N99: ALMEIDA/KHARLA NAYARA ABRANTES | O99: =_xlfn.XLOOKUP(N99,DEPARA!F:F,DEPARA!H:H,0) -> KHARLA NAYARA ABRANTES DE ALMEIDA | P99: =_xlfn.XLOOKUP(O99,dimColaborador!A:A,dimColaborador!B:B,0) -> 26175 | Q99: =_xlfn.XLOOKUP(O99,dimColaborador!A:A,dimColaborador!C:C,) -> GC -MÉDIO/GRANDE PORTE - NO/NE | R99: =_xlfn.XLOOKUP(O99,dimColaborador!A:A,dimColaborador!D:D) -> GRANDES CONTAS | S99: CURITIBA | T99: 23/07/25 a 25/07/25 - FIAT ARGO, CHEVROLET ONIX, VW GOL (1. | U99: 45861 | V99: 45863 | W99: 2118 | X99: 733853 | Y99: 383 | Z99: 0 | AA99: 0 | AB99: 383
A100: 45891 | B100: 53679 | C100: 6932 | D100: HTL | E100: LAGO DA PALMA | F100: =_xlfn.XLOOKUP(E100,DEPARA!A:A,DEPARA!C:C,"Verificar") -> HOSPEDAGEM | G100: FIRSTLAB IND. IMP. E EXP. DE PROD. PARA LAB. LTDA | H100: 056-EQUIPE COMERCIAL 4 | I100: =_xlfn.XLOOKUP(fatoG1[[#This Row],[Centro de Custo]],dimCentroCusto[Centro_Custo],dimCentroCusto[Codigo_CentroCusto]) -> #N/A | J100: =fatoG1[[#This Row],[Desc. C. Custo Cliente]] -> 056-EQUIPE COMERCIAL 4 | L100: PROSPECTAR REGIÃO | N100: ALMEIDA/KHARLA NAYARA ABRANTES | O100: =_xlfn.XLOOKUP(N100,DEPARA!F:F,DEPARA!H:H,0) -> KHARLA NAYARA ABRANTES DE ALMEIDA | P100: =_xlfn.XLOOKUP(O100,dimColaborador!A:A,dimColaborador!B:B,0) -> 26175 | Q100: =_xlfn.XLOOKUP(O100,dimColaborador!A:A,dimColaborador!C:C,) -> GC -MÉDIO/GRANDE PORTE - NO/NE | R100: =_xlfn.XLOOKUP(O100,dimColaborador!A:A,dimColaborador!D:D) -> GRANDES CONTAS | S100: PALMAS | T100: 01 QUARTO CASAL ECONÔMICO - 19/08/25 a 22/08/25 | U100: 45888 | V100: 45891 | W100: 4000 | X100: 566593 | Y100: 710.04 | Z100: 0 | AA100: 0 | AB100: 710.04
...

Sheet DEPARA
A1: De | C1: Para - Despesas | F1: De | H1: Para - Colaboradores | K1: De | M1: Para - Centro de Custo
A2: UNIDAS | C2: LOCAÇÃO DE VEÍCULOS | F2: LUZ/MARCIO ARRUDA | H2: MARCIO ARRUDA LUZ | K2: 055-EQUIPE COMERCIAL 3 | M2: Comercial
A3: SCALA RESIDENCE HOTEL | C3: HOSPEDAGEM | F3: MARCIO ARRUDA LUZ | H3: MARCIO ARRUDA LUZ | K3: 048-COMERCIAL INTERNO | M3: Comercial
A4: FENIX POUSO ALEGRE HOTEL | C4: HOSPEDAGEM | F4: GONCALVES/THIAGO NARCISO OLIVEIRA | H4: THIAGO NARCISO OLIVEIRA GONÇALVES | K4: 056-EQUIPE COMERCIAL 4 | M4: Comercial
A5: HOTEL DO PAPAI NOEL | C5: HOSPEDAGEM | F5: ALMEIDA/KHARLA NAYARA ABRANTES | H5: KHARLA NAYARA ABRANTES DE ALMEIDA | K5: 049-EQUIPE COMERCIAL 1 | M5: Comercial
A6: INTERCITY CURITIBA CENTRO CIVICO | C6: HOSPEDAGEM | F6: PEREIRA/FELIPE LUIZ RIBEIRO | H6: FELIPE LUIZ RIBEIRO PEREIRA | K6: 054-EQUIPE COMERCIAL 2 | M6: Comercial
A7: IBIS STYLES GOIANIA SHOPPING ESTACAO | C7: HOSPEDAGEM | F7: NAYARA ABRANTES DE ALMEIDA/KHARLA | H7: KHARLA NAYARA ABRANTES DE ALMEIDA | K7: 10-PRODUÇÃO | M7: Produção
A8: BRISA TOWER BRASILIA HOTEL | C8: HOSPEDAGEM | F8: OLIVEIRA/JOANA MARIA TEIXEIRA DE | H8: JOANA MARIA TEIXEIRA DE OLIVEIRA
A9: HOTEL NACIONAL DE RIO PRETO | C9: HOSPEDAGEM | F9: MARIA TEIXEIRA DE OLIVEIRA/JOANA | H9: JOANA MARIA TEIXEIRA DE OLIVEIRA
A10: GOL LINHAS AÉREAS | C10: PASSAGEM | F10: VAZ/LETICIA CAMPOS DA SILVA | H10: LETICIA CAMPOS DA SILVA VAZ
A11: TAM LINHAS AÉREAS | C11: PASSAGEM | F11: VAZ/LETICIA | H11: LETICIA CAMPOS DA SILVA VAZ
A12: AZUL LINHAS AÉREAS BRASILEIRAS | C12: PASSAGEM | F12: NARCISO OLIVEIRA GONCALVES/THIAGO | H12: THIAGO NARCISO OLIVEIRA GONÇALVES
A13: MOVIDA RENT A CAR | C13: LOCAÇÃO DE VEÍCULOS | F13: LETICIA CAMPOS DA SILVA VAZ | H13: LETICIA CAMPOS DA SILVA VAZ
A14: NORTH HOTEL | C14: HOSPEDAGEM | F14: NUEVO/IGOR MARIANO | H14: IGOR MARIANO NUEVO
A15: OMNIBEES | C15: HOSPEDAGEM | F15: THIAGO NARCISO OLIVEIRA GONCALVES | H15: THIAGO NARCISO OLIVEIRA GONÇALVES
A16: TRANSAMERICA FIT VITÓRIA RETA DA PENHA | C16: HOSPEDAGEM | F16: SANTOS/LAURA | H16: LAURA BENTO DOS SANTOS
A17: HOTEL SANTA CRUZ | C17: HOSPEDAGEM | F17: SHINKAI/RAQUEL AICO | H17: RAQUEL AICO SHINKAI
A18: TRI HOTEL SMART CAXIAS | C18: HOSPEDAGEM | F18: RAQUEL AICO SHINKAI | H18: RAQUEL AICO SHINKAI
A19: IBIS STYLES PORTO ALEGRE CENTRO | C19: HOSPEDAGEM | F19: SCALON/AMANDA | H19: AMANDA BRANCHER SCALON
... A50: GOLDMEN BUSINESS CRICIÚMA | C50: HOSPEDAGEM | F50: FARIA GASPARIN/JULIANA | H50: JULIANA FARIA GASPARIN
A51: AERA SAO JOSE FLORIPA | C51: HOSPEDAGEM
A52: HOTEL PORTO SOL INGLESES | C52: HOSPEDAGEM
A53: PREMIER SAO LUIS | C53: HOSPEDAGEM
A54: VIA PARK TERRA HOSPEDAGEM | C54: HOSPEDAGEM
A55: HOTEL MINUANO | C55: HOSPEDAGEM
A56: DUBAI MACAÉ BY ATLANTICA | C56: HOSPEDAGEM
A57: SAN JUAN TOUR FOZ HOTEL | C57: HOSPEDAGEM
A58: PLAZA CASCAVEL HOTEL | C58: HOSPEDAGEM
A59: HOTEL IPIRANGA MARINGA | C59: HOSPEDAGEM
A60: NATIVO HOTEL | C60: HOSPEDAGEM
A61: APÊ BROOKLIN BERRINI | C61: HOSPEDAGEM
A62: IBIS CURITIBA AEROPORTO | C62: HOSPEDAGEM
... A92: QATAR AIRWAYS | C92: PASSAGEM

Sheet Faturamento
A1: fatoFaturamento[Data Emissão] | B1: dimCanal[Sub-região_ajustada] | C1: dimConsiderar[Considerar] | D1: [SumValor_Total_Líquido]
A2: 43203 | B2: DR - STANDARD - SUL | D2: 9594.38
A3: 43230 | B3: DR - STANDARD - SUL | C3: Considerar | D3: 65.76
A4: 43257 | B4: DR - STANDARD - SUL | C4: Considerar | D4: 14.14
A5: 43269 | B5: DR - STANDARD - SUL | D5: 700000
A6: 43276 | B6: DR - STANDARD - SUL | D6: 13755
A7: 43280 | B7: DR - STANDARD - SUL | D7: 30000
A8: 43311 | B8: DR - STANDARD - SUL | D8: 13100
A9: 43346 | B9: DR - STANDARD - SUL | C9: Considerar | D9: 15.4
A10: 43362 | B10: DR - PRIME - SUL | C10: Considerar | D10: 8498
A11: 43369 | B11: DR - STANDARD - NORTE | C11: Considerar | D11: 6392
A12: 43370 | B12: OUTROS | D12: 7861.12
A13: 43381 | B13: DR - STANDARD - CENTRO OESTE | C13: Considerar | D13: 1041
A14: 43384 | B14: DR - STANDARD - SUDESTE | C14: Considerar | D14: 900
A15: 43384 | B15: OUTROS | C15: Considerar | D15: 316.46
A16: 43390 | B16: DR - STANDARD - CENTRO OESTE | C16: Considerar | D16: 1354
A17: 43395 | B17: DR - STANDARD - SP | C17: Considerar | D17: 98.7
A18: 43395 | B18: DR - STANDARD - SUL | C18: Considerar | D18: 1001.4
A19: 43398 | B19: DR - STANDARD - SP | D19: 19.74
A20: 43404 | B20: DR - STANDARD - SP | D20: 17.21
A21: 43405 | B21: DR - STANDARD - SP | D21: 78.96
A22: 43405 | B22: DR - STANDARD - SP | C22: Considerar | D22: 7500
A23: 43405 | B23: DR - STANDARD - SUL | C23: Considerar | D23: 1650
A24: 43410 | B24: DR - STANDARD - SP | C24: Considerar | D24: 1350
A25: 43411 | B25: DR - STANDARD - NORTE | C25: Considerar | D25: 1655
A26: 43411 | B26: DR - STANDARD - SUL | C26: Considerar | D26: 177.7
A27: 43412 | B27: DR - PRIME - SUDESTE | C27: Considerar | D27: 1008
A28: 43413 | B28: DR - STANDARD - SP | D28: 20
A29: 43413 | B29: DR - STANDARD - SP | C29: Considerar | D29: 246.58
A30: 43413 | B30: OUTROS | C30: Considerar | D30: 1260
A31: 43416 | B31: DR - STANDARD - SUL | C31: Considerar | D31: 58
A32: 43417 | B32: DR - PRIME - SUDESTE | C32: Considerar | D32: 1200
A33: 43417 | B33: DR - STANDARD - NORDESTE | C33: Considerar | D33: 916.8
A34: 43417 | B34: DR - STANDARD - SUDESTE | C34: Considerar | D34: 179.8
A35: 43417 | B35: OUTROS | C35: Considerar | D35: 899
A36: 43420 | B36: DR - PRIME - NORDESTE | C36: Considerar | D36: 911.4
A37: 43420 | B37: DR - STANDARD - NORDESTE | C37: Considerar | D37: 3720
A38: 43420 | B38: DR - STANDARD - SUDESTE | C38: Considerar | D38: 1040
A39: 43424 | B39: LPC - EDITAIS | D39: 22
A40: 43427 | B40: CF - PEQUENO PORTE - NO/NE | C40: Considerar | D40: 801.3
A41: 43427 | B41: DR - PRIME - SP | C41: Considerar | D41: 6000
A42: 43427 | B42: DR - STANDARD - SUDESTE | D42: 17.35
A43: 43427 | B43: DR - STANDARD - SUDESTE | C43: Considerar | D43: 396.9
A44: 43430 | B44: DR - PRIME - SUDESTE | C44: Considerar | D44: 886.8
A45: 43430 | B45: DR - PRIME - SUL | C45: Considerar | D45: 2800
A46: 43430 | B46: DR - STANDARD - NORTE | C46: Considerar | D46: 96.31
A47: 43430 | B47: DR - STANDARD - SUDESTE | D47: 18
A48: 43433 | B48: DR - STANDARD - CENTRO OESTE | C48: Considerar | D48: 778.5
A49: 43433 | B49: DR - STANDARD - NORDESTE | C49: Considerar | D49: 1132.74
A50: 43433 | B50: DR - STANDARD - SUDESTE | C50: Considerar | D50: 860
A51: 43434 | B51: DR - PRIME - SUDESTE | C51: Considerar | D51: 700
A52: 43434 | B52: DR - STANDARD - SP | C52: Considerar | D52: 1817.5
A53: 43437 | B53: DR - PRIME - SUDESTE | C53: Considerar | D53: 1008
A54: 43437 | B54: DR - STANDARD - SUL | C54: Considerar | D54: 156.8
A55: 43438 | B55: DR - STANDARD - SUDESTE | C55: Considerar | D55: 812.8
A56: 43439 | B56: DR - STANDARD - SUDESTE | C56: Considerar | D56: 9912.8
A57: 43441 | B57: DR - STANDARD - CENTRO OESTE | D57: 15.12
A58: 43441 | B58: DR - STANDARD - NORDESTE | D58: 31.11
A59: 43441 | B59: DR - STANDARD - NORDESTE | C59: Considerar | D59: 611.2
A60: 43441 | B60: OUTROS | D60: 10999
A61: 43444 | B61: DR - PRIME - SUL | C61: Considerar | D61: 3470
A62: 43445 | B62: DR - PRIME - SUL | C62: Considerar | D62: 2337
A63: 43445 | B63: DR - STANDARD - NORDESTE | D63: 15.98
A64: 43446 | B64: DR - STANDARD - NORDESTE | C64: Considerar | D64: 1383.58
A65: 43447 | B65: DR - STANDARD - SUDESTE | C65: Considerar | D65: 1386.1
A66: 43452 | B66: DR - STANDARD - SUDESTE | C66: Considerar | D66: 251.4
A67: 43452 | B67: OUTROS | D67: 19512.8
A68: 43452 | B68: OUTROS | C68: Considerar | D68: 622.8
A69: 43454 | B69: DR - STANDARD - NORDESTE | C69: Considerar | D69: 1445
A70: 43455 | B70: DR - STANDARD - NORDESTE | C70: Considerar | D70: 3503.2
A71: 43461 | B71: DR - STANDARD - SP | C71: Considerar | D71: 1717
A72: 43461 | B72: DR - STANDARD - SUL | D72: 695
A73: 43462 | B73: DR - STANDARD - SUL | D73: 2151.5
A74: 43462 | B74: OUTROS | D74: 52.37
A75: 43462 | B75: OUTROS | C75: Considerar | D75: 752
A76: 43467 | B76: DR - STANDARD - NORTE | C76: Considerar | D76: 1527.76
A77: 43469 | B77: DR - PRIME - SUDESTE | C77: Considerar | D77: 1350
A78: 43469 | B78: LPC - EDITAIS | D78: 23
A79: 43472 | B79: DR - PRIME - SUL | C79: Considerar | D79: 4776
A80: 43472 | B80: DR - STANDARD - CENTRO OESTE | C80: Considerar | D80: 688.4
A81: 43472 | B81: DR - STANDARD - SUDESTE | C81: Considerar | D81: 1175.5
A82: 43473 | B82: DR - STANDARD - NORDESTE | C82: Considerar | D82: 34
A83: 43473 | B83: OUTROS | C83: Considerar | D83: 899
A84: 43474 | B84: DR - STANDARD - SP | C84: Considerar | D84: 1681.7
A85: 43476 | B85: DR - PRIME - NORDESTE | C85: Considerar | D85: 1829
A86: 43476 | B86: DR - STANDARD - NORDESTE | C86: Considerar | D86: 510
A87: 43476 | B87: DR - STANDARD - SP | D87: 20.6
A88: 43476 | B88: DR - STANDARD - SUDESTE | C88: Considerar | D88: 1997.18
A89: 43476 | B89: GC -MÉDIO/GRANDE PORTE - NO/NE | C89: Considerar | D89: 1980.79
A90: 43479 | B90: DR - STANDARD - SUDESTE | C90: Considerar | D90: 609.6
A91: 43479 | B91: DR - STANDARD - SUL | C91: Considerar | D91: 800
A92: 43481 | B92: DR - STANDARD - SUDESTE | D92: 251.4
A93: 43481 | B93: DR - STANDARD - SUDESTE | C93: Considerar | D93: 361
A94: 43482 | B94: DR - PRIME - NORDESTE | C94: Considerar | D94: 2239.9
A95: 43483 | B95: DR - STANDARD - SP | C95: Considerar | D95: 687.4
A96: 43483 | B96: DR - STANDARD - SUDESTE | C96: Considerar | D96: 2800
A97: 43486 | B97: DR - STANDARD - CENTRO OESTE | C97: Considerar | D97: 4113
A98: 43487 | B98: DR - PRIME - SP | C98: Considerar | D98: 1008.16
A99: 43487 | B99: DR - STANDARD - NORDESTE | C99: Considerar | D99: 1838
A100: 43488 | B100: DR - STANDARD - NORDESTE | C100: Considerar | D100: 285.6
...

Sheet dimsubRegião
A1: Sub-região_ajustada
A2: DR - STANDARD - SUL
A3: DR - PRIME - SUL
A4: DR - STANDARD - NORTE
A5: OUTROS
A6: DR - STANDARD - CENTRO OESTE
A7: DR - STANDARD - SUDESTE
A8: DR - STANDARD - SP
A9: DR - PRIME - SUDESTE
A10: DR - STANDARD - NORDESTE
A11: DR - PRIME - NORDESTE
A12: LPC - EDITAIS
... A32: LPC - PROJETOS
